Workbook

Sheet Vendas 2026 - APP
A1: Data | B1: CPF | C1: Cliente | D1: Nome do Cliente Emissor Bemol On-line | E1: Endereço de e-mail | F1: Data de Nascimento | G1: Categoria do Bemol Run | H1: Modalidades do Bemol Run | I1: Bemol Run Genero | J1: Tamanho das camisetas | K1: Tipo de pagamento | L1: Valor do Pedido | M1: Status | N1: EventId | O1: Evento
A2: 46140 | B2: 03638638260 | C2: 2436398 | D2: RAFAEL RIBEIRO BATISTA | E2: rafael37qq@gmail.com | F2: 35501 | G2: GERAL | H2: 5KM | I2: M | J2: GG | K2: CB | L2: 129.9 | M2: INSCRITO | N2: bemol-run-mao-2026_1 | O2: =IF(N2="bemol-run-mao-2026_1", "Manaus", IF(N2="bemol-run-rbr-2026_1", "Rio Branco", IF(N2="bemol-run-pvh-2026_1", "Porto Velho", IF(N2="bemol-run-bvb-2026_1", "Boa Vista", N2)))) -> Manaus
A3: 46140 | B3: 83484965215 | C3: 3697815 | D3: ROMULO HENRIQUE DA SILVA LIMA | E3: iromulo181@gmail.com | F3: 30999 | G3: GERAL | H3: 5KM | I3: F | J3: XG | K3: CB | L3: 129.9 | M3: INSCRITO | N3: bemol-run-mao-2026_1 | O3: =IF(N3="bemol-run-mao-2026_1", "Manaus", IF(N3="bemol-run-rbr-2026_1", "Rio Branco", IF(N3="bemol-run-pvh-2026_1", "Porto Velho", IF(N3="bemol-run-bvb-2026_1", "Boa Vista", N3)))) -> Manaus
A4: 46140 | B4: 96365862253 | C4: 2038651 | D4: ALESSANDRA DE LIMA OLIVEIRA | E4: alessandralima711@gmail.com | F4: 32787 | G4: GERAL | H4: 5KM | I4: F | J4: M | K4: CB | L4: 129.9 | M4: INSCRITO | N4: bemol-run-mao-2026_1 | O4: =IF(N4="bemol-run-mao-2026_1", "Manaus", IF(N4="bemol-run-rbr-2026_1", "Rio Branco", IF(N4="bemol-run-pvh-2026_1", "Porto Velho", IF(N4="bemol-run-bvb-2026_1", "Boa Vista", N4)))) -> Manaus
A5: 46140 | B5: 03114208266 | C5: 2433958 | D5: RUAN CARLOS SANTOS PANTOJA | E5: carlosruanruan@outlook.com | F5: 35815 | G5: GERAL | H5: 10KM | I5: F | J5: PP | K5: CB | L5: 149.9 | M5: INSCRITO | N5: bemol-run-mao-2026_1 | O5: =IF(N5="bemol-run-mao-2026_1", "Manaus", IF(N5="bemol-run-rbr-2026_1", "Rio Branco", IF(N5="bemol-run-pvh-2026_1", "Porto Velho", IF(N5="bemol-run-bvb-2026_1", "Boa Vista", N5)))) -> Manaus
A6: 46140 | B6: 01949743241 | C6: 1903972 | D6: JULLYENNE LIMA CAMPELO | E6: jullyennelima.campelo@gmail.com | F6: 34438 | G6: COLAB | H6: 5KM | I6: F | J6: G | K6: CB | L6: 129.9 | M6: INSCRITO | N6: bemol-run-mao-2026_1 | O6: =IF(N6="bemol-run-mao-2026_1", "Manaus", IF(N6="bemol-run-rbr-2026_1", "Rio Branco", IF(N6="bemol-run-pvh-2026_1", "Porto Velho", IF(N6="bemol-run-bvb-2026_1", "Boa Vista", N6)))) -> Manaus
A7: 46140 | B7: 02746108259 | C7: 2068839 | D7: LETICIA DA SILVA | E7: leticiasilv0901@gmail.com | F7: 35073 | G7: GERAL | H7: 5KM | I7: F | J7: XG | K7: CB | L7: 129.9 | M7: INSCRITO | N7: bemol-run-mao-2026_1 | O7: =IF(N7="bemol-run-mao-2026_1", "Manaus", IF(N7="bemol-run-rbr-2026_1", "Rio Branco", IF(N7="bemol-run-pvh-2026_1", "Porto Velho", IF(N7="bemol-run-bvb-2026_1", "Boa Vista", N7)))) -> Manaus
A8: 46140 | B8: 92009735234 | C8: 1287641 | D8: BIANCA BITENCOURT DA ROCHA | E8: biancabittencourtt@gmail.com | F8: 32997 | G8: COLAB | H8: 5KM | I8: F | J8: P | K8: PIX | L8: 129.9 | M8: INSCRITO | N8: bemol-run-mao-2026_1 | O8: =IF(N8="bemol-run-mao-2026_1", "Manaus", IF(N8="bemol-run-rbr-2026_1", "Rio Branco", IF(N8="bemol-run-pvh-2026_1", "Porto Velho", IF(N8="bemol-run-bvb-2026_1", "Boa Vista", N8)))) -> Manaus
A9: 46140 | B9: 44128177253 | C9: 202062 | D9: DRAYTON HELIO GUERRA DA SILVA | E9: draytonguerra@gmail.com | F9: 26549 | G9: GERAL | H9: 5KM | I9: M | J9: G | K9: CB | L9: 129.9 | M9: INSCRITO | N9: bemol-run-mao-2026_1 | O9: =IF(N9="bemol-run-mao-2026_1", "Manaus", IF(N9="bemol-run-rbr-2026_1", "Rio Branco", IF(N9="bemol-run-pvh-2026_1", "Porto Velho", IF(N9="bemol-run-bvb-2026_1", "Boa Vista", N9)))) -> Manaus
A10: 46140 | B10: 05245774208 | C10: 3897134 | D10: TAINARA CRUZ DA SILVA | E10: taycruz424242@gmail.com | F10: 37158 | G10: COLAB | H10: 5KM | I10: F | J10: M | K10: CB | L10: 129.9 | M10: INSCRITO | N10: bemol-run-mao-2026_1 | O10: =IF(N10="bemol-run-mao-2026_1", "Manaus", IF(N10="bemol-run-rbr-2026_1", "Rio Branco", IF(N10="bemol-run-pvh-2026_1", "Porto Velho", IF(N10="bemol-run-bvb-2026_1", "Boa Vista", N10)))) -> Manaus
A11: 46140 | B11: 00553147242 | C11: 1311577 | D11: LIDIANE MUNHOZ DA SILVEIRA | E11: lidiane.msilveira@hotmail.com | F11: 33229 | G11: GERAL | H11: 5KM | I11: F | J11: P | K11: CB | L11: 129.9 | M11: INSCRITO | N11: bemol-run-mao-2026_1 | O11: =IF(N11="bemol-run-mao-2026_1", "Manaus", IF(N11="bemol-run-rbr-2026_1", "Rio Branco", IF(N11="bemol-run-pvh-2026_1", "Porto Velho", IF(N11="bemol-run-bvb-2026_1", "Boa Vista", N11)))) -> Manaus
A12: 46140 | B12: 00820537233 | D12: GUSTAVO DE ALMEIDA COSTA | E12: gustavocostaalmeida@gmail.com | F12: 35720 | G12: COLAB | H12: 5KM | I12: M | J12: G | K12: PIX | L12: 129.9 | M12: CANCELADO | N12: bemol-run-mao-2026_1 | O12: =IF(N12="bemol-run-mao-2026_1", "Manaus", IF(N12="bemol-run-rbr-2026_1", "Rio Branco", IF(N12="bemol-run-pvh-2026_1", "Porto Velho", IF(N12="bemol-run-bvb-2026_1", "Boa Vista", N12)))) -> Manaus
A13: 46140 | B13: 11658580613 | D13: TAIANNE VALERIE ALVES MOTTA | E13: taiannemotta@gmail.com | F13: 35011 | G13: COLAB | H13: 10KM | I13: M | J13: M | K13: PIX | L13: 129.9 | M13: CANCELADO | N13: bemol-run-rbr-2026_1 | O13: =IF(N13="bemol-run-mao-2026_1", "Manaus", IF(N13="bemol-run-rbr-2026_1", "Rio Branco", IF(N13="bemol-run-pvh-2026_1", "Porto Velho", IF(N13="bemol-run-bvb-2026_1", "Boa Vista", N13)))) -> Rio Branco
A14: 46140 | B14: 07548772211 | C14: 4673140 | D14: JOELSON SILVA MARTINS | E14: mjoelson.martins22@gmail.com | F14: 38409 | G14: GERAL | H14: 10KM | I14: M | J14: G | K14: CB | L14: 129.9 | M14: INSCRITO | N14: bemol-run-mao-2026_1 | O14: =IF(N14="bemol-run-mao-2026_1", "Manaus", IF(N14="bemol-run-rbr-2026_1", "Rio Branco", IF(N14="bemol-run-pvh-2026_1", "Porto Velho", IF(N14="bemol-run-bvb-2026_1", "Boa Vista", N14)))) -> Manaus
A15: 46140 | B15: 00589689207 | C15: 1747043 | D15: AIMEE GOMES DA PENHA MARIA | E15: aimeegpm@gmail.com | F15: 32910 | G15: COLAB | H15: 10KM | I15: F | J15: P | K15: PIX | L15: 129.9 | M15: INSCRITO | N15: bemol-run-mao-2026_1 | O15: =IF(N15="bemol-run-mao-2026_1", "Manaus", IF(N15="bemol-run-rbr-2026_1", "Rio Branco", IF(N15="bemol-run-pvh-2026_1", "Porto Velho", IF(N15="bemol-run-bvb-2026_1", "Boa Vista", N15)))) -> Manaus
A16: 46140 | B16: 70063771292 | C16: 2508055 | D16: MARCOS SOUZA DIAS | E16: marcossouzadias.50@gmail.com | F16: 36308 | G16: GERAL | H16: 5KM | I16: M | J16: M | K16: CB | L16: 129.9 | M16: INSCRITO | N16: bemol-run-mao-2026_1 | O16: =IF(N16="bemol-run-mao-2026_1", "Manaus", IF(N16="bemol-run-rbr-2026_1", "Rio Branco", IF(N16="bemol-run-pvh-2026_1", "Porto Velho", IF(N16="bemol-run-bvb-2026_1", "Boa Vista", N16)))) -> Manaus
A17: 46140 | B17: 70529494230 | C17: 4366151 | D17: KIMBERLY MORAES RIBEIRO | E17: kimberlyribeiro678@gmail.com | F17: 37672 | G17: GERAL | H17: 5KM | I17: F | J17: PP | K17: PIX | L17: 129.9 | M17: INSCRITO | N17: bemol-run-mao-2026_1 | O17: =IF(N17="bemol-run-mao-2026_1", "Manaus", IF(N17="bemol-run-rbr-2026_1", "Rio Branco", IF(N17="bemol-run-pvh-2026_1", "Porto Velho", IF(N17="bemol-run-bvb-2026_1", "Boa Vista", N17)))) -> Manaus
A18: 46140 | B18: 02626761257 | D18: VINICIUS FONTOURA BATISTA | E18: viniciusfontourabatista@hotmail.com | F18: 36711 | G18: GERAL | H18: 10KM | I18: M | J18: M | K18: PIX | L18: 149.9 | M18: CANCELADO | N18: bemol-run-pvh-2026_1 | O18: =IF(N18="bemol-run-mao-2026_1", "Manaus", IF(N18="bemol-run-rbr-2026_1", "Rio Branco", IF(N18="bemol-run-pvh-2026_1", "Porto Velho", IF(N18="bemol-run-bvb-2026_1", "Boa Vista", N18)))) -> Porto Velho
A19: 46140 | B19: 85886181253 | C19: 1134138 | D19: ARGELLY ZAIDEM SANTANA DOS SANTOS | E19: argellyzaidem@bemol.com.br | F19: 31290 | G19: COLAB | H19: 5KM | I19: F | J19: P | K19: CB | L19: 129.9 | M19: INSCRITO | N19: bemol-run-mao-2026_1 | O19: =IF(N19="bemol-run-mao-2026_1", "Manaus", IF(N19="bemol-run-rbr-2026_1", "Rio Branco", IF(N19="bemol-run-pvh-2026_1", "Porto Velho", IF(N19="bemol-run-bvb-2026_1", "Boa Vista", N19)))) -> Manaus
A20: 46140 | B20: 02899967240 | D20: ANTONIO ALBERTO DE SOUZA BARBOSA | E20: antonioalbertodsb@gmail.com | F20: 36346 | G20: COLAB | H20: 10KM | I20: F | J20: G | K20: PIX | L20: 129.9 | M20: CANCELADO | N20: bemol-run-bvb-2026_1 | O20: =IF(N20="bemol-run-mao-2026_1", "Manaus", IF(N20="bemol-run-rbr-2026_1", "Rio Branco", IF(N20="bemol-run-pvh-2026_1", "Porto Velho", IF(N20="bemol-run-bvb-2026_1", "Boa Vista", N20)))) -> Boa Vista
A21: 46140 | B21: 02949034292 | D21: KATIANE AMARANTE CABRAL | E21: katiiane.cabral@gmail.com | F21: 36159 | G21: GERAL | H21: 5KM | I21: F | J21: PP | K21: PIX | L21: 149.9 | M21: CANCELADO | N21: bemol-run-pvh-2026_1 | O21: =IF(N21="bemol-run-mao-2026_1", "Manaus", IF(N21="bemol-run-rbr-2026_1", "Rio Branco", IF(N21="bemol-run-pvh-2026_1", "Porto Velho", IF(N21="bemol-run-bvb-2026_1", "Boa Vista", N21)))) -> Porto Velho
A22: 46140 | B22: 75413639287 | C22: 2077277 | D22: MAURICIO XAVIER TEIXEIRA | E22: mauricioteixeira@bemol.com.br | F22: 30861 | G22: COLAB | H22: 5KM | I22: M | J22: M | K22: CB | L22: 129.9 | M22: INSCRITO | N22: bemol-run-mao-2026_1 | O22: =IF(N22="bemol-run-mao-2026_1", "Manaus", IF(N22="bemol-run-rbr-2026_1", "Rio Branco", IF(N22="bemol-run-pvh-2026_1", "Porto Velho", IF(N22="bemol-run-bvb-2026_1", "Boa Vista", N22)))) -> Manaus
A23: 46140 | B23: 00827504241 | D23: TIAGO ALMEIDA DOS SANTOS | E23: tiagoalmeida@bemol.com.br | F23: 36773 | G23: COLAB | H23: 10KM | I23: M | J23: PP | K23: PIX | L23: 129.9 | M23: CANCELADO | N23: bemol-run-mao-2026_1 | O23: =IF(N23="bemol-run-mao-2026_1", "Manaus", IF(N23="bemol-run-rbr-2026_1", "Rio Branco", IF(N23="bemol-run-pvh-2026_1", "Porto Velho", IF(N23="bemol-run-bvb-2026_1", "Boa Vista", N23)))) -> Manaus
A24: 46140 | B24: 03490528409 | D24: CHRISTIAN BARNADD DANNIELL GOMES E | E24: barnaddmanaus@gmail.com | F24: 29286 | G24: GERAL | H24: 5KM | I24: F | J24: PP | K24: PIX | L24: 149.9 | M24: CANCELADO | N24: bemol-run-bvb-2026_1 | O24: =IF(N24="bemol-run-mao-2026_1", "Manaus", IF(N24="bemol-run-rbr-2026_1", "Rio Branco", IF(N24="bemol-run-pvh-2026_1", "Porto Velho", IF(N24="bemol-run-bvb-2026_1", "Boa Vista", N24)))) -> Boa Vista
A25: 46140 | B25: 00820537233 | D25: GUSTAVO DE ALMEIDA COSTA | E25: gustavocostaalmeida@gmail.com | F25: 35720 | G25: COLAB | H25: 5KM | I25: M | J25: G | K25: PIX | L25: 129.9 | M25: CANCELADO | N25: bemol-run-pvh-2026_1 | O25: =IF(N25="bemol-run-mao-2026_1", "Manaus", IF(N25="bemol-run-rbr-2026_1", "Rio Branco", IF(N25="bemol-run-pvh-2026_1", "Porto Velho", IF(N25="bemol-run-bvb-2026_1", "Boa Vista", N25)))) -> Porto Velho
A26: 46140 | B26: 03281503209 | C26: 2214363 | D26: LICIANE MESQUITA FILGUEIRA | E26: licianeleandro2@gmail.com | F26: 35106 | G26: GERAL | H26: 10KM | I26: F | J26: M | K26: CB | L26: 129.9 | M26: INSCRITO | N26: bemol-run-mao-2026_1 | O26: =IF(N26="bemol-run-mao-2026_1", "Manaus", IF(N26="bemol-run-rbr-2026_1", "Rio Branco", IF(N26="bemol-run-pvh-2026_1", "Porto Velho", IF(N26="bemol-run-bvb-2026_1", "Boa Vista", N26)))) -> Manaus
A27: 46140 | B27: 03482573255 | D27: ANA PAULA CASSIANO DA SILVA | E27: mc.marmed@gmail.com | F27: 34588 | G27: GERAL | H27: 5KM | I27: F | J27: XG | K27: PIX | L27: 149.9 | M27: CANCELADO | N27: bemol-run-mao-2026_1 | O27: =IF(N27="bemol-run-mao-2026_1", "Manaus", IF(N27="bemol-run-rbr-2026_1", "Rio Branco", IF(N27="bemol-run-pvh-2026_1", "Porto Velho", IF(N27="bemol-run-bvb-2026_1", "Boa Vista", N27)))) -> Manaus
A28: 46140 | B28: 02875521284 | C28: 1889603 | D28: DANDARA ERENDIRA DE SOUZA | E28: dandara.ere@gmail.com | F28: 35324 | G28: COLAB | H28: 5KM | I28: M | J28: P | K28: CB | L28: 129.9 | M28: INSCRITO | N28: bemol-run-pvh-2026_1 | O28: =IF(N28="bemol-run-mao-2026_1", "Manaus", IF(N28="bemol-run-rbr-2026_1", "Rio Branco", IF(N28="bemol-run-pvh-2026_1", "Porto Velho", IF(N28="bemol-run-bvb-2026_1", "Boa Vista", N28)))) -> Porto Velho
A29: 46140 | B29: 03003024280 | C29: 4796339 | D29: IGOR KALIEL DE OLIVEIRA MARQUES | E29: igorkaliel6@gmail.com | F29: 38082 | G29: GERAL | H29: 5KM | I29: M | J29: P | K29: CB | L29: 129.9 | M29: INSCRITO | N29: bemol-run-pvh-2026_1 | O29: =IF(N29="bemol-run-mao-2026_1", "Manaus", IF(N29="bemol-run-rbr-2026_1", "Rio Branco", IF(N29="bemol-run-pvh-2026_1", "Porto Velho", IF(N29="bemol-run-bvb-2026_1", "Boa Vista", N29)))) -> Porto Velho
A30: 46140 | B30: 01615936238 | C30: 1743909 | D30: LETICIA RODRIGUES DE MELO | E30: la2057324@icloud.com | F30: 33399 | G30: GERAL | H30: 10KM | I30: F | J30: PP | K30: CB | L30: 129.9 | M30: INSCRITO | N30: bemol-run-pvh-2026_1 | O30: =IF(N30="bemol-run-mao-2026_1", "Manaus", IF(N30="bemol-run-rbr-2026_1", "Rio Branco", IF(N30="bemol-run-pvh-2026_1", "Porto Velho", IF(N30="bemol-run-bvb-2026_1", "Boa Vista", N30)))) -> Porto Velho
A31: 46140 | B31: 00842969250 | C31: 2088638 | D31: CHARLOTE MORAES BRACHER | E31: chachabracher@hotmail.com | F31: 32993 | G31: GERAL | H31: 5KM | I31: M | J31: M | K31: CB | L31: 149.9 | M31: INSCRITO | N31: bemol-run-mao-2026_1 | O31: =IF(N31="bemol-run-mao-2026_1", "Manaus", IF(N31="bemol-run-rbr-2026_1", "Rio Branco", IF(N31="bemol-run-pvh-2026_1", "Porto Velho", IF(N31="bemol-run-bvb-2026_1", "Boa Vista", N31)))) -> Manaus
A32: 46140 | B32: 02949034292 | C32: 3708453 | D32: KATIANE AMARANTE CABRAL | E32: katiiane.cabral@gmail.com | F32: 36159 | G32: GERAL | H32: 5KM | I32: F | J32: PP | K32: CB | L32: 149.9 | M32: INSCRITO | N32: bemol-run-rbr-2026_1 | O32: =IF(N32="bemol-run-mao-2026_1", "Manaus", IF(N32="bemol-run-rbr-2026_1", "Rio Branco", IF(N32="bemol-run-pvh-2026_1", "Porto Velho", IF(N32="bemol-run-bvb-2026_1", "Boa Vista", N32)))) -> Rio Branco
A33: 46140 | B33: 51342294220 | C33: 1896919 | D33: ADRIANA COSTA RAMIRES | E33: adriianeramires@hotmail.com | F33: 28527 | G33: GERAL | H33: 10KM | I33: M | J33: P | K33: CB | L33: 129.9 | M33: INSCRITO | N33: bemol-run-mao-2026_1 | O33: =IF(N33="bemol-run-mao-2026_1", "Manaus", IF(N33="bemol-run-rbr-2026_1", "Rio Branco", IF(N33="bemol-run-pvh-2026_1", "Porto Velho", IF(N33="bemol-run-bvb-2026_1", "Boa Vista", N33)))) -> Manaus
A34: 46140 | B34: 98407465291 | C34: 2564566 | D34: TILARA MOURA LOPES | E34: tilara.lopes@gmail.com | F34: 33814 | G34: COLAB | H34: 5KM | I34: F | J34: M | K34: CB | L34: 129.9 | M34: INSCRITO | N34: bemol-run-mao-2026_1 | O34: =IF(N34="bemol-run-mao-2026_1", "Manaus", IF(N34="bemol-run-rbr-2026_1", "Rio Branco", IF(N34="bemol-run-pvh-2026_1", "Porto Velho", IF(N34="bemol-run-bvb-2026_1", "Boa Vista", N34)))) -> Manaus
A35: 46140 | B35: 02949034292 | C35: 3708453 | D35: KATIANE AMARANTE CABRAL | E35: katiiane.cabral@gmail.com | F35: 36159 | G35: GERAL | H35: 5KM | I35: F | J35: PP | K35: CB | L35: 149.9 | M35: INSCRITO | N35: bemol-run-pvh-2026_1 | O35: =IF(N35="bemol-run-mao-2026_1", "Manaus", IF(N35="bemol-run-rbr-2026_1", "Rio Branco", IF(N35="bemol-run-pvh-2026_1", "Porto Velho", IF(N35="bemol-run-bvb-2026_1", "Boa Vista", N35)))) -> Porto Velho
A36: 46140 | B36: 53162706220 | C36: 1239268 | D36: VITOR AZEVEDO DE SOUZA | E36: vitorsouza84@icloud.com | F36: 32626 | G36: GERAL | H36: 10KM | I36: M | J36: P | K36: PIX | L36: 129.9 | M36: INSCRITO | N36: bemol-run-pvh-2026_1 | O36: =IF(N36="bemol-run-mao-2026_1", "Manaus", IF(N36="bemol-run-rbr-2026_1", "Rio Branco", IF(N36="bemol-run-pvh-2026_1", "Porto Velho", IF(N36="bemol-run-bvb-2026_1", "Boa Vista", N36)))) -> Porto Velho
A37: 46140 | B37: 01466440260 | C37: 2400031 | D37: THAIS EMANUELLE CARVALHO DA SILVA | E37: thaissilva@bemol.com.br | F37: 35660 | G37: COLAB | H37: 5KM | I37: F | J37: P | K37: CB | L37: 129.9 | M37: INSCRITO | N37: bemol-run-mao-2026_1 | O37: =IF(N37="bemol-run-mao-2026_1", "Manaus", IF(N37="bemol-run-rbr-2026_1", "Rio Branco", IF(N37="bemol-run-pvh-2026_1", "Porto Velho", IF(N37="bemol-run-bvb-2026_1", "Boa Vista", N37)))) -> Manaus
A38: 46140 | B38: 02530352283 | C38: 2312984 | D38: LARISSA SILVA PONTE | E38: lariissasilva_@hotmail.com | F38: 34873 | G38: GERAL | H38: 5KM | I38: F | J38: P | K38: CB | L38: 149.9 | M38: INSCRITO | N38: bemol-run-pvh-2026_1 | O38: =IF(N38="bemol-run-mao-2026_1", "Manaus", IF(N38="bemol-run-rbr-2026_1", "Rio Branco", IF(N38="bemol-run-pvh-2026_1", "Porto Velho", IF(N38="bemol-run-bvb-2026_1", "Boa Vista", N38)))) -> Porto Velho
A39: 46140 | B39: 00653862210 | C39: 2683242 | D39: BRENDA MORAES SANTOS | E39: brendamsantos@hotmail.com | F39: 34556 | G39: GERAL | H39: 5KM | I39: F | J39: P | K39: CB | L39: 149.9 | M39: INSCRITO | N39: bemol-run-pvh-2026_1 | O39: =IF(N39="bemol-run-mao-2026_1", "Manaus", IF(N39="bemol-run-rbr-2026_1", "Rio Branco", IF(N39="bemol-run-pvh-2026_1", "Porto Velho", IF(N39="bemol-run-bvb-2026_1", "Boa Vista", N39)))) -> Porto Velho
... A49: 46140 | B49: 99086964249 | C49: 1662504 | D49: TAINA LOPES MONTEIRO | E49: taina_rox@hotmail.com | F49: 39570 | G49: GERAL | H49: 10KM | I49: M | J49: P | K49: CB | L49: 149.9 | M49: INSCRITO | N49: bemol-run-pvh-2026_1 | O49: =IF(N49="bemol-run-mao-2026_1", "Manaus", IF(N49="bemol-run-rbr-2026_1", "Rio Branco", IF(N49="bemol-run-pvh-2026_1", "Porto Velho", IF(N49="bemol-run-bvb-2026_1", "Boa Vista", N49)))) -> Porto Velho
A50: 46140 | B50: 03957011205 | D50: DEYVISON SAVIO SANTOS DE MELO | E50: sntosmelo123@gmail.com | F50: 37532 | G50: GERAL | H50: 5KM | I50: M | J50: M | K50: PIX | L50: 129.9 | M50: CANCELADO | N50: bemol-run-pvh-2026_1 | O50: =IF(N50="bemol-run-mao-2026_1", "Manaus", IF(N50="bemol-run-rbr-2026_1", "Rio Branco", IF(N50="bemol-run-pvh-2026_1", "Porto Velho", IF(N50="bemol-run-bvb-2026_1", "Boa Vista", N50)))) -> Porto Velho
A51: 46140 | B51: 71228772215 | C51: 2105425 | D51: HERICA IGREJA | E51: herica.igreja@gmail.com | F51: 29957 | G51: GERAL | H51: 5KM | I51: F | J51: P | K51: CB | L51: 149.9 | M51: INSCRITO | N51: bemol-run-mao-2026_1 | O51: =IF(N51="bemol-run-mao-2026_1", "Manaus", IF(N51="bemol-run-rbr-2026_1", "Rio Branco", IF(N51="bemol-run-pvh-2026_1", "Porto Velho", IF(N51="bemol-run-bvb-2026_1", "Boa Vista", N51)))) -> Manaus
A52: 46140 | B52: 53094450210 | C52: 3223489 | D52: MILENA MESSIAS DE CASTRO | E52: mi.lenacastropvh@gmail.com | F52: 32145 | G52: GERAL | H52: 5KM | I52: F | J52: M | K52: CB | L52: 149.9 | M52: INSCRITO | N52: bemol-run-pvh-2026_1 | O52: =IF(N52="bemol-run-mao-2026_1", "Manaus", IF(N52="bemol-run-rbr-2026_1", "Rio Branco", IF(N52="bemol-run-pvh-2026_1", "Porto Velho", IF(N52="bemol-run-bvb-2026_1", "Boa Vista", N52)))) -> Porto Velho
A53: 46140 | B53: 51751070204 | C53: 1202516 | D53: SHEILA CRISTINA LEAL DOS SANTOS | E53: sheilasantos@bemol.com.br | F53: 27759 | G53: COLAB | H53: 5KM | I53: F | J53: P | K53: CB | L53: 129.9 | M53: INSCRITO | N53: bemol-run-mao-2026_1 | O53: =IF(N53="bemol-run-mao-2026_1", "Manaus", IF(N53="bemol-run-rbr-2026_1", "Rio Branco", IF(N53="bemol-run-pvh-2026_1", "Porto Velho", IF(N53="bemol-run-bvb-2026_1", "Boa Vista", N53)))) -> Manaus
A54: 46140 | B54: 03119061255 | C54: 3980959 | D54: ALINE BERTOZO CAVALHEIRO | E54: aline_cavalheiro_ro@hotmail.com | F54: 35148 | G54: GERAL | H54: 5KM | I54: F | J54: PP | K54: PIX | L54: 149.9 | M54: INSCRITO | N54: bemol-run-pvh-2026_1 | O54: =IF(N54="bemol-run-mao-2026_1", "Manaus", IF(N54="bemol-run-rbr-2026_1", "Rio Branco", IF(N54="bemol-run-pvh-2026_1", "Porto Velho", IF(N54="bemol-run-bvb-2026_1", "Boa Vista", N54)))) -> Porto Velho
A55: 46140 | B55: 00975381245 | C55: 1882456 | D55: IDA TAMILLES MARINHO SANTOS | E55: idasantos90@gmail.com | F55: 34435 | G55: GERAL | H55: 5KM | I55: M | J55: P | K55: PIX | L55: 149.9 | M55: INSCRITO | N55: bemol-run-mao-2026_1 | O55: =IF(N55="bemol-run-mao-2026_1", "Manaus", IF(N55="bemol-run-rbr-2026_1", "Rio Branco", IF(N55="bemol-run-pvh-2026_1", "Porto Velho", IF(N55="bemol-run-bvb-2026_1", "Boa Vista", N55)))) -> Manaus
A56: 46140 | B56: 74033972234 | C56: 1941981 | D56: LEANDRO GONCALVES SALAM | E56: leandrosalam.01@gmail.com | F56: 30856 | G56: GERAL | H56: 5KM | I56: M | J56: GG | K56: CB | L56: 129.9 | M56: INSCRITO | N56: bemol-run-mao-2026_1 | O56: =IF(N56="bemol-run-mao-2026_1", "Manaus", IF(N56="bemol-run-rbr-2026_1", "Rio Branco", IF(N56="bemol-run-pvh-2026_1", "Porto Velho", IF(N56="bemol-run-bvb-2026_1", "Boa Vista", N56)))) -> Manaus
A57: 46140 | B57: 93456603215 | C57: 2361067 | D57: BRUNA MARIA ASSUMPCAO RAMOS | E57: bruna.assumpcao@hotmail.com | F57: 33602 | G57: COLAB | H57: 5KM | I57: F | J57: P | K57: CB | L57: 129.9 | M57: INSCRITO | N57: bemol-run-mao-2026_1 | O57: =IF(N57="bemol-run-mao-2026_1", "Manaus", IF(N57="bemol-run-rbr-2026_1", "Rio Branco", IF(N57="bemol-run-pvh-2026_1", "Porto Velho", IF(N57="bemol-run-bvb-2026_1", "Boa Vista", N57)))) -> Manaus
A58: 46140 | B58: 02400837414 | C58: 5712068 | D58: JOSE DE ANCHIETA ALMEIDA DA SILVA | E58: anchietaalmeida3885@gmail.com | F58: 28487 | G58: GERAL | H58: 10KM | I58: M | J58: M | K58: PIX | L58: 149.9 | M58: INSCRITO | N58: bemol-run-pvh-2026_1 | O58: =IF(N58="bemol-run-mao-2026_1", "Manaus", IF(N58="bemol-run-rbr-2026_1", "Rio Branco", IF(N58="bemol-run-pvh-2026_1", "Porto Velho", IF(N58="bemol-run-bvb-2026_1", "Boa Vista", N58)))) -> Porto Velho
A59: 46140 | B59: 02529638225 | C59: 4988067 | D59: LEANDRO DA SILVA CAVALCANTE | E59: leandrosilvasil007@gmail.com | F59: 36736 | G59: GERAL | H59: 5KM | I59: M | J59: M | K59: CB | L59: 149.9 | M59: INSCRITO | N59: bemol-run-pvh-2026_1 | O59: =IF(N59="bemol-run-mao-2026_1", "Manaus", IF(N59="bemol-run-rbr-2026_1", "Rio Branco", IF(N59="bemol-run-pvh-2026_1", "Porto Velho", IF(N59="bemol-run-bvb-2026_1", "Boa Vista", N59)))) -> Porto Velho
A60: 46140 | B60: 03781407284 | C60: 2514015 | D60: JOSE EDUARDO DE MACEDO ARAUJO | E60: eduardo.macedoii@hotmail.com | F60: 35815 | G60: GERAL | H60: 10KM | I60: M | J60: G | K60: CB | L60: 149.9 | M60: INSCRITO | N60: bemol-run-mao-2026_1 | O60: =IF(N60="bemol-run-mao-2026_1", "Manaus", IF(N60="bemol-run-rbr-2026_1", "Rio Branco", IF(N60="bemol-run-pvh-2026_1", "Porto Velho", IF(N60="bemol-run-bvb-2026_1", "Boa Vista", N60)))) -> Manaus
A61: 46140 | B61: 03290369200 | C61: 2424670 | D61: LARISSA DOS SANTOS PALHETA | E61: larissapalheta75@gmail.com | F61: 35665 | G61: GERAL | H61: 10KM | I61: F | J61: PP | K61: CB | L61: 129.9 | M61: INSCRITO | N61: bemol-run-mao-2026_1 | O61: =IF(N61="bemol-run-mao-2026_1", "Manaus", IF(N61="bemol-run-rbr-2026_1", "Rio Branco", IF(N61="bemol-run-pvh-2026_1", "Porto Velho", IF(N61="bemol-run-bvb-2026_1", "Boa Vista", N61)))) -> Manaus
A62: 46140 | B62: 79816096234 | C62: 2096514 | D62: AUDILEIA YUKO DE MORAES | E62: audiyuko@gmail.com | F62: 31159 | G62: GERAL | H62: 5KM | I62: F | J62: G | K62: CB | L62: 129.9 | M62: INSCRITO | N62: bemol-run-pvh-2026_1 | O62: =IF(N62="bemol-run-mao-2026_1", "Manaus", IF(N62="bemol-run-rbr-2026_1", "Rio Branco", IF(N62="bemol-run-pvh-2026_1", "Porto Velho", IF(N62="bemol-run-bvb-2026_1", "Boa Vista", N62)))) -> Porto Velho
... A65: 46140 | B65: 93891563272 | C65: 1397113 | D65: ADREA DA CUNHA GUEDES | E65: adria191@hotmail.com | F65: 33422 | G65: GERAL | H65: 5KM | I65: F | J65: M | K65: CB | L65: 129.9 | M65: INSCRITO | N65: bemol-run-mao-2026_1 | O65: =IF(N65="bemol-run-mao-2026_1", "Manaus", IF(N65="bemol-run-rbr-2026_1", "Rio Branco", IF(N65="bemol-run-pvh-2026_1", "Porto Velho", IF(N65="bemol-run-bvb-2026_1", "Boa Vista", N65)))) -> Manaus
A66: 46140 | B66: 01879036207 | D66: RAMON BRENO DOS SANTOS RODRIGUES | E66: ramonicet@gmail.com | F66: 35153 | G66: COLAB | H66: 5KM | I66: M | J66: M | K66: PIX | L66: 129.9 | M66: CANCELADO | N66: bemol-run-rbr-2026_1 | O66: =IF(N66="bemol-run-mao-2026_1", "Manaus", IF(N66="bemol-run-rbr-2026_1", "Rio Branco", IF(N66="bemol-run-pvh-2026_1", "Porto Velho", IF(N66="bemol-run-bvb-2026_1", "Boa Vista", N66)))) -> Rio Branco
A67: 46140 | B67: 95443371215 | C67: 1450027 | D67: CLELY AZEVEDO DA SILVA | E67: clelyazevedo40@gmail.com | F67: 31213 | G67: COLAB | H67: 5KM | I67: F | J67: M | K67: CB | L67: 129.9 | M67: INSCRITO | N67: bemol-run-mao-2026_1 | O67: =IF(N67="bemol-run-mao-2026_1", "Manaus", IF(N67="bemol-run-rbr-2026_1", "Rio Branco", IF(N67="bemol-run-pvh-2026_1", "Porto Velho", IF(N67="bemol-run-bvb-2026_1", "Boa Vista", N67)))) -> Manaus
A68: 46140 | B68: 52948625220 | C68: 1673653 | D68: RAFAEL FERREIRA GUEDES | E68: davirafaelguedes30@gmail.com | F68: 39570 | G68: GERAL | H68: 5KM | I68: M | J68: G | K68: CB | L68: 149.9 | M68: INSCRITO | N68: bemol-run-pvh-2026_1 | O68: =IF(N68="bemol-run-mao-2026_1", "Manaus", IF(N68="bemol-run-rbr-2026_1", "Rio Branco", IF(N68="bemol-run-pvh-2026_1", "Porto Velho", IF(N68="bemol-run-bvb-2026_1", "Boa Vista", N68)))) -> Porto Velho
A69: 46140 | B69: 08385531254 | C69: 4754158 | D69: EDNELSON CAUA TRINDADE PIRES | E69: ednelsoncauatrindadepires@gmail.com | F69: 38951 | G69: COLAB | H69: 10KM | I69: M | J69: M | K69: CB | L69: 129.9 | M69: INSCRITO | N69: bemol-run-mao-2026_1 | O69: =IF(N69="bemol-run-mao-2026_1", "Manaus", IF(N69="bemol-run-rbr-2026_1", "Rio Branco", IF(N69="bemol-run-pvh-2026_1", "Porto Velho", IF(N69="bemol-run-bvb-2026_1", "Boa Vista", N69)))) -> Manaus
A70: 46140 | B70: 92719430234 | C70: 2613667 | D70: ALBERTO PELEGRINE DA N NETO | E70: alberto.ouv@gmail.com | F70: 35474 | G70: GERAL | H70: 5KM | I70: F | J70: XG | K70: PIX | L70: 129.9 | M70: INSCRITO | N70: bemol-run-mao-2026_1 | O70: =IF(N70="bemol-run-mao-2026_1", "Manaus", IF(N70="bemol-run-rbr-2026_1", "Rio Branco", IF(N70="bemol-run-pvh-2026_1", "Porto Velho", IF(N70="bemol-run-bvb-2026_1", "Boa Vista", N70)))) -> Manaus
A71: 46140 | B71: 01364071290 | C71: 4350921 | D71: NAINA LIMA CANTO | E71: nainalimacanto@gmail.com | F71: 33407 | G71: GERAL | H71: 5KM | I71: M | J71: M | K71: CB | L71: 129.9 | M71: INSCRITO | N71: bemol-run-mao-2026_1 | O71: =IF(N71="bemol-run-mao-2026_1", "Manaus", IF(N71="bemol-run-rbr-2026_1", "Rio Branco", IF(N71="bemol-run-pvh-2026_1", "Porto Velho", IF(N71="bemol-run-bvb-2026_1", "Boa Vista", N71)))) -> Manaus
A72: 46140 | B72: 03956819284 | C72: 3219446 | D72: AMANDA JAQUELINE IZEL DE ASSIS | E72: nayronstorage@gmail.com | F72: 36249 | G72: GERAL | H72: 5KM | I72: F | J72: G | K72: PIX | L72: 149.9 | M72: INSCRITO | N72: bemol-run-pvh-2026_1 | O72: =IF(N72="bemol-run-mao-2026_1", "Manaus", IF(N72="bemol-run-rbr-2026_1", "Rio Branco", IF(N72="bemol-run-pvh-2026_1", "Porto Velho", IF(N72="bemol-run-bvb-2026_1", "Boa Vista", N72)))) -> Porto Velho
A73: 46140 | B73: 03470831297 | C73: 2602024 | D73: FELIPE LIMA DA COSTA | E73: Felipe.lima.nbd@gmail.com | F73: 35491 | G73: GERAL | H73: 10KM | I73: M | J73: GG | K73: CB | L73: 129.9 | M73: INSCRITO | N73: bemol-run-mao-2026_1 | O73: =IF(N73="bemol-run-mao-2026_1", "Manaus", IF(N73="bemol-run-rbr-2026_1", "Rio Branco", IF(N73="bemol-run-pvh-2026_1", "Porto Velho", IF(N73="bemol-run-bvb-2026_1", "Boa Vista", N73)))) -> Manaus
A74: 46140 | B74: 03347806247 | C74: 2566293 | D74: FERNANDA NAHMIAS WANDERLEY | E74: fernandanahmias6@gmail.com | F74: 36453 | G74: GERAL | H74: 10KM | I74: F | J74: M | K74: PIX | L74: 129.9 | M74: INSCRITO | N74: bemol-run-mao-2026_1 | O74: =IF(N74="bemol-run-mao-2026_1", "Manaus", IF(N74="bemol-run-rbr-2026_1", "Rio Branco", IF(N74="bemol-run-pvh-2026_1", "Porto Velho", IF(N74="bemol-run-bvb-2026_1", "Boa Vista", N74)))) -> Manaus
A75: 46140 | B75: 02470702208 | C75: 5135832 | D75: ANA ALICE CAVALCANTE DE OLIVEIRA | E75: aliceoliveirana@gmail.com | F75: 38287 | G75: GERAL | H75: 5KM | I75: F | J75: GG | K75: CB | L75: 149.9 | M75: INSCRITO | N75: bemol-run-pvh-2026_1 | O75: =IF(N75="bemol-run-mao-2026_1", "Manaus", IF(N75="bemol-run-rbr-2026_1", "Rio Branco", IF(N75="bemol-run-pvh-2026_1", "Porto Velho", IF(N75="bemol-run-bvb-2026_1", "Boa Vista", N75)))) -> Porto Velho
A76: 46140 | B76: 81992521204 | C76: 1488231 | D76: LAZARO DAVID BICHO COUTINHO | E76: lazarodavid@bemol.com.br | F76: 30723 | G76: COLAB | H76: 5KM | I76: M | J76: GG | K76: CB | L76: 129.9 | M76: INSCRITO | N76: bemol-run-mao-2026_1 | O76: =IF(N76="bemol-run-mao-2026_1", "Manaus", IF(N76="bemol-run-rbr-2026_1", "Rio Branco", IF(N76="bemol-run-pvh-2026_1", "Porto Velho", IF(N76="bemol-run-bvb-2026_1", "Boa Vista", N76)))) -> Manaus
A77: 46140 | B77: 32226269878 | C77: 2233949 | D77: ADAUTO SENE MARTINS | E77: sene.adauto@gmail.com | F77: 30691 | G77: COLAB | H77: 5KM | I77: M | J77: G | K77: CB | L77: 129.9 | M77: INSCRITO | N77: bemol-run-mao-2026_1 | O77: =IF(N77="bemol-run-mao-2026_1", "Manaus", IF(N77="bemol-run-rbr-2026_1", "Rio Branco", IF(N77="bemol-run-pvh-2026_1", "Porto Velho", IF(N77="bemol-run-bvb-2026_1", "Boa Vista", N77)))) -> Manaus
A78: 46140 | B78: 03092377265 | C78: 4061617 | D78: ROMAIKA MARIA PEREIRA DA SILVA | E78: romaikasilva@bemol.com.br | F78: 34542 | G78: COLAB | H78: 5KM | I78: F | J78: PP | K78: CB | L78: 129.9 | M78: INSCRITO | N78: bemol-run-rbr-2026_1 | O78: =IF(N78="bemol-run-mao-2026_1", "Manaus", IF(N78="bemol-run-rbr-2026_1", "Rio Branco", IF(N78="bemol-run-pvh-2026_1", "Porto Velho", IF(N78="bemol-run-bvb-2026_1", "Boa Vista", N78)))) -> Rio Branco
... A89: 46140 | B89: 63103206291 | C89: 1012616 | D89: CARYTHA D ALMEIDA CORREA | E89: carytha@bemol.com.br | F89: 28784 | G89: COLAB | H89: 5KM | I89: F | J89: GG | K89: CB | L89: 129.9 | M89: INSCRITO | N89: bemol-run-mao-2026_1 | O89: =IF(N89="bemol-run-mao-2026_1", "Manaus", IF(N89="bemol-run-rbr-2026_1", "Rio Branco", IF(N89="bemol-run-pvh-2026_1", "Porto Velho", IF(N89="bemol-run-bvb-2026_1", "Boa Vista", N89)))) -> Manaus
A90: 46140 | B90: 31479162272 | D90: LEILA SILVA | E90: melo_leila@yahoo.com.br | F90: 26141 | G90: COLAB | H90: 5KM | I90: F | J90: PP | K90: CB | L90: 149.9 | M90: CANCELADO | N90: bemol-run-mao-2026_1 | O90: =IF(N90="bemol-run-mao-2026_1", "Manaus", IF(N90="bemol-run-rbr-2026_1", "Rio Branco", IF(N90="bemol-run-pvh-2026_1", "Porto Velho", IF(N90="bemol-run-bvb-2026_1", "Boa Vista", N90)))) -> Manaus
A91: 46140 | B91: 01109323239 | C91: 1823718 | D91: KASSIA KAROLYNA REIS PEZOS | E91: pezoskk@gmail.com | F91: 33775 | G91: GERAL | H91: 10KM | I91: F | J91: PP | K91: CB | L91: 129.9 | M91: INSCRITO | N91: bemol-run-mao-2026_1 | O91: =IF(N91="bemol-run-mao-2026_1", "Manaus", IF(N91="bemol-run-rbr-2026_1", "Rio Branco", IF(N91="bemol-run-pvh-2026_1", "Porto Velho", IF(N91="bemol-run-bvb-2026_1", "Boa Vista", N91)))) -> Manaus
A92: 46140 | B92: 02629664929 | C92: 2646316 | D92: ALESANDRA FERREIRA | E92: manuzinha224.agcf@gmail.com | F92: 28845 | G92: GERAL | H92: 5KM | I92: F | J92: M | K92: CB | L92: 149.9 | M92: INSCRITO | N92: bemol-run-pvh-2026_1 | O92: =IF(N92="bemol-run-mao-2026_1", "Manaus", IF(N92="bemol-run-rbr-2026_1", "Rio Branco", IF(N92="bemol-run-pvh-2026_1", "Porto Velho", IF(N92="bemol-run-bvb-2026_1", "Boa Vista", N92)))) -> Porto Velho
A93: 46140 | B93: 01823451225 | C93: 3069093 | D93: Jancleverson Gomes | E93: jancleversong@hotmail.com | F93: 34987 | G93: GERAL | H93: 10KM | I93: M | J93: G | K93: CB | L93: 149.9 | M93: INSCRITO | N93: bemol-run-mao-2026_1 | O93: =IF(N93="bemol-run-mao-2026_1", "Manaus", IF(N93="bemol-run-rbr-2026_1", "Rio Branco", IF(N93="bemol-run-pvh-2026_1", "Porto Velho", IF(N93="bemol-run-bvb-2026_1", "Boa Vista", N93)))) -> Manaus
A94: 46140 | B94: 01372817220 | C94: 2694421 | D94: AMANDA NUNES VIEIRA | E94: amandavnunes@outlook.com | F94: 34491 | G94: GERAL | H94: 5KM | I94: M | J94: M | K94: CB | L94: 129.9 | M94: INSCRITO | N94: bemol-run-mao-2026_1 | O94: =IF(N94="bemol-run-mao-2026_1", "Manaus", IF(N94="bemol-run-rbr-2026_1", "Rio Branco", IF(N94="bemol-run-pvh-2026_1", "Porto Velho", IF(N94="bemol-run-bvb-2026_1", "Boa Vista", N94)))) -> Manaus
A95: 46140 | B95: 41765540291 | C95: 294471 | D95: EDNARA BATISTA DA CRUZ | E95: ednaracruz@gmail.com | F95: 26353 | G95: GERAL | H95: 5KM | I95: F | J95: M | K95: CB | L95: 129.9 | M95: INSCRITO | N95: bemol-run-mao-2026_1 | O95: =IF(N95="bemol-run-mao-2026_1", "Manaus", IF(N95="bemol-run-rbr-2026_1", "Rio Branco", IF(N95="bemol-run-pvh-2026_1", "Porto Velho", IF(N95="bemol-run-bvb-2026_1", "Boa Vista", N95)))) -> Manaus
A96: 46140 | B96: 70200610287 | C96: 1179566 | D96: LEVI SANTOS DE ARAUJO | E96: faoeac@bol.com.br | F96: 29819 | G96: GERAL | H96: 10KM | I96: M | J96: M | K96: PIX | L96: 149.9 | M96: INSCRITO | N96: bemol-run-pvh-2026_1 | O96: =IF(N96="bemol-run-mao-2026_1", "Manaus", IF(N96="bemol-run-rbr-2026_1", "Rio Branco", IF(N96="bemol-run-pvh-2026_1", "Porto Velho", IF(N96="bemol-run-bvb-2026_1", "Boa Vista", N96)))) -> Porto Velho
A97: 46140 | B97: 80899978215 | C97: 2146024 | D97: TOBIAS FERREIRA DA SILVA JUNIOR | E97: prjuniortobias@gmail.com | F97: 39570 | G97: GERAL | H97: 10KM | I97: F | J97: P | K97: CB | L97: 149.9 | M97: INSCRITO | N97: bemol-run-pvh-2026_1 | O97: =IF(N97="bemol-run-mao-2026_1", "Manaus", IF(N97="bemol-run-rbr-2026_1", "Rio Branco", IF(N97="bemol-run-pvh-2026_1", "Porto Velho", IF(N97="bemol-run-bvb-2026_1", "Boa Vista", N97)))) -> Porto Velho
A98: 46140 | B98: 01293490202 | C98: 1876127 | D98: HEMERSON CARLOS SANTOS DUARTE | E98: hemersonc87@gmail.com | F98: 33761 | G98: COLAB | H98: 10KM | I98: F | J98: P | K98: CB | L98: 129.9 | M98: INSCRITO | N98: bemol-run-mao-2026_1 | O98: =IF(N98="bemol-run-mao-2026_1", "Manaus", IF(N98="bemol-run-rbr-2026_1", "Rio Branco", IF(N98="bemol-run-pvh-2026_1", "Porto Velho", IF(N98="bemol-run-bvb-2026_1", "Boa Vista", N98)))) -> Manaus
A99: 46140 | B99: 00591964244 | D99: GUILHERME ANDRADE DE OLIVEIRA | E99: guilhermeao1991@gmail.com | F99: 33433 | G99: GERAL | H99: 5KM | I99: M | J99: M | K99: PIX | L99: 149.9 | M99: CANCELADO | N99: bemol-run-pvh-2026_1 | O99: =IF(N99="bemol-run-mao-2026_1", "Manaus", IF(N99="bemol-run-rbr-2026_1", "Rio Branco", IF(N99="bemol-run-pvh-2026_1", "Porto Velho", IF(N99="bemol-run-bvb-2026_1", "Boa Vista", N99)))) -> Porto Velho
A100: 46140 | B100: 63000105204 | C100: 1014320 | D100: JANAINNA BARROSO MUNIZ DOS SANTOS | E100: aguiamoreirasantos@gmail.com | F100: 28478 | G100: GERAL | H100: 5KM | I100: F | J100: PP | K100: CB | L100: 129.9 | M100: INSCRITO | N100: bemol-run-mao-2026_1 | O100: =IF(N100="bemol-run-mao-2026_1", "Manaus", IF(N100="bemol-run-rbr-2026_1", "Rio Branco", IF(N100="bemol-run-pvh-2026_1", "Porto Velho", IF(N100="bemol-run-bvb-2026_1", "Boa Vista", N100)))) -> Manaus
A101: 46140 | B101: 95593691215 | D101: DAYNA TEREZA DA SILVA BEZERRA | E101: daynatereza@gmail.com | F101: 32919 | G101: COLAB | H101: 5KM | I101: F | J101: M | K101: PIX | L101: 129.9 | M101: CANCELADO | N101: bemol-run-mao-2026_1 | O101: =IF(N101="bemol-run-mao-2026_1", "Manaus", IF(N101="bemol-run-rbr-2026_1", "Rio Branco", IF(N101="bemol-run-pvh-2026_1", "Porto Velho", IF(N101="bemol-run-bvb-2026_1", "Boa Vista", N101)))) -> Manaus
A102: 46140 | B102: 69839948253 | C102: 1490820 | D102: CHARLYS NERES DE CASTRO | E102: admcharlys@gmail.com | F102: 29836 | G102: COLAB | H102: 5KM | I102: M | J102: M | K102: CB | L102: 129.9 | M102: INSCRITO | N102: bemol-run-rbr-2026_1 | O102: =IF(N102="bemol-run-mao-2026_1", "Manaus", IF(N102="bemol-run-rbr-2026_1", "Rio Branco", IF(N102="bemol-run-pvh-2026_1", "Porto Velho", IF(N102="bemol-run-bvb-2026_1", "Boa Vista", N102)))) -> Rio Branco
A103: 46140 | B103: 51370999291 | C103: 1486797 | D103: THAIS DE FARIA SANTANA SILVA | E103: thais.santana@gmail.com | F103: 29334 | G103: GERAL | H103: 10KM | I103: M | J103: M | K103: CB | L103: 129.9 | M103: INSCRITO | N103: bemol-run-mao-2026_1 | O103: =IF(N103="bemol-run-mao-2026_1", "Manaus", IF(N103="bemol-run-rbr-2026_1", "Rio Branco", IF(N103="bemol-run-pvh-2026_1", "Porto Velho", IF(N103="bemol-run-bvb-2026_1", "Boa Vista", N103)))) -> Manaus
A104: 46140 | B104: 67731082253 | C104: 1294172 | D104: CLEY ALVES DE CASTRO | E104: cleycastro@bemol.com.br | F104: 29428 | G104: COLAB | H104: 5KM | I104: M | J104: PP | K104: CB | L104: 129.9 | M104: INSCRITO | N104: bemol-run-mao-2026_1 | O104: =IF(N104="bemol-run-mao-2026_1", "Manaus", IF(N104="bemol-run-rbr-2026_1", "Rio Branco", IF(N104="bemol-run-pvh-2026_1", "Porto Velho", IF(N104="bemol-run-bvb-2026_1", "Boa Vista", N104)))) -> Manaus
A105: 46140 | B105: 81291205268 | C105: 3075610 | D105: DIANA NOGUEIRA BENTES | E105: dianynha_bentes@hotmail.com | F105: 30624 | G105: GERAL | H105: 5KM | I105: F | J105: PP | K105: CB | L105: 129.9 | M105: INSCRITO | N105: bemol-run-mao-2026_1 | O105: =IF(N105="bemol-run-mao-2026_1", "Manaus", IF(N105="bemol-run-rbr-2026_1", "Rio Branco", IF(N105="bemol-run-pvh-2026_1", "Porto Velho", IF(N105="bemol-run-bvb-2026_1", "Boa Vista", N105)))) -> Manaus
A106: 46140 | B106: 00850944201 | D106: FELIPE BONATES MOTA MARROCOS | E106: felipmarrocos@gmail.com | F106: 33162 | G106: GERAL | H106: 5KM | I106: M | J106: P | K106: PIX | L106: 149.9 | M106: CANCELADO | N106: bemol-run-mao-2026_1 | O106: =IF(N106="bemol-run-mao-2026_1", "Manaus", IF(N106="bemol-run-rbr-2026_1", "Rio Branco", IF(N106="bemol-run-pvh-2026_1", "Porto Velho", IF(N106="bemol-run-bvb-2026_1", "Boa Vista", N106)))) -> Manaus
A107: 46140 | B107: 05524202200 | D107: LINDINALVA PASSOS VIEIRA | E107: lindinalvapassosvieira@gmail.com | F107: 19369 | G107: GERAL | H107: 5KM | I107: F | J107: PP | K107: PIX | L107: 74.95 | M107: CANCELADO | N107: bemol-run-mao-2026_1 | O107: =IF(N107="bemol-run-mao-2026_1", "Manaus", IF(N107="bemol-run-rbr-2026_1", "Rio Branco", IF(N107="bemol-run-pvh-2026_1", "Porto Velho", IF(N107="bemol-run-bvb-2026_1", "Boa Vista", N107)))) -> Manaus
A108: 46140 | B108: 80679676287 | C108: 4562344 | D108: BRENDA DA SILVA SOUSA | E108: brendasousa83@outlook.com | F108: 37330 | G108: GERAL | H108: 10KM | I108: F | J108: GG | K108: CB | L108: 129.9 | M108: INSCRITO | N108: bemol-run-mao-2026_1 | O108: =IF(N108="bemol-run-mao-2026_1", "Manaus", IF(N108="bemol-run-rbr-2026_1", "Rio Branco", IF(N108="bemol-run-pvh-2026_1", "Porto Velho", IF(N108="bemol-run-bvb-2026_1", "Boa Vista", N108)))) -> Manaus
A109: 46140 | B109: 02317279256 | C109: 2364381 | D109: ALEKSANDER BRUNO SILVA DE SOUZA | E109: aleksander12385@gmail.com | F109: 35050 | G109: COLAB | H109: 5KM | I109: F | J109: M | K109: CB | L109: 129.9 | M109: INSCRITO | N109: bemol-run-mao-2026_1 | O109: =IF(N109="bemol-run-mao-2026_1", "Manaus", IF(N109="bemol-run-rbr-2026_1", "Rio Branco", IF(N109="bemol-run-pvh-2026_1", "Porto Velho", IF(N109="bemol-run-bvb-2026_1", "Boa Vista", N109)))) -> Manaus
A110: 46140 | B110: 00523602294 | C110: 2525520 | D110: DANIELY BEZERRA DA SILVA | E110: danielybezerragm@gmail.com | F110: 33001 | G110: COLAB | H110: 5KM | I110: F | J110: P | K110: CB | L110: 129.9 | M110: INSCRITO | N110: bemol-run-pvh-2026_1 | O110: =IF(N110="bemol-run-mao-2026_1", "Manaus", IF(N110="bemol-run-rbr-2026_1", "Rio Branco", IF(N110="bemol-run-pvh-2026_1", "Porto Velho", IF(N110="bemol-run-bvb-2026_1", "Boa Vista", N110)))) -> Porto Velho
A111: 46140 | B111: 70063322226 | C111: 2443680 | D111: JOSE WICLIFF ALVES FERREIRA | E111: josewicliff40@gmail.com | F111: 36315 | G111: GERAL | H111: 5KM | I111: M | J111: M | K111: CB | L111: 149.9 | M111: INSCRITO | N111: bemol-run-mao-2026_1 | O111: =IF(N111="bemol-run-mao-2026_1", "Manaus", IF(N111="bemol-run-rbr-2026_1", "Rio Branco", IF(N111="bemol-run-pvh-2026_1", "Porto Velho", IF(N111="bemol-run-bvb-2026_1", "Boa Vista", N111)))) -> Manaus
A112: 46140 | B112: 70378919245 | C112: 4496339 | D112: KERVENS LOUIS | E112: kervenslouis1607@gmail.com | F112: 37453 | G112: COLAB | H112: 5KM | I112: F | J112: G | K112: CB | L112: 129.9 | M112: INSCRITO | N112: bemol-run-mao-2026_1 | O112: =IF(N112="bemol-run-mao-2026_1", "Manaus", IF(N112="bemol-run-rbr-2026_1", "Rio Branco", IF(N112="bemol-run-pvh-2026_1", "Porto Velho", IF(N112="bemol-run-bvb-2026_1", "Boa Vista", N112)))) -> Manaus
A113: 46140 | B113: 46399941253 | C113: 301481 | D113: WELLINGTON MOREIRA DOS SANTOS | E113: aguiamoreirasantos@gmail.com | F113: 27542 | G113: GERAL | H113: 10KM | I113: F | J113: G | K113: CB | L113: 129.9 | M113: INSCRITO | N113: bemol-run-mao-2026_1 | O113: =IF(N113="bemol-run-mao-2026_1", "Manaus", IF(N113="bemol-run-rbr-2026_1", "Rio Branco", IF(N113="bemol-run-pvh-2026_1", "Porto Velho", IF(N113="bemol-run-bvb-2026_1", "Boa Vista", N113)))) -> Manaus
A114: 46140 | B114: 80055915272 | C114: 1154473 | D114: DAIANE DA CRUZ LIMA | E114: daianellimacruz@gmail.com | F114: 31424 | G114: GERAL | H114: 5KM | I114: F | J114: M | K114: CB | L114: 149.9 | M114: INSCRITO | N114: bemol-run-mao-2026_1 | O114: =IF(N114="bemol-run-mao-2026_1", "Manaus", IF(N114="bemol-run-rbr-2026_1", "Rio Branco", IF(N114="bemol-run-pvh-2026_1", "Porto Velho", IF(N114="bemol-run-bvb-2026_1", "Boa Vista", N114)))) -> Manaus
A115: 46140 | B115: 82405697220 | C115: 1387451 | D115: CLEITON RANGEL DOS ANJOS | E115: ggeysse@gmail.com | F115: 30858 | G115: GERAL | H115: 5KM | I115: F | J115: M | K115: CB | L115: 129.9 | M115: INSCRITO | N115: bemol-run-mao-2026_1 | O115: =IF(N115="bemol-run-mao-2026_1", "Manaus", IF(N115="bemol-run-rbr-2026_1", "Rio Branco", IF(N115="bemol-run-pvh-2026_1", "Porto Velho", IF(N115="bemol-run-bvb-2026_1", "Boa Vista", N115)))) -> Manaus
A116: 46140 | B116: 86018230259 | C116: 1411941 | D116: CAMILA SILVA DE FREITAS | E116: camifreittas@gmail.com | F116: 31725 | G116: GERAL | H116: 10KM | I116: F | J116: P | K116: PIX | L116: 149.9 | M116: INSCRITO | N116: bemol-run-mao-2026_1 | O116: =IF(N116="bemol-run-mao-2026_1", "Manaus", IF(N116="bemol-run-rbr-2026_1", "Rio Branco", IF(N116="bemol-run-pvh-2026_1", "Porto Velho", IF(N116="bemol-run-bvb-2026_1", "Boa Vista", N116)))) -> Manaus
A117: 46140 | B117: 02032049210 | C117: 1884218 | D117: LETICIA BARROS LEONEL DE OLIVEIRA | E117: letcia.lbl@hotmail.com | F117: 34366 | G117: COLAB | H117: 5KM | I117: F | J117: P | K117: CB | L117: 129.9 | M117: INSCRITO | N117: bemol-run-pvh-2026_1 | O117: =IF(N117="bemol-run-mao-2026_1", "Manaus", IF(N117="bemol-run-rbr-2026_1", "Rio Branco", IF(N117="bemol-run-pvh-2026_1", "Porto Velho", IF(N117="bemol-run-bvb-2026_1", "Boa Vista", N117)))) -> Porto Velho
A118: 46140 | B118: 81195702272 | C118: 1617320 | D118: BRAS JUNIOR DA SILVA ANDRADE | E118: juniorbras@hotmail.com | F118: 30944 | G118: GERAL | H118: 10KM | I118: M | J118: G | K118: CB | L118: 129.9 | M118: INSCRITO | N118: bemol-run-mao-2026_1 | O118: =IF(N118="bemol-run-mao-2026_1", "Manaus", IF(N118="bemol-run-rbr-2026_1", "Rio Branco", IF(N118="bemol-run-pvh-2026_1", "Porto Velho", IF(N118="bemol-run-bvb-2026_1", "Boa Vista", N118)))) -> Manaus
A119: 46140 | B119: 52047440297 | C119: 2407739 | D119: VANESSA RAMOS DA COSTA | E119: vanessacosta@bemol.com.br | F119: 29813 | G119: COLAB | H119: 10KM | I119: F | J119: PP | K119: CB | L119: 129.9 | M119: INSCRITO | N119: bemol-run-mao-2026_1 | O119: =IF(N119="bemol-run-mao-2026_1", "Manaus", IF(N119="bemol-run-rbr-2026_1", "Rio Branco", IF(N119="bemol-run-pvh-2026_1", "Porto Velho", IF(N119="bemol-run-bvb-2026_1", "Boa Vista", N119)))) -> Manaus
... A127: 46140 | B127: 62998080200 | C127: 1036486 | D127: HUGO DOS SANTOS CUSTODIO | E127: hugo332008@hotmail.com | F127: 27606 | G127: GERAL | H127: 10KM | I127: F | J127: P | K127: CB | L127: 129.9 | M127: INSCRITO | N127: bemol-run-mao-2026_1 | O127: =IF(N127="bemol-run-mao-2026_1", "Manaus", IF(N127="bemol-run-rbr-2026_1", "Rio Branco", IF(N127="bemol-run-pvh-2026_1", "Porto Velho", IF(N127="bemol-run-bvb-2026_1", "Boa Vista", N127)))) -> Manaus
A128: 46140 | B128: 96125039234 | D128: LUCIANE PATRICIA IMBIRIBA TAPAJOS | E128: lucianetapajos.fabricio@gmail.com | F128: 32695 | G128: COLAB | H128: 5KM | I128: F | J128: M | K128: PIX | L128: 129.9 | M128: CANCELADO | N128: bemol-run-mao-2026_1 | O128: =IF(N128="bemol-run-mao-2026_1", "Manaus", IF(N128="bemol-run-rbr-2026_1", "Rio Branco", IF(N128="bemol-run-pvh-2026_1", "Porto Velho", IF(N128="bemol-run-bvb-2026_1", "Boa Vista", N128)))) -> Manaus
...

Sheet Vendas - Tickets
A1: numeroPedido | B1: dataPedido | C1: status | D1: formaDePagamento | E1: idEvento | F1: tituloEvento | G1: realizacao | H1: inscricao_grupo | I1: inscricao | J1: nome | K1: documento | L1: email | M1: celular | N1: sexo | O1: nascimento | P1: categoria | Q1: modalidade | R1: valorUnitario | S1: valorTaxa | T1: valorDesconto | U1: valorRepasse | V1: cep | W1: endereco | X1: numero | Y1: bairro | Z1: cidade | AA1: estado | AB1: pais | AC1: camiseta_5km | AD1: camiseta_10km | AE1: camiseta_kids | AF1: camisetas | AG1: responsavel | AH1: emailResponsavel | AI1: documentoResponsavel
A2: 12485139 | B2: 23/04/2026 17:54 | C2: Cancelado | D2: Started | E2: 86645 | F2: Manaus | G2: 30/08/2026 | H2: FALSE | I2: 15252914 | J2: Louise Silva | K2: 02711568210 | L2: louisebaptista96@hotmail.com | M2: 5592993032059 | N2: F | O2: 08/11/1996 | P2: KIT PARTICIPAÇÃO | Q2: 5KM | R2: 149,90 | S2: 14,99 | T2: 0,00 | U2: 149,90 | V2: 69058122 | W2: Rua Almirante | X2: 22C | Y2: Parque 10 | Z2: Manaus | AA2: AM | AB2: Brasil | AC2: P | AF2: P | AG2: Louise Silva | AH2: louisebaptista96@hotmail.com | AI2: 02711568210
A3: 12521816 | B3: 28/04/2026 11:53 | C3: Pago | D3: Pix | E3: 86647 | F3: Porto Velho | G3: 26/07/2026 | H3: FALSE | I3: 15295574 | J3: Luciana Ermita | K3: 92746187191 | L3: luoliveira2309@gmail.com | M3: 5569981700508 | N3: F | O3: 23/09/1978 | P3: KIT PARTICIPAÇÃO | Q3: 5KM | R3: 149,90 | S3: 14,99 | T3: 0,00 | U3: 149,90 | V3: 76820294 | W3: Rua Reverendo Elias Fontes | X3: 1714 | Y3: Agenor de carvalho | Z3: Porto Velho | AA3: RO | AB3: Brasil | AC3: G | AF3: G | AG3: Carlos Eduardo Ermita | AH3: ermita260144@gmail.com | AI3: 36146323187
A4: 12521816 | B4: 28/04/2026 11:53 | C4: Pago | D4: Pix | E4: 86647 | F4: Porto Velho | G4: 26/07/2026 | H4: FALSE | I4: 15295573 | J4: Carlos Eduardo Ermita | K4: 36146323187 | L4: ermita260144@gmail.com | M4: 5569981158476 | N4: M | O4: 04/04/1970 | P4: KIT PARTICIPAÇÃO | Q4: 10KM | R4: 149,90 | S4: 14,99 | T4: 0,00 | U4: 149,90 | V4: 76820294 | W4: Rua Reverendo Elias Fontes | X4: 1714 | Y4: Agenor de carvalho | Z4: Porto Velho | AA4: RO | AB4: Brasil | AD4: GG | AF4: GG | AG4: Carlos Eduardo Ermita | AH4: ermita260144@gmail.com | AI4: 36146323187
A5: 12524462 | B5: 28/04/2026 14:32 | C5: Cancelado | D5: Started | E5: 86645 | F5: Manaus | G5: 30/08/2026 | H5: FALSE | I5: 15298662 | J5: Larissa Teixeira Maddy | K5: 94690855234 | L5: larissamaddyc@gmail.com | M5: 5592984197246 | N5: F | O5: 14/01/1995 | P5: KIT PARTICIPAÇÃO | Q5: 5KM | R5: 149,90 | S5: 14,99 | T5: 0,00 | U5: 149,90 | V5: 69088390 | W5: Rua Acaete | X5: 3 | Y5: Jorge Teixeira | Z5: Manaus | AA5: AM | AB5: Brasil | AC5: M | AF5: M | AG5: Larissa Teixeira Maddy | AH5: larissamaddyc@gmail.com | AI5: 94690855234
A6: 12524468 | B6: 28/04/2026 14:10 | C6: Pago | D6: Cartão Crédito | E6: 86647 | F6: Porto Velho | G6: 26/07/2026 | H6: FALSE | I6: 15298672 | J6: Carlos Henrique Lustosa Silva | K6: 87112035287 | L6: carloshenriquepvh@gmail.com | M6: 69985018770 | N6: M | O6: 15/04/1989 | P6: KIT PARTICIPAÇÃO | Q6: 10KM | R6: 149,90 | S6: 14,99 | T6: 0,00 | U6: 149,90 | V6: 76812642 | W6: Rua Lirio | X6: 6409 | Y6: Três Marias | Z6: Porto Velho | AA6: RO | AB6: Brasil | AD6: M | AF6: M | AG6: Carlos Henrique Lustosa Silva | AH6: carloshenriquepvh@gmail.com | AI6: 87112035287
A7: 12524505 | B7: 28/04/2026 14:37 | C7: Pago | D7: Cartão Crédito | E7: 86647 | F7: Porto Velho | G7: 26/07/2026 | H7: FALSE | I7: 15298714 | J7: Sabrina Alves Pereira Valerio | K7: 01850084297 | L7: salvespereiravalerio@gmail.com | M7: 5569992322374 | N7: F | O7: 03/11/1992 | P7: KIT PARTICIPAÇÃO | Q7: 5KM | R7: 149,90 | S7: 14,99 | T7: 0,00 | U7: 149,90 | V7: 76860000 | W7: Rua Duarte Da Costa | X7: 287 | Y7: União | Z7: Candeias do Jamari | AA7: RO | AB7: Brasil | AC7: P | AF7: P | AG7: Sabrina Alves Pereira Valerio | AH7: salvespereiravalerio@gmail.com | AI7: 01850084297
A8: 12524512 | B8: 28/04/2026 14:58 | C8: Pago | D8: Pix | E8: 86647 | F8: Porto Velho | G8: 26/07/2026 | H8: FALSE | I8: 15298722 | J8: Lidia De Azevedo Jaghoub | K8: 00992415284 | L8: lidiaazevedo@outlook.com | M8: 5569993943388 | N8: F | O8: 21/11/2000 | P8: KIT PARTICIPAÇÃO | Q8: 10KM | R8: 149,90 | S8: 14,99 | T8: 0,00 | U8: 149,90 | V8: 76801492 | W8: Rua Jamary | X8: 1823 | Y8: pedrinhas | Z8: Porto Velho | AA8: RO | AB8: Brasil | AD8: PP | AF8: PP | AG8: Lidia De Azevedo Jaghoub | AH8: lidiaazevedo@outlook.com | AI8: 00992415284
A9: 12524548 | B9: 28/04/2026 14:03 | C9: Cancelado | D9: Started | E9: 86647 | F9: Porto Velho | G9: 26/07/2026 | H9: FALSE | I9: 15298768 | J9: Flavia Barbosa Riela Cavalcante | K9: 85782742291 | L9: cafeparisro@gmail.com | M9: 5569993440047 | N9: F | O9: 23/04/1984 | P9: KIT PARTICIPAÇÃO | Q9: 5KM | R9: 149,90 | S9: 14,99 | T9: 0,00 | U9: 149,90 | Z9: Porto Velho | AA9: RO | AB9: Brasil | AC9: P | AF9: P | AG9: Leandro Da Silva Cavalcante | AH9: leandrosilvasil007@gmail.com | AI9: 02529638225
A10: 12524551 | B10: 28/04/2026 14:22 | C10: Pago | D10: Cartão Crédito | E10: 86645 | F10: Manaus | G10: 30/08/2026 | H10: FALSE | I10: 15298772 | J10: Claudia Rejane Facanha | K10: 55945538272 | L10: claudia.rejane1907@gmail.com | M10: 92992253847 | N10: F | O10: 09/07/1974 | P10: KIT PARTICIPAÇÃO | Q10: 5KM | R10: 149,90 | S10: 14,99 | T10: 0,00 | U10: 149,90 | V10: 69060020 | W10: Avenida Ephigênio Salles | X10: 1835 | Y10: Aleixo | Z10: Manaus | AA10: AM | AB10: Brasil | AC10: P | AF10: P | AG10: Adenor De Lima | AH10: adenor.lima33@gmail.com | AI10: 19277237287
A11: 12524551 | B11: 28/04/2026 14:22 | C11: Pago | D11: Cartão Crédito | E11: 86645 | F11: Manaus | G11: 30/08/2026 | H11: FALSE | I11: 15298771 | J11: Adenor De Lima | K11: 19277237287 | L11: adenor.lima33@gmail.com | M11: 92981339951 | N11: M | O11: 12/08/1964 | P11: KIT PARTICIPAÇÃO | Q11: 5KM | R11: 149,90 | S11: 7,50 | T11: 74,95 | U11: 74,95 | V11: 69060020 | W11: Avenida Ephigênio Salles | X11: 1835 | Y11: Aleixo | Z11: Manaus | AA11: AM | AB11: Brasil | AC11: M | AF11: M | AG11: Adenor De Lima | AH11: adenor.lima33@gmail.com | AI11: 19277237287
A12: 12524562 | B12: 28/04/2026 14:42 | C12: Pago | D12: Pix | E12: 86645 | F12: Manaus | G12: 30/08/2026 | H12: FALSE | I12: 15298786 | J12: Gustavo Turner | K12: 33202180851 | L12: gustavoturner@hotmail.com | N12: M | O12: 30/12/1981 | P12: KIT PARTICIPAÇÃO | Q12: 10KM | R12: 149,90 | S12: 14,99 | T12: 0,00 | U12: 149,90 | V12: 69054238 | W12: Rua Heisei | X12: 321 | Y12: Parque 10 de Novembro | Z12: Manaus | AA12: AM | AB12: Brasil | AD12: G | AF12: G | AG12: Gustavo Turner | AH12: gustavoturner@hotmail.com | AI12: 33202180851
A13: 12524572 | B13: 28/04/2026 14:42 | C13: Cancelado | D13: Started | E13: 86647 | F13: Porto Velho | G13: 26/07/2026 | H13: FALSE | I13: 15298797 | J13: Lucas Varnou Da Silva | K13: 00459663208 | L13: l.varnou@gmail.com | M13: 5569993684011 | N13: M | O13: 05/09/1990 | P13: KIT PARTICIPAÇÃO | Q13: 10KM | R13: 149,90 | S13: 14,99 | T13: 0,00 | U13: 149,90 | V13: 76817001 | W13: Rua Jardins | X13: 114 | Y13: Bairro novo | Z13: Porto Velho | AA13: RO | AB13: Brasil | AD13: M | AF13: M | AG13: Lucas Varnou Da Silva | AH13: l.varnou@gmail.com | AI13: 00459663208
A14: 12524658 | B14: 28/04/2026 14:46 | C14: Cancelado | D14: Started | E14: 86647 | F14: Porto Velho | G14: 26/07/2026 | H14: FALSE | I14: 15298889 | J14: Noel Leite Da Silva | K14: 52095223268 | L14: noelleitedasilva@hotmail.com | M14: 5569984314545 | N14: M | O14: 29/01/1982 | P14: KIT PARTICIPAÇÃO | Q14: 5KM | R14: 149,90 | S14: 14,99 | T14: 0,00 | U14: 149,90 | V14: 76.821460 | W14: Casa | X14: 4670 | Y14: Rio Madeira | Z14: Porto Velho | AA14: RO | AB14: Brasil | AC14: XG | AF14: XG | AG14: Noel Leite Da Silva | AH14: noelleitedasilva@hotmail.com | AI14: 52095223268
A15: 12524659 | B15: 28/04/2026 14:09 | C15: Cancelado | D15: Started | E15: 86645 | F15: Manaus | G15: 30/08/2026 | H15: FALSE | I15: 15298890 | J15: Luciana Maria Pinheiro De Freitas | K15: 66416671204 | L15: lmcpinheiro@gmail.com | M15: 5592981118966 | N15: F | O15: 04/04/1981 | P15: KIT PARTICIPAÇÃO | Q15: 5KM | R15: 149,90 | S15: 14,99 | T15: 0,00 | U15: 149,90 | V15: 69083120 | W15: Rua Nelson Batista De Sales | X15: 01 | Y15: Aleixo | Z15: Manaus | AA15: AM | AB15: Brasil | AC15: M | AF15: M | AG15: Luciana Maria Pinheiro De Freitas | AH15: lmcpinheiro@gmail.com | AI15: 66416671204
A16: 12524669 | B16: 28/04/2026 14:55 | C16: Cancelado | D16: Started | E16: 86647 | F16: Porto Velho | G16: 26/07/2026 | H16: FALSE | I16: 15298900 | J16: Luciana Martins De Matos | K16: 84688700210 | L16: mluciana012@gmail.com | M16: 5569993561848 | N16: F | O16: 27/08/1983 | P16: KIT PARTICIPAÇÃO | Q16: 5KM | R16: 149,90 | S16: 14,99 | T16: 0,00 | U16: 149,90 | V16: 76860000 | W16: Rua Rio Branco | X16: 608 | Y16: União | Z16: Candeias do Jamari | AA16: RO | AB16: Brasil | AC16: P | AF16: P | AG16: Luciana Martins De Matos | AH16: mluciana012@gmail.com | AI16: 84688700210
A17: 12524679 | B17: 28/04/2026 14:07 | C17: Pago | D17: Cartão Crédito/Mastercard | E17: 86645 | F17: Manaus | G17: 30/08/2026 | H17: FALSE | I17: 15298915 | J17: Alexsandro Silva Souza | K17: 84289244220 | L17: x.sandro.souza@gmail.com | M17: 5592981477164 | N17: M | O17: 06/08/1986 | P17: KIT PARTICIPAÇÃO | Q17: 10KM | R17: 149,90 | S17: 14,99 | T17: 0,00 | U17: 149,90 | Z17: Manaus | AA17: AM | AB17: Brasil | AD17: M | AF17: M | AG17: Patricia Silva Souza | AH17: patty8044@hotmail.com | AI17: 74251791215
A18: 12524679 | B18: 28/04/2026 14:07 | C18: Pago | D18: Cartão Crédito/Mastercard | E18: 86645 | F18: Manaus | G18: 30/08/2026 | H18: FALSE | I18: 15298914 | J18: Patricia Silva Souza | K18: 74251791215 | L18: patty8044@hotmail.com | M18: 92991251520 | N18: F | O18: 24/03/1983 | P18: KIT PARTICIPAÇÃO | Q18: 10KM | R18: 149,90 | S18: 14,99 | T18: 0,00 | U18: 149,90 | Z18: Manaus | AA18: AM | AB18: Brasil | AD18: M | AF18: M | AG18: Patricia Silva Souza | AH18: patty8044@hotmail.com | AI18: 74251791215
A19: 12524708 | B19: 28/04/2026 14:00 | C19: Cancelado | D19: Started | E19: 86645 | F19: Manaus | G19: 30/08/2026 | H19: FALSE | I19: 15298946 | J19: Marcilene De Moraes Ferreira | K19: 36976970215 | L19: marcilenedmoraes@gmail.com | M19: 5592981275414 | N19: F | O19: 13/03/1970 | P19: KIT PARTICIPAÇÃO | Q19: 5KM | R19: 149,90 | S19: 14,99 | T19: 0,00 | U19: 149,90 | V19: 69097772 | W19: Rua Flora Rica | X19: 13 | Y19: Nova Cidade | Z19: Manaus | AA19: AM | AB19: Brasil | AC19: P | AF19: P | AG19: Marcilene De Moraes Ferreira | AH19: marcilenedmoraes@gmail.com | AI19: 36976970215
A20: 12524729 | B20: 28/04/2026 14:04 | C20: Pago | D20: Pix | E20: 86647 | F20: Porto Velho | G20: 26/07/2026 | H20: FALSE | I20: 15298970 | J20: Gecelia Do Socorro David Silva Macedo | K20: 63255189268 | L20: geceliamacedo@gmail.com | M20: 5569992728353 | N20: F | O20: 02/10/1978 | P20: KIT PARTICIPAÇÃO | Q20: 5KM | R20: 149,90 | S20: 14,99 | T20: 0,00 | U20: 149,90 | V20: 76824082 | W20: Rua Paulo Fortes | X20: 6308 | Y20: Aponiã | Z20: Porto Velho | AA20: RO | AB20: Brasil | AC20: G | AF20: G | AG20: Gecelia Do Socorro David Silva Macedo | AH20: geceliamacedo@gmail.com | AI20: 63255189268
A21: 12524729 | B21: 28/04/2026 14:04 | C21: Pago | D21: Pix | E21: 86647 | F21: Porto Velho | G21: 26/07/2026 | H21: FALSE | I21: 15298971 | J21: Humberto Junior Macedo Passos | K21: 18326382272 | L21: hjunior1322@gmail.com | M21: 5569993315474 | N21: M | O21: 10/01/1966 | P21: KIT PARTICIPAÇÃO | Q21: 5KM | R21: 149,90 | S21: 7,50 | T21: 74,95 | U21: 74,95 | V21: 76824082 | W21: Rua Paulo Fortes | X21: 6308 | Y21: Aponiã | Z21: Porto Velho | AA21: RO | AB21: Brasil | AC21: G | AF21: G | AG21: Gecelia Do Socorro David Silva Macedo | AH21: geceliamacedo@gmail.com | AI21: 63255189268
A22: 12524763 | B22: 28/04/2026 15:31 | C22: Cancelado | D22: Cartão Crédito/Mastercard | E22: 86647 | F22: Porto Velho | G22: 26/07/2026 | H22: FALSE | I22: 15299012 | J22: Ana Carolina Monteiro De Souza | K22: 02694846203 | L22: carolcla153@gmail.com | M22: 5569992379239 | N22: F | O22: 26/06/1996 | P22: KIT PARTICIPAÇÃO | Q22: 10KM | R22: 149,90 | S22: 14,99 | T22: 0,00 | U22: 149,90 | V22: 76824046 | W22: Paulo Fortes | X22: 6850 | Y22: Aponia | Z22: Porto Velho | AA22: RO | AB22: Brasil | AD22: PP | AF22: PP | AG22: Ana Carolina Monteiro De Souza | AH22: carolcla153@gmail.com | AI22: 02694846203
A23: 12524779 | B23: 28/04/2026 15:31 | C23: Pago | D23: Cartão Crédito/Visa | E23: 86647 | F23: Porto Velho | G23: 26/07/2026 | H23: FALSE | I23: 15299040 | J23: Wanderlea Lessa Mariaca | K23: 22099883220 | L23: wlmariaca@hotmail.com | M23: 69999843016 | N23: F | O23: 05/10/1966 | P23: KIT PARTICIPAÇÃO | Q23: 10KM | R23: 149,90 | S23: 7,50 | T23: 74,95 | U23: 74,95 | V23: 76803814 | W23: Rua Francisco Fonseca | X23: 1736 | Y23: São João Bosco | Z23: Porto Velho | AA23: RO | AB23: Brasil | AD23: PP | AF23: PP | AG23: Wanderlea Lessa Mariaca | AH23: wlmariaca@hotmail.com | AI23: 22099883220
A24: 12524785 | B24: 28/04/2026 15:57 | C24: Pago | D24: Pix | E24: 86647 | F24: Porto Velho | G24: 26/07/2026 | H24: FALSE | I24: 15299050 | J24: Lucas Varnou Da Silva | K24: 00459663208 | L24: l.varnou@gmail.com | M24: 5569993684011 | N24: M | O24: 05/09/1990 | P24: KIT PARTICIPAÇÃO | Q24: 5KM | R24: 149,90 | S24: 14,99 | T24: 0,00 | U24: 149,90 | V24: 76817001 | W24: Rua Jardins | X24: 114 | Y24: Bairro novo | Z24: Porto Velho | AA24: RO | AB24: Brasil | AC24: M | AF24: M | AG24: Lucas Varnou Da Silva | AH24: l.varnou@gmail.com | AI24: 00459663208
A25: 12524790 | B25: 28/04/2026 15:16 | C25: Cancelado | D25: Started | E25: 86645 | F25: Manaus | G25: 30/08/2026 | H25: FALSE | I25: 15299056 | J25: Leandro Nascimento Simao Filho | K25: 47289643291 | L25: leandrosimao.filho@hotmail.com | M25: 92991444679 | N25: M | O25: 26/10/1975 | P25: KIT PARTICIPAÇÃO | Q25: 10KM | R25: 149,90 | S25: 14,99 | T25: 0,00 | U25: 149,90 | V25: 69036520 | W25: Retiro Santa Luzia | X25: 350 | Y25: Santo Agostinho | Z25: Manaus | AA25: AM | AB25: Brasil | AD25: G | AF25: G | AG25: Leandro Nascimento Simao Filho | AH25: leandrosimao.filho@hotmail.com | AI25: 47289643291
A26: 12524797 | B26: 28/04/2026 15:06 | C26: Cancelado | D26: Started | E26: 86647 | F26: Porto Velho | G26: 26/07/2026 | H26: FALSE | I26: 15299063 | J26: Ivan Eduardo Carvalho Da Silva | K26: 02771531232 | L26: ivaneduardo233@gmail.com | M26: 5569993386672 | N26: M | O26: 01/09/1999 | P26: KIT PARTICIPAÇÃO | Q26: 5KM | R26: 149,90 | S26: 14,99 | T26: 0,00 | U26: 149,90 | V26: 76803892 | W26: Senador Alvaro Maia | X26: 2380 | Y26: São João bosco | Z26: Porto Velho | AA26: RO | AB26: Brasil | AC26: G | AF26: G | AG26: Ivan Eduardo Carvalho Da Silva | AH26: ivaneduardo233@gmail.com | AI26: 02771531232
A27: 12524799 | B27: 28/04/2026 15:21 | C27: Pago | D27: Pix | E27: 86645 | F27: Manaus | G27: 30/08/2026 | H27: FALSE | I27: 15299065 | J27: Rose Mary Silva De Araujo | K27: 24255459215 | L27: lui.dog@hotmail.com | M27: 92981201616 | N27: F | O27: 23/06/1962 | P27: KIT PARTICIPAÇÃO | Q27: 10KM | R27: 149,90 | S27: 7,50 | T27: 74,95 | U27: 74,95 | V27: 69054130 | W27: Rua Rainha Catarina, Conj. Vila Do Rei | X27: 12 | Y27: Parque 10 | Z27: Manaus | AA27: AM | AB27: Brasil | AD27: P | AF27: P | AG27: Rose Mary Silva De Araujo | AH27: lui.dog@hotmail.com | AI27: 24255459215
A28: 12524803 | B28: 28/04/2026 15:53 | C28: Pago | D28: Cartão Crédito | E28: 86645 | F28: Manaus | G28: 30/08/2026 | H28: FALSE | I28: 15299071 | J28: Kellem Da Silva Lopes | K28: 59836571272 | L28: eunice.ozaky@proverconsultores.com.br | M28: 92981339829 | N28: F | O28: 26/08/1977 | P28: KIT PARTICIPAÇÃO | Q28: 5KM | R28: 149,90 | S28: 14,99 | T28: 0,00 | U28: 149,90 | AC28: P | AF28: P | AG28: Eunice Ozaki Lopes Da Rosa | AH28: eunicelopes15@gmail.com | AI28: 34630317287
A29: 12524803 | B29: 28/04/2026 15:53 | C29: Pago | D29: Cartão Crédito | E29: 86645 | F29: Manaus | G29: 30/08/2026 | H29: FALSE | I29: 15299070 | J29: Joao Domingos Da Rosa | K29: 04427984827 | L29: eunice.ozaky@proverconsultores.com.br | M29: 92981339829 | N29: M | O29: 11/11/1962 | P29: KIT PARTICIPAÇÃO | Q29: 5KM | R29: 149,90 | S29: 7,50 | T29: 74,95 | U29: 74,95 | AC29: GG | AF29: GG | AG29: Eunice Ozaki Lopes Da Rosa | AH29: eunicelopes15@gmail.com | AI29: 34630317287
A30: 12524808 | B30: 28/04/2026 15:18 | C30: Pago | D30: Cartão Crédito | E30: 86647 | F30: Porto Velho | G30: 26/07/2026 | H30: FALSE | I30: 15299076 | J30: Rosalina Maria De Oliveira Sevegnani Nicocelli | K30: 40973590297 | L30: nikaanicocelli@gmail.com | M30: 69992150239 | N30: F | O30: 20/04/1973 | P30: KIT PARTICIPAÇÃO | Q30: 10KM | R30: 149,90 | S30: 14,99 | T30: 0,00 | U30: 149,90 | V30: 76803790 | W30: Rua Jose Ferreira Sobrinho | X30: 1604 | Y30: São João Bosco | Z30: Porto Velho | AA30: RO | AB30: Brasil | AD30: P | AF30: P | AG30: Rosalina Maria De Oliveira Sevegnani Nicocelli | AH30: nikaanicocelli@gmail.com | AI30: 40973590297
A31: 12524813 | B31: 28/04/2026 15:42 | C31: Pago | D31: Pix | E31: 86647 | F31: Porto Velho | G31: 26/07/2026 | H31: FALSE | I31: 15299081 | J31: Noel Leite Da Silva | K31: 52095223268 | L31: noelleitedasilva@hotmail.com | M31: 5569984314545 | N31: M | O31: 29/01/1982 | P31: KIT PARTICIPAÇÃO | Q31: 5KM | R31: 149,90 | S31: 14,99 | T31: 0,00 | U31: 149,90 | V31: 76.821460 | W31: Casa | X31: 4670 | Y31: Rio Madeira | Z31: Porto Velho | AA31: RO | AB31: Brasil | AC31: XG | AF31: XG | AG31: Noel Leite Da Silva | AH31: noelleitedasilva@hotmail.com | AI31: 52095223268
A32: 12524820 | B32: 28/04/2026 15:12 | C32: Pago | D32: Cartão Crédito | E32: 86651 | F32: Manaus Kids | G32: 29/08/2026 | H32: FALSE | I32: 15299088 | J32: Marina Carvalho Dib | K32: 09846066295 | L32: amyrdib@gmail.com | M32: 5592981389937 | N32: F | O32: 25/07/2021 | P32: KIT ATLETA | Q32: 100m - 5 a 6 anos | R32: 119,90 | S32: 11,99 | T32: 0,00 | U32: 119,90 | Z32: Manaus | AA32: AM | AB32: Brasil | AE32: 6 anos | AF32: 6 anos | AG32: Amyr Mussa Dib | AH32: amyrdib@gmail.com | AI32: 52803686287
A33: 12524822 | B33: 28/04/2026 15:28 | C33: Pago | D33: Pix | E33: 86647 | F33: Porto Velho | G33: 26/07/2026 | H33: FALSE | I33: 15299090 | J33: Shaiene Costa Silva | K33: 02340870216 | L33: shaienecostapvh@gmail.com | M33: 5569993200123 | N33: F | O33: 10/12/1992 | P33: KIT PARTICIPAÇÃO | Q33: 5KM | R33: 149,90 | S33: 14,99 | T33: 0,00 | U33: 149,90 | V33: 76829532 | W33: Amelia Farias | X33: 3540 | Y33: Tancredo Neves | Z33: Porto Velho | AA33: RO | AB33: Brasil | AC33: GG | AF33: GG | AG33: Shaiene Costa Silva | AH33: shaienecostapvh@gmail.com | AI33: 02340870216
A34: 12524826 | B34: 28/04/2026 15:36 | C34: Cancelado | D34: Pix | E34: 86645 | F34: Manaus | G34: 30/08/2026 | H34: FALSE | I34: 15299095 | J34: Shemilly Da Rocha Mauricio | K34: 04916496221 | L34: shemyrocha@gmail.com | M34: 5592984134231 | N34: F | O34: 23/12/1998 | P34: KIT PARTICIPAÇÃO | Q34: 5KM | R34: 149,90 | S34: 14,99 | T34: 0,00 | U34: 149,90 | V34: 69730000 | W34: Rua Antonio Vinhorte | X34: 154 | Y34: santo elias | Z34: Novo Airão | AA34: AM | AB34: Brasil | AC34: PP | AF34: PP | AG34: Soraia Rodrigues De Souza | AH34: soraiarodrigues833@gmail.com | AI34: 02703566220
A35: 12524831 | B35: 28/04/2026 15:56 | C35: Cancelado | D35: Started | E35: 86647 | F35: Porto Velho | G35: 26/07/2026 | H35: FALSE | I35: 15299101 | J35: Naiara Raquel Silva Carneiro | K35: 81499400225 | L35: naiarasraquel@gmail.com | M35: 5569999194572 | N35: F | O35: 18/09/1984 | P35: KIT PARTICIPAÇÃO | Q35: 5KM | R35: 149,90 | S35: 14,99 | T35: 0,00 | U35: 149,90 | V35: 76820108 | W35: Rua Joao Pedro Da Rocha | X35: 560 | Y35: Nova Porto Velho | Z35: Porto Velho | AA35: RO | AB35: Brasil | AC35: M | AF35: M | AG35: Naiara Raquel Silva Carneiro | AH35: naiarasraquel@gmail.com | AI35: 81499400225
A36: 12524895 | B36: 28/04/2026 15:54 | C36: Cancelado | D36: Started | E36: 86647 | F36: Porto Velho | G36: 26/07/2026 | H36: FALSE | I36: 15299178 | J36: Axelly Ashelley Gama Nobre | K36: 05492065238 | L36: axellyashelley@gmail.com | M36: 5569993839557 | N36: F | O36: 28/02/2007 | P36: KIT PARTICIPAÇÃO | Q36: 5KM | R36: 149,90 | S36: 14,99 | T36: 0,00 | U36: 149,90 | V36: 76824068 | W36: Rua Veleiro | X36: 6207 | Y36: Aponiã | Z36: Porto Velho | AA36: RO | AB36: Brasil | AC36: PP | AF36: PP | AG36: Axelly Ashelley Gama Nobre | AH36: axellyashelley@gmail.com | AI36: 05492065238
A37: 12524918 | B37: 28/04/2026 15:53 | C37: Pago | D37: Pix | E37: 86645 | F37: Manaus | G37: 30/08/2026 | H37: FALSE | I37: 15299206 | J37: Adalberto Ferreira De Oliveira | K37: 13569635287 | L37: adalberto2014@hotmail.com | M37: 81067467 | N37: M | O37: 07/01/1965 | P37: KIT PARTICIPAÇÃO | Q37: 10KM | R37: 149,90 | S37: 7,50 | T37: 74,95 | U37: 74,95 | V37: 69036800 | W37: rua 7 casa 31 quadra10 | X37: 31 | Y37: santo agostinho | Z37: Manaus | AA37: AM | AB37: Brasil | AD37: G | AF37: G | AG37: Bruna Vaneska L Vieira | AH37: bvieira.tam@gmail.com | AI37: 85007323268
A38: 12524921 | B38: 28/04/2026 15:17 | C38: Pago | D38: Pix | E38: 86647 | F38: Porto Velho | G38: 26/07/2026 | H38: FALSE | I38: 15299209 | J38: Ana B C S Moraes | K38: 02092094297 | L38: mad.csmoraes@gmail.com | M38: 5569999048231 | N38: F | O38: 21/08/1992 | P38: KIT PARTICIPAÇÃO | Q38: 5KM | R38: 149,90 | S38: 14,99 | T38: 0,00 | U38: 149,90 | V38: 76821405 | W38: R Eng Anysio Da Rocha Compasso | X38: 2165 | Y38: Rio Madeira | Z38: Porto Velho | AA38: RO | AB38: Brasil | AC38: PP | AF38: PP | AG38: Ana B C S Moraes | AH38: mad.csmoraes@gmail.com | AI38: 02092094297
A39: 12524959 | B39: 28/04/2026 15:19 | C39: Cancelado | D39: Pix | E39: 86647 | F39: Porto Velho | G39: 26/07/2026 | H39: FALSE | I39: 15299264 | J39: Isabeli Facanha | K39: 04489599250 | L39: belifacanha@gmail.com | M39: 5569992948864 | N39: F | O39: 29/01/2009 | P39: KIT PARTICIPAÇÃO | Q39: 5KM | R39: 149,90 | S39: 14,99 | T39: 0,00 | U39: 149,90 | V39: 76821405 | W39: Av. Engenheiro Anysio Da Rocha Compasso | X39: 6021 | Y39: Rio Madeira | Z39: Porto Velho | AA39: RO | AB39: Brasil | AC39: PP | AF39: PP | AG39: Isabeli Facanha | AH39: belifacanha@gmail.com | AI39: 04489599250
A40: 12524967 | B40: 28/04/2026 15:08 | C40: Cancelado | D40: Started | E40: 86645 | F40: Manaus | G40: 30/08/2026 | H40: FALSE | I40: 15299275 | J40: Marcilene Machado Batista | K40: 58829270210 | L40: marcikka.batista@gmail.com | M40: 92985345697 | N40: F | O40: 11/04/1976 | P40: KIT PARTICIPAÇÃO | Q40: 5KM | R40: 149,90 | S40: 14,99 | T40: 0,00 | U40: 149,90 | V40: 69033000 | W40: Avenida São Jorge | X40: 253 | Y40: São Jorge | Z40: Manaus | AA40: AM | AB40: Brasil | AC40: P | AF40: P | AG40: Marcilene Machado Batista | AH40: marcikka.batista@gmail.com | AI40: 58829270210
A41: 12524978 | B41: 28/04/2026 15:09 | C41: Pago | D41: Cartão Crédito/Visa | E41: 86647 | F41: Porto Velho | G41: 26/07/2026 | H41: FALSE | I41: 15299287 | J41: Jaqueline Rangel De Sousa | K41: 02966458267 | L41: jaquesousar@gmail.com | M41: (69) 99223-8724 | N41: F | O41: 25/12/1996 | P41: KIT PARTICIPAÇÃO | Q41: 5KM | R41: 149,90 | S41: 14,99 | T41: 0,00 | U41: 149,90 | V41: 76829272 | W41: Rua Voluntários da Pátria | X41: 2923 | Y41: Socialista | Z41: Porto Velho | AA41: RO | AB41: Brasil | AC41: PP | AF41: PP | AG41: Jaqueline Rangel De Sousa | AH41: jaquesousar@gmail.com | AI41: 02966458267
A42: 12524998 | B42: 28/04/2026 15:57 | C42: Pago | D42: Pix | E42: 86645 | F42: Manaus | G42: 30/08/2026 | H42: FALSE | I42: 15299312 | J42: Shemilly Da Rocha Mauricio | K42: 04916496221 | L42: shemyrocha@gmail.com | M42: 5592984134231 | N42: F | O42: 23/12/1998 | P42: KIT PARTICIPAÇÃO | Q42: 5KM | R42: 149,90 | S42: 14,99 | T42: 0,00 | U42: 149,90 | V42: 69730000 | W42: Rua Antonio Vinhorte | X42: 154 | Y42: santo elias | Z42: Novo Airão | AA42: AM | AB42: Brasil | AC42: PP | AF42: PP | AG42: Soraia Rodrigues De Souza | AH42: soraiarodrigues833@gmail.com | AI42: 02703566220
A43: 12525007 | B43: 28/04/2026 15:50 | C43: Cancelado | D43: Started | E43: 86647 | F43: Porto Velho | G43: 26/07/2026 | H43: FALSE | I43: 15299329 | J43: Davi Cristian Menezes Castro | K43: 03542595209 | L43: davicristiansccp@gmail.com | M43: 69999502002 | N43: M | O43: 25/07/2002 | P43: KIT PARTICIPAÇÃO | Q43: 5KM | R43: 149,90 | S43: 14,99 | T43: 0,00 | U43: 149,90 | V43: 76808336 | W43: Rua Madagascar | X43: 3951 | Y43: Conceição | Z43: Porto Velho | AA43: RO | AB43: Brasil | AC43: M | AF43: M | AG43: Davi Cristian Menezes Castro | AH43: davicristiansccp@gmail.com | AI43: 03542595209
A44: 12525018 | B44: 28/04/2026 15:34 | C44: Pago | D44: Pix | E44: 86645 | F44: Manaus | G44: 30/08/2026 | H44: FALSE | I44: 15299343 | J44: Vera Lucia Cajaty | K44: 66302234204 | L44: cajaty.vera@gmail.com | M44: (92) 98201-1594 | N44: F | O44: 18/09/1976 | P44: KIT PARTICIPAÇÃO | Q44: 5KM | R44: 149,90 | S44: 14,99 | T44: 0,00 | U44: 149,90 | AC44: M | AF44: M | AG44: Christian Melo Cajaty | AH44: curubasrun@gmail.com | AI44: 61242403604
A45: 12525029 | B45: 28/04/2026 15:30 | C45: Pago | D45: Cartão Crédito | E45: 86645 | F45: Manaus | G45: 30/08/2026 | H45: FALSE | I45: 15299356 | J45: Edinelza Pereira Da Silva | K45: 11190868253 | L45: edbonates@hotmail.com | M45: 5592991285544 | N45: F | O45: 08/01/1958 | P45: KIT PARTICIPAÇÃO | Q45: 5KM | R45: 149,90 | S45: 7,50 | T45: 74,95 | U45: 74,95 | Z45: Manaus | AA45: AM | AB45: Brasil | AC45: M | AF45: M | AG45: Priscilla Rodrigues Martins | AH45: priscilla_pe@hotmail.com | AI45: 04163306498
A46: 12525029 | B46: 28/04/2026 15:30 | C46: Pago | D46: Cartão Crédito | E46: 86645 | F46: Manaus | G46: 30/08/2026 | H46: FALSE | I46: 15299355 | J46: Priscilla Rodrigues Martins | K46: 04163306498 | L46: priscilla_pe@hotmail.com | M46: 92982778898 | N46: F | O46: 10/04/1984 | P46: KIT PARTICIPAÇÃO | Q46: 5KM | R46: 149,90 | S46: 14,99 | T46: 0,00 | U46: 149,90 | Z46: Manaus | AA46: AM | AB46: Brasil | AC46: M | AF46: M | AG46: Priscilla Rodrigues Martins | AH46: priscilla_pe@hotmail.com | AI46: 04163306498
A47: 12525033 | B47: 28/04/2026 15:40 | C47: Cancelado | D47: Cartão Crédito/Visa | E47: 86645 | F47: Manaus | G47: 30/08/2026 | H47: FALSE | I47: 15299359 | J47: danielle andrade de carvalho | K47: 18350992 | L47: danielle.santosandrade@gmail.com | M47: 92995204246 | N47: F | O47: 05/10/1984 | P47: KIT PARTICIPAÇÃO | Q47: 10KM | R47: 149,90 | S47: 14,99 | T47: 0,00 | U47: 149,90 | V47: 69041770 | W47: Casa | X47: 3 | Y47: Tarumã | Z47: Manaus | AA47: AM | AB47: Brasil | AD47: P | AF47: P | AG47: danielle andrade de carvalho | AH47: danielle.santosandrade@gmail.com | AI47: 18350992
A48: 12525038 | B48: 28/04/2026 15:31 | C48: Cancelado | D48: Started | E48: 86647 | F48: Porto Velho | G48: 26/07/2026 | H48: FALSE | I48: 15299367 | J48: Axelly Ashelley | K48: 15979849220 | L48: axellynobre@gmail.com | M48: 5569993839557 | N48: F | O48: 28/02/2007 | P48: KIT PARTICIPAÇÃO | Q48: 5KM | R48: 149,90 | S48: 14,99 | T48: 0,00 | U48: 149,90 | Z48: Porto Velho | AA48: RO | AB48: Brasil | AC48: PP | AF48: PP | AG48: Axelly Ashelley Gama Nobre | AH48: axellyashelley@gmail.com | AI48: 05492065238
A49: 12525054 | B49: 28/04/2026 15:04 | C49: Pago | D49: Pix | E49: 86647 | F49: Porto Velho | G49: 26/07/2026 | H49: FALSE | I49: 15299384 | J49: Edu Wayne | K49: 83635009253 | L49: educivil.eng@gmail.com | M49: 06993238667 | N49: M | O49: 10/03/1986 | P49: KIT PARTICIPAÇÃO | Q49: 10KM | R49: 149,90 | S49: 14,99 | T49: 0,00 | U49: 149,90 | V49: 76810154 | W49: Rua Caetano Donizete | X49: 2400 | Y49: Novo Horizonte | Z49: Porto Velho | AA49: RO | AB49: Brasil | AD49: P | AF49: P | AG49: Edu Wayne | AH49: educivil.eng@gmail.com | AI49: 83635009253
A50: 12525059 | B50: 28/04/2026 15:49 | C50: Cancelado | D50: Started | E50: 86647 | F50: Porto Velho | G50: 26/07/2026 | H50: FALSE | I50: 15299389 | J50: Renan Douglas Costa Mesquita | K50: 02808807236 | L50: renan.mesquita.184@hotmail.com | M50: 5569992612216 | N50: M | O50: 26/04/2002 | P50: KIT PARTICIPAÇÃO | Q50: 5KM | R50: 149,90 | S50: 14,99 | T50: 0,00 | U50: 149,90 | V50: 76804138 | W50: Rua Dom Pedro Ii | X50: 2692 | Y50: Nossa senhora das graças | Z50: Porto Velho | AA50: RO | AB50: Brasil | AC50: M | AF50: M | AG50: Renan Douglas Costa Mesquita | AH50: renan.mesquita.184@hotmail.com | AI50: 02808807236
A51: 12525084 | B51: 28/04/2026 15:10 | C51: Cancelado | D51: Started | E51: 86647 | F51: Porto Velho | G51: 26/07/2026 | H51: FALSE | I51: 15299425 | J51: Vaniu Barros Cavalcante Junior | K51: 81113455349 | L51: vaniu@hotmail.com | M51: 69992479098 | N51: M | O51: 12/11/1980 | P51: KIT PARTICIPAÇÃO | Q51: 10KM | R51: 149,90 | S51: 14,99 | T51: 0,00 | U51: 149,90 | V51: 76810164 | W51: Rua Secundaria | X51: 1950 | Y51: Novo Horizonte | Z51: Porto Velho | AA51: RO | AB51: Brasil | AD51: M | AF51: M | AG51: Vaniu Barros Cavalcante Junior | AH51: vaniu@hotmail.com | AI51: 81113455349
A52: 12525087 | B52: 28/04/2026 15:40 | C52: Pago | D52: Pix | E52: 86645 | F52: Manaus | G52: 30/08/2026 | H52: FALSE | I52: 15299428 | J52: Paulo Roberto Braga Reis | K52: 12294454200 | L52: pr.repres@gmail.com | M52: 92981144970 | N52: M | O52: 25/07/1960 | P52: KIT PARTICIPAÇÃO | Q52: 10KM | R52: 149,90 | S52: 7,50 | T52: 74,95 | U52: 74,95 | V52: 69037000 | W52: Avenida Coronel Teixeira | X52: 4080 | Y52: Ponta Negra | Z52: Manaus | AA52: AM | AB52: Brasil | AD52: M | AF52: M | AG52: Bruna Vaneska L Vieira | AH52: bvieira.tam@gmail.com | AI52: 85007323268
A53: 12525092 | B53: 28/04/2026 15:26 | C53: Pago | D53: Pix | E53: 86647 | F53: Porto Velho | G53: 26/07/2026 | H53: FALSE | I53: 15299433 | J53: Carla Simone Alves | K53: 92898831204 | L53: carla.simonemartins01@gmail.com | M53: 5569992142220 | N53: F | O53: 17/11/1986 | P53: KIT PARTICIPAÇÃO | Q53: 5KM | R53: 149,90 | S53: 14,99 | T53: 0,00 | U53: 149,90 | V53: 76820488 | W53: Rua Fonte Nova | X53: 4874 | Y53: Flodoaldo | Z53: Porto Velho | AA53: RO | AB53: Brasil | AC53: PP | AF53: PP | AG53: Edu Wayne | AH53: educivil.eng@gmail.com | AI53: 83635009253
A54: 12525093 | B54: 28/04/2026 15:36 | C54: Cancelado | D54: Started | E54: 86648 | F54: Boa Vista | G54: 11/10/2026 | H54: FALSE | I54: 15299436 | J54: Josué Gomes Da Silva | K54: 82539839215 | L54: josuesempre@hotmail.com | M54: 95991334327 | N54: M | O54: 19/07/1986 | P54: KIT PARTICIPAÇÃO | Q54: 10KM | R54: 149,90 | S54: 14,99 | T54: 0,00 | U54: 149,90 | V54: 69317328 | W54: Rua Cidade Cascavel | X54: 179 | Y54: Equatorial | Z54: Boa Vista | AA54: RR | AB54: Brasil | AD54: PP | AF54: PP | AG54: Josué Gomes Da Silva | AH54: josuesempre@hotmail.com | AI54: 82539839215
A55: 12525137 | B55: 28/04/2026 15:33 | C55: Cancelado | D55: Started | E55: 86645 | F55: Manaus | G55: 30/08/2026 | H55: FALSE | I55: 15299490 | J55: Kellen Muller | K55: 70638675200 | L55: kellmuller@hotmail.com | M55: 092981103336 | N55: F | O55: 04/08/1980 | P55: KIT PARTICIPAÇÃO | Q55: 5KM | R55: 149,90 | S55: 14,99 | T55: 0,00 | U55: 149,90 | V55: 69093415 | W55: Avenida Torquato Tapajos | X55: 7726 | Y55: Colonia Terra Nova | Z55: Manaus | AA55: AM | AB55: Brasil | AC55: M | AF55: M | AG55: Kellen Muller | AH55: kellmuller@hotmail.com | AI55: 70638675200
A56: 12525139 | B56: 28/04/2026 15:37 | C56: Cancelado | D56: Cartão Crédito/Visa | E56: 86645 | F56: Manaus | G56: 30/08/2026 | H56: FALSE | I56: 15299494 | J56: Valeria Liborio De Brito | K56: 78355842200 | L56: valiborio@gmail.com | M56: 92981790887 | N56: F | O56: 10/09/1987 | P56: KIT PARTICIPAÇÃO | Q56: 5KM | R56: 149,90 | S56: 14,99 | T56: 0,00 | U56: 149,90 | V56: 69050010 | W56: Av Djalma Batista | X56: 1719 | Y56: Chapada | Z56: Manaus | AA56: AM | AB56: Brasil | AC56: M | AF56: M | AG56: Valeria Liborio De Brito | AH56: valiborio@gmail.com | AI56: 78355842200
A57: 12525147 | B57: 28/04/2026 15:02 | C57: Cancelado | D57: Started | E57: 86647 | F57: Porto Velho | G57: 26/07/2026 | H57: FALSE | I57: 15299502 | J57: Ueslen Reis Barroso | K57: 84790008215 | L57: uesmanieri@gmail.com | M57: 5569993908855 | N57: M | O57: 09/10/1986 | P57: KIT PARTICIPAÇÃO | Q57: 10KM | R57: 149,90 | S57: 14,99 | T57: 0,00 | U57: 149,90 | V57: 76829302 | W57: Rua Felipe Dos Santos | X57: 8359 | Y57: JK1 | Z57: Porto Velho | AA57: RO | AB57: Brasil | AD57: G | AF57: G | AG57: Ueslen Reis Barroso | AH57: uesmanieri@gmail.com | AI57: 84790008215
A58: 12525149 | B58: 28/04/2026 15:08 | C58: Cancelado | D58: Started | E58: 86647 | F58: Porto Velho | G58: 26/07/2026 | H58: FALSE | I58: 15299504 | J58: Fabiana Dos Santos Botelho | K58: 04652303262 | L58: botelhofabiana07@gmail.com | M58: 5569993644604 | N58: F | O58: 18/11/1999 | P58: KIT PARTICIPAÇÃO | Q58: 5KM | R58: 149,90 | S58: 14,99 | T58: 0,00 | U58: 149,90 | V58: 76824720 | W58: Irani Gadelha | X58: 5491 | Y58: escola de policia | Z58: Porto Velho | AA58: RO | AB58: Brasil | AC58: PP | AF58: PP | AG58: Fabiana Dos Santos Botelho | AH58: botelhofabiana07@gmail.com | AI58: 04652303262
A59: 12525176 | B59: 28/04/2026 15:49 | C59: Pago | D59: Pix | E59: 86647 | F59: Porto Velho | G59: 26/07/2026 | H59: FALSE | I59: 15299540 | J59: Paulo Vitor Alevs Miranda Chaves | K59: 75280990230 | L59: vitor2713@gmail.com | M59: (69) 99353-4242 | N59: F | O59: 27/03/1984 | P59: KIT PARTICIPAÇÃO | Q59: 5KM | R59: 149,90 | S59: 14,99 | T59: 0,00 | U59: 149,90 | V59: 76803564 | W59: Rua São Luiz | X59: 2948 | Y59: costa e silva | Z59: porto velho | AA59: RO | AB59: Brasil | AC59: G | AF59: G | AG59: Paulo Vitor Alevs Miranda Chaves | AH59: vitor2713@gmail.com | AI59: 75280990230
A60: 12525179 | B60: 28/04/2026 15:05 | C60: Cancelado | D60: Started | E60: 86647 | F60: Porto Velho | G60: 26/07/2026 | H60: FALSE | I60: 15299544 | J60: Jose Antonio Araujo Gil | K60: 31556485204 | L60: jaantoniogil@gmail.com | M60: 69993136930 | N60: M | O60: 23/06/1968 | P60: KIT PARTICIPAÇÃO | Q60: 5KM | R60: 149,90 | S60: 14,99 | T60: 0,00 | U60: 149,90 | V60: 76803776 | W60: Salgado Filho | X60: 3446 | Y60: Sao joao bosco | Z60: Porto Velho | AA60: RO | AB60: Brasil | AC60: M | AF60: M | AG60: Jose Antonio Araujo Gil | AH60: jaantoniogil@gmail.com | AI60: 31556485204
A61: 12525196 | B61: 28/04/2026 15:46 | C61: Pago | D61: Pix | E61: 86645 | F61: Manaus | G61: 30/08/2026 | H61: FALSE | I61: 15299562 | J61: Alvaro Augusto Meninea | K61: 73007749700 | L61: alvaromeninea@hotmail.com | M61: 92988024359 | N61: M | O61: 23/09/1965 | P61: KIT PARTICIPAÇÃO | Q61: 10KM | R61: 149,90 | S61: 7,50 | T61: 74,95 | U61: 74,95 | V61: 69053578 | W61: Rua Nova Palma | X61: 345 | Y61: Nossa Senhora das Graças | Z61: Manaus | AA61: AM | AB61: Brasil | AD61: G | AF61: G | AG61: Alvaro Augusto Meninea | AH61: alvaromeninea@hotmail.com | AI61: 73007749700
A62: 12525200 | B62: 28/04/2026 15:00 | C62: Cancelado | D62: Started | E62: 86645 | F62: Manaus | G62: 30/08/2026 | H62: FALSE | I62: 15299566 | J62: Aline Nogueira Da Silva | K62: 01372268294 | L62: vitoriaealine197@gmail.com | M62: 5592985905465 | N62: F | O62: 05/07/1992 | P62: KIT PARTICIPAÇÃO | Q62: 5KM | R62: 149,90 | S62: 14,99 | T62: 0,00 | U62: 149,90 | V62: 69099132 | W62: Rua Vila Lobos, | X62: 65 | Y62: Cidade de Deus | Z62: Manaus | AA62: AM | AB62: Brasil | AC62: G | AF62: G | AG62: Aline Nogueira Da Silva | AH62: vitoriaealine197@gmail.com | AI62: 01372268294
A63: 12525212 | B63: 28/04/2026 15:58 | C63: Cancelado | D63: Started | E63: 86647 | F63: Porto Velho | G63: 26/07/2026 | H63: FALSE | I63: 15299579 | J63: Juliano Amora Couceiro | K63: 35091363220 | L63: Juliano.tjro@gmail.com | M63: 69992183000 | N63: M | O63: 28/01/1973 | P63: KIT PARTICIPAÇÃO | Q63: 10KM | R63: 149,90 | S63: 14,99 | T63: 0,00 | U63: 149,90 | V63: 76801144 | W63: Jose Bonifacio | X63: 615 | Y63: Caiari | Z63: Porto Velho | AA63: RO | AB63: Brasil | AD63: M | AF63: M | AG63: Juliano Amora Couceiro | AH63: Juliano.tjro@gmail.com | AI63: 35091363220
A64: 12525217 | B64: 28/04/2026 15:30 | C64: Pago | D64: Cartão Crédito | E64: 86647 | F64: Porto Velho | G64: 26/07/2026 | H64: FALSE | I64: 15299585 | J64: Elizangela Da Silva Queiroz Falcao | K64: 98544667287 | L64: elizfalcao123@gmail.com | M64: 556993441577 | N64: F | O64: 29/12/1985 | P64: KIT PARTICIPAÇÃO | Q64: 10KM | R64: 149,90 | S64: 14,99 | T64: 0,00 | U64: 149,90 | V64: 76808554 | W64: Bartolomeu Pereira | X64: 2832 | Y64: Eletronorte | Z64: Porto Velho | AA64: RO | AB64: Brasil | AD64: PP | AF64: PP | AG64: Elizangela Da Silva Queiroz Falcao | AH64: elizfalcao123@gmail.com | AI64: 98544667287
A65: 12525220 | B65: 28/04/2026 15:44 | C65: Pago | D65: Pix | E65: 86645 | F65: Manaus | G65: 30/08/2026 | H65: FALSE | I65: 15299588 | J65: Maria Da Conceicao Pereira | K65: 44204795234 | L65: thaissuellenpereira@hotmail.com | M65: 9299359234 | N65: F | O65: 08/12/1959 | P65: KIT PARTICIPAÇÃO | Q65: 5KM | R65: 149,90 | S65: 7,50 | T65: 74,95 | U65: 74,95 | V65: 69099027 | W65: Rua Herculano de Souza | X65: 301 | Y65: Novo Aleixo | Z65: manaus | AA65: AM | AB65: Brasil | AC65: M | AF65: M | AG65: Maria Da Conceicao Pereira | AH65: thaissuellenpereira@hotmail.com | AI65: 44204795234
A66: 12525236 | B66: 28/04/2026 15:07 | C66: Pago | D66: Cartão Crédito/Mastercard | E66: 86645 | F66: Manaus | G66: 30/08/2026 | H66: FALSE | I66: 15299612 | J66: Dayanne Pinheiro | K66: 60926511220 | L66: dayannepinheiro@hotmail.com | M66: 92981384243 | N66: F | O66: 08/11/1977 | P66: KIT PARTICIPAÇÃO | Q66: 10KM | R66: 149,90 | S66: 14,99 | T66: 0,00 | U66: 149,90 | V66: 69060085 | W66: Avenida Via Láctea | X66: 1086 | Y66: Aleixo | Z66: Manaus | AA66: AM | AB66: Brasil | AD66: P | AF66: P | AG66: Dayanne Pinheiro | AH66: dayannepinheiro@hotmail.com | AI66: 60926511220
A67: 12525250 | B67: 28/04/2026 15:30 | C67: Pago | D67: Cartão Crédito | E67: 86645 | F67: Manaus | G67: 30/08/2026 | H67: FALSE | I67: 15299628 | J67: Daniel De Deus Brandao Dias | K67: 95035168204 | L67: daniel_brandao6@hotmail.com | M67: 92991171442 | N67: M | O67: 17/08/1991 | P67: KIT PARTICIPAÇÃO | Q67: 5KM | R67: 149,90 | S67: 14,99 | T67: 0,00 | U67: 149,90 | V67: 69093132 | W67: Rua E | X67: 99 | Y67: Nova Cidade | Z67: Manaus | AA67: AM | AB67: Brasil | AC67: GG | AF67: GG | AG67: Marivone Brandao De Lima | AH67: marivone-brandao@hotmail.com | AI67: 50899570291
A68: 12525253 | B68: 28/04/2026 15:43 | C68: Cancelado | D68: Started | E68: 86645 | F68: Manaus | G68: 30/08/2026 | H68: FALSE | I68: 15299632 | J68: Karen Priscilla Silva Pimentel Pereira | K68: 12928622705 | L68: karenp.pimentel@gmail.com | M68: 92981270247 | N68: F | O68: 28/09/1987 | P68: KIT PARTICIPAÇÃO | Q68: 5KM | R68: 149,90 | S68: 14,99 | T68: 0,00 | U68: 149,90 | V68: 69074217 | W68: Rua Dea Alencar | X68: 2228 | Y68: Sao Lazaro | Z68: Manaus | AA68: AM | AB68: Brasil | AC68: G | AF68: G | AG68: Karen Priscilla Silva Pimentel Pereira | AH68: karenp.pimentel@gmail.com | AI68: 12928622705
A69: 12525257 | B69: 28/04/2026 15:08 | C69: Pago | D69: Pix | E69: 86647 | F69: Porto Velho | G69: 26/07/2026 | H69: FALSE | I69: 15299636 | J69: Rosbergue Rodrigues Xisto | K69: 00383858216 | L69: bergxisto@gmail.com | M69: 5569992962851 | N69: M | O69: 06/04/1990 | P69: KIT PARTICIPAÇÃO | Q69: 10KM | R69: 149,90 | S69: 14,99 | T69: 0,00 | U69: 149,90 | V69: 76808630 | W69: Rua Seringueiras | X69: 3128 | Y69: Eletronorte | Z69: Porto Velho | AA69: RO | AB69: Brasil | AD69: M | AF69: M | AG69: Rosbergue Rodrigues Xisto | AH69: bergxisto@gmail.com | AI69: 00383858216
A70: 12525260 | B70: 28/04/2026 15:21 | C70: Cancelado | D70: Started | E70: 86647 | F70: Porto Velho | G70: 26/07/2026 | H70: FALSE | I70: 15299640 | J70: Adriana Cordeiro De Lima Maia | K70: 42163439291 | L70: adri.cordeirolimamaia@gmail.com | M70: 5569992254289 | N70: F | O70: 30/09/1972 | P70: KIT PARTICIPAÇÃO | Q70: 5KM | R70: 149,90 | S70: 14,99 | T70: 0,00 | U70: 149,90 | V70: 76810156 | W70: Rua Joao Paulo L | X70: 2400 | Y70: Novo horizonte | Z70: Porto Velho | AA70: RO | AB70: Brasil | AC70: G | AF70: G | AG70: Adriana Cordeiro De Lima Maia | AH70: adri.cordeirolimamaia@gmail.com | AI70: 42163439291
A71: 12525266 | B71: 28/04/2026 15:58 | C71: Cancelado | D71: Started | E71: 86645 | F71: Manaus | G71: 30/08/2026 | H71: FALSE | I71: 15299648 | J71: Adriane Barroso De Miranda | K71: 94740674220 | L71: a05barroso86@gmail.com | M71: 55929933271 | N71: F | O71: 06/05/1986 | P71: KIT PARTICIPAÇÃO | Q71: 5KM | R71: 149,90 | S71: 14,99 | T71: 0,00 | U71: 149,90 | V71: 69080293 | W71: Rua Paula Francinete | X71: 102 | Y71: Coroado | Z71: Manaus | AA71: AM | AB71: Brasil | AC71: M | AF71: M | AG71: Adriane Barroso De Miranda | AH71: a05barroso86@gmail.com | AI71: 94740674220
A72: 12525273 | B72: 28/04/2026 15:38 | C72: Cancelado | D72: Pix | E72: 86647 | F72: Porto Velho | G72: 26/07/2026 | H72: FALSE | I72: 15299657 | J72: Isabeli Facanha | K72: 04489599250 | L72: belifacanha@gmail.com | M72: 5569992948864 | N72: F | O72: 29/01/2009 | P72: KIT PARTICIPAÇÃO | Q72: 5KM | R72: 149,90 | S72: 14,99 | T72: 0,00 | U72: 149,90 | V72: 76821405 | W72: Av. Engenheiro Anysio Da Rocha Compasso | X72: 6021 | Y72: Rio Madeira | Z72: Porto Velho | AA72: RO | AB72: Brasil | AC72: PP | AF72: PP | AG72: Isabeli Facanha | AH72: belifacanha@gmail.com | AI72: 04489599250
A73: 12525275 | B73: 28/04/2026 15:45 | C73: Pago | D73: Cartão Crédito/Visa | E73: 86645 | F73: Manaus | G73: 30/08/2026 | H73: FALSE | I73: 15299659 | J73: Francisca Albuquerque Da Costa | K73: 49414127291 | L73: cintiacosta365@gmail.com | M73: (92) 98116-1649 | N73: F | O73: 18/11/1974 | P73: KIT PARTICIPAÇÃO | Q73: 5KM | R73: 149,90 | S73: 14,99 | T73: 0,00 | U73: 149,90 | AC73: M | AF73: M | AG73: Joelle Goncalves De Arruda Ricardo | AH73: joelle94@gmail.com | AI73: 00552568210
A74: 12525299 | B74: 28/04/2026 15:47 | C74: Pago | D74: Pix | E74: 86645 | F74: Manaus | G74: 30/08/2026 | H74: FALSE | I74: 15299686 | J74: Rubem Afonso Rocha Figueira | K74: 95593730210 | L74: rubem.figueira@outlook.com | M74: (91) 99196-3361 | N74: M | O74: 30/11/1988 | P74: KIT PARTICIPAÇÃO | Q74: 10KM | R74: 149,90 | S74: 14,99 | T74: 0,00 | U74: 149,90 | V74: 69055719 | W74: Travessa Muniz | X74: 58 | Y74: Parque 10 | Z74: Manaus | AA74: AM | AB74: Brasil | AD74: G | AF74: G | AG74: Rubem Afonso Rocha Figueira | AH74: rubem.figueira@outlook.com | AI74: 95593730210
A75: 12525307 | B75: 28/04/2026 15:25 | C75: Cancelado | D75: Started | E75: 86645 | F75: Manaus | G75: 30/08/2026 | H75: FALSE | I75: 15299696 | J75: Aline Rocha Martins | K75: 86288733253 | L75: alinerocha48@hotmail.com | M75: 92981019650 | N75: F | O75: 16/06/1984 | P75: KIT PARTICIPAÇÃO | Q75: 5KM | R75: 149,90 | S75: 14,99 | T75: 0,00 | U75: 149,90 | V75: 69058690 | W75: Rua Visconde De Caete | X75: 100 | Y75: Flores | Z75: Manaus | AA75: AM | AB75: Brasil | AC75: P | AF75: P | AG75: Lorena Michiles Veiga | AH75: lorenaveiga14@gmail.com | AI75: 90172183200
A76: 12525309 | B76: 28/04/2026 15:38 | C76: Cancelado | D76: Pix | E76: 86647 | F76: Porto Velho | G76: 26/07/2026 | H76: FALSE | I76: 15299698 | J76: Anderson Soares Cardoso | K76: 02080305220 | L76: anderson.ceu@gmail.com | M76: 5569984713656 | N76: M | O76: 03/09/1988 | P76: KIT PARTICIPAÇÃO | Q76: 5KM | R76: 149,90 | S76: 14,99 | T76: 0,00 | U76: 149,90 | V76: 76820832 | W76: Rua Duque De Caxias | X76: 3025 | Y76: Embratel | Z76: Porto Velho | AA76: RO | AB76: Brasil | AC76: M | AF76: M | AG76: Anderson Soares Cardoso | AH76: anderson.ceu@gmail.com | AI76: 02080305220
A77: 12525311 | B77: 28/04/2026 15:43 | C77: Cancelado | D77: Pix | E77: 86647 | F77: Porto Velho | G77: 26/07/2026 | H77: FALSE | I77: 15299702 | J77: Leticia Rani Pimenta Almeida | K77: 05915148344 | L77: leticiarani_@hotmail.com | M77: 556981446373 | N77: F | O77: 23/12/1994 | P77: KIT PARTICIPAÇÃO | Q77: 5KM | R77: 149,90 | S77: 14,99 | T77: 0,00 | U77: 149,90 | V77: 76820832 | W77: Duque De Caxias | X77: 3025 | Y77: Embratel | Z77: Porto Velho | AA77: RO | AB77: Brasil | AC77: P | AF77: P | AG77: Leticia Rani Pimenta Almeida | AH77: leticiarani_@hotmail.com | AI77: 05915148344
A78: 12525323 | B78: 28/04/2026 15:06 | C78: Cancelado | D78: Started | E78: 86651 | F78: Manaus Kids | G78: 29/08/2026 | H78: FALSE | I78: 15299715 | J78: Helena Vitoria De Souza Leite | K78: 06183071250 | L78: thaisgaby29@gmail.com | M78: 5592985974183 | N78: F | O78: 29/04/2017 | P78: KIT ATLETA | Q78: 200m - 7 a 10 anos | R78: 119,90 | S78: 11,99 | T78: 0,00 | U78: 119,90 | Z78: Manaus | AA78: AM | AB78: Brasil | AE78: 12 anos | AF78: 12 anos | AG78: Alisson Pantoja | AH78: lalittta29@gmail.com | AI78: 03911645201
A79: 12525324 | B79: 28/04/2026 15:07 | C79: Cancelado | D79: Started | E79: 86645 | F79: Manaus | G79: 30/08/2026 | H79: FALSE | I79: 15299716 | J79: Rocha Carvalho | K79: 24129992287 | L79: rocharun320@gmail.com | M79: 92991211315 | N79: M | O79: 25/05/1965 | P79: KIT PARTICIPAÇÃO | Q79: 10KM | R79: 149,90 | S79: 7,50 | T79: 74,95 | U79: 74,95 | V79: 69033230 | W79: Rua Castelo Branco | X79: 320 | Y79: Sao Jorge | Z79: Manaus | AA79: AM | AB79: Brasil | AD79: M | AF79: M | AG79: Rocha Carvalho | AH79: rocharun320@gmail.com | AI79: 24129992287
A80: 12525327 | B80: 28/04/2026 15:31 | C80: Pago | D80: Pix | E80: 86645 | F80: Manaus | G80: 30/08/2026 | H80: FALSE | I80: 15299720 | J80: Anne Caroline Serafim Garcia | K80: 96688998220 | L80: annevieira90@icloud.com | M80: 55929986152054 | N80: F | O80: 06/12/1990 | P80: KIT PARTICIPAÇÃO | Q80: 5KM | R80: 149,90 | S80: 14,99 | T80: 0,00 | U80: 149,90 | V80: 69058581 | W80: Rua Barao Do Rio Branco | X80: 699 | Y80: Flores | Z80: Manaus | AA80: AM | AB80: Brasil | AC80: PP | AF80: PP | AG80: Anne Caroline Serafim Garcia | AH80: annevieira90@icloud.com | AI80: 96688998220
A81: 12525346 | B81: 28/04/2026 15:06 | C81: Cancelado | D81: Started | E81: 86645 | F81: Manaus | G81: 30/08/2026 | H81: FALSE | I81: 15299742 | J81: Lorena Michiles Veiga | K81: 90172183200 | L81: lorenaveiga14@gmail.com | M81: 5592994644160 | N81: F | O81: 25/07/1991 | P81: KIT PARTICIPAÇÃO | Q81: 5KM | R81: 149,90 | S81: 14,99 | T81: 0,00 | U81: 149,90 | V81: 69038600 | W81: Rua Sao Joao Do Paraiso | X81: 6 | Y81: lirio do vale 2 | Z81: Manaus | AA81: AM | AB81: Brasil | AC81: P | AF81: P | AG81: Lorena Michiles Veiga | AH81: lorenaveiga14@gmail.com | AI81: 90172183200
A82: 12525355 | B82: 28/04/2026 15:04 | C82: Pago | D82: Pix | E82: 86647 | F82: Porto Velho | G82: 26/07/2026 | H82: FALSE | I82: 15299753 | J82: Valdemir Alves Sousa | K82: 84200960249 | L82: valdemircrj@hotmail.com | M82: 5569993106632 | N82: M | O82: 29/06/1984 | P82: KIT PARTICIPAÇÃO | Q82: 5KM | R82: 149,90 | S82: 14,99 | T82: 0,00 | U82: 149,90 | V82: 76997000 | W82: Rua Paraiba | X82: 504 | Y82: Eldorado | Z82: Cerejeiras | AA82: RO | AB82: Brasil | AC82: P | AF82: P | AG82: Valdemir Alves Sousa | AH82: valdemircrj@hotmail.com | AI82: 84200960249
A83: 12525363 | B83: 28/04/2026 15:33 | C83: Cancelado | D83: Started | E83: 86645 | F83: Manaus | G83: 30/08/2026 | H83: FALSE | I83: 15299761 | J83: Antonio Lucas Do Nascimento Junior | K83: 83244204287 | L83: antoniolucasjr@hotmail.com | M83: 5592994439398 | N83: M | O83: 09/11/1984 | P83: KIT PARTICIPAÇÃO | Q83: 5KM | R83: 149,90 | S83: 14,99 | T83: 0,00 | U83: 149,90 | V83: 69054672 | W83: Rua Misushiro | X83: 170 | Y83: Parque 10 de Novembro | Z83: Manaus | AA83: AM | AB83: Brasil | AC83: G | AF83: G | AG83: Antonio Lucas Do Nascimento Junior | AH83: antoniolucasjr@hotmail.com | AI83: 83244204287
A84: 12525365 | B84: 28/04/2026 15:44 | C84: Cancelado | D84: Started | E84: 86645 | F84: Manaus | G84: 30/08/2026 | H84: FALSE | I84: 15299763 | J84: JOYCE DA SILVA | K84: 52474798234 | L84: joycecaroline.mv@hotmail.com | M84: 55929851171 | N84: F | O84: 17/04/1982 | P84: KIT PARTICIPAÇÃO | Q84: 5KM | R84: 149,90 | S84: 14,99 | T84: 0,00 | U84: 149,90 | V84: 69063280 | W84: Rua Rodrigues Do Carmo | Y84: São Francisco | Z84: Manaus | AA84: AM | AB84: Brasil | AC84: G | AF84: G | AG84: JOYCE DA SILVA | AH84: joycecaroline.mv@hotmail.com | AI84: 52474798234
A85: 12525367 | B85: 28/04/2026 15:50 | C85: Cancelado | D85: Started | E85: 86647 | F85: Porto Velho | G85: 26/07/2026 | H85: FALSE | I85: 15299766 | J85: Fatineli Rodrigues Teixeira | K85: 02174242281 | L85: teixeirafatineli@gmail.com | M85: 5593818132 | N85: F | O85: 07/03/1992 | P85: KIT PARTICIPAÇÃO | Q85: 10KM | R85: 149,90 | S85: 14,99 | T85: 0,00 | U85: 149,90 | V85: 76808630 | W85: Avenida Campo Sales | X85: 3128 | Y85: Eletronorte | Z85: Porto Velho | AA85: RO | AB85: Brasil | AD85: PP | AF85: PP | AG85: Fatineli Rodrigues Teixeira | AH85: teixeirafatineli@gmail.com | AI85: 02174242281
A86: 12525375 | B86: 28/04/2026 16:43 | C86: Pago | D86: Pix | E86: 86645 | F86: Manaus | G86: 30/08/2026 | H86: FALSE | I86: 15299778 | J86: Roberia Alves Da Silva | K86: 28018292850 | L86: roberia39alves@gmail.com | M86: (92) 99318-5203 | N86: F | O86: 19/04/1979 | P86: KIT PARTICIPAÇÃO | Q86: 5KM | R86: 149,90 | S86: 14,99 | T86: 0,00 | U86: 149,90 | AC86: P | AF86: P | AG86: Joelle Goncalves De Arruda Ricardo | AH86: joelle94@gmail.com | AI86: 00552568210
A87: 12525380 | B87: 28/04/2026 16:32 | C87: Pago | D87: Pix | E87: 86645 | F87: Manaus | G87: 30/08/2026 | H87: FALSE | I87: 15299783 | J87: Ranyelle Lopes Barros | K87: 00712479201 | L87: ranyelle.barros@gmail.com | M87: 92929922449 | N87: F | O87: 29/07/1993 | P87: KIT PARTICIPAÇÃO | Q87: 5KM | R87: 149,90 | S87: 14,99 | T87: 0,00 | U87: 149,90 | V87: 69035510 | W87: Parque Ayapua | X87: 16 | Y87: PONTA NEGRA | Z87: Manaus | AA87: AM | AB87: Brasil | AC87: PP | AF87: PP | AG87: Ranyelle Lopes Barros | AH87: ranyelle.barros@gmail.com | AI87: 00712479201
A88: 12525382 | B88: 28/04/2026 16:41 | C88: Pago | D88: Cartão Crédito | E88: 86647 | F88: Porto Velho | G88: 26/07/2026 | H88: FALSE | I88: 15299785 | J88: Andonai Krauze De Franca | K88: 59952806272 | L88: andonai.krauze@gmail.com | M88: 69993990184 | N88: M | O88: 03/10/1977 | P88: KIT PARTICIPAÇÃO | Q88: 10KM | R88: 149,90 | S88: 14,99 | T88: 0,00 | U88: 149,90 | V88: 76828320 | W88: Rua Paulo Freire | X88: 9440 | Y88: Jardim Santana | Z88: Porto Velho | AA88: RO | AB88: Brasil | AD88: M | AF88: M | AG88: Andonai Krauze De Franca | AH88: andonai.krauze@gmail.com | AI88: 59952806272
A89: 12525383 | B89: 28/04/2026 16:41 | C89: Pago | D89: Cartão Crédito | E89: 86647 | F89: Porto Velho | G89: 26/07/2026 | H89: FALSE | I89: 15299786 | J89: Kamila Gomes De Souza | K89: 01142699200 | L89: kamsgoms@gmail.com | M89: 5569999119202 | N89: F | O89: 07/12/1994 | P89: KIT PARTICIPAÇÃO | Q89: 5KM | R89: 149,90 | S89: 14,99 | T89: 0,00 | U89: 149,90 | V89: 76820346 | W89: Rua Abnatal Bentes De Lima | X89: 1571 | Y89: Agenor de Carvalho | Z89: Porto Velho | AA89: RO | AB89: Brasil | AC89: G | AF89: G | AG89: Kamila Gomes De Souza | AH89: kamsgoms@gmail.com | AI89: 01142699200
A90: 12525388 | B90: 28/04/2026 16:52 | C90: Cancelado | D90: Started | E90: 86647 | F90: Porto Velho | G90: 26/07/2026 | H90: FALSE | I90: 15299792 | J90: Francisca Juscileide Do Nascimento Azevedo Pimenta | K90: 90437357287 | L90: juscileideazevedo@gmail.com | M90: 69999274754 | N90: F | O90: 17/01/1987 | P90: KIT PARTICIPAÇÃO | Q90: 10KM | R90: 149,90 | S90: 14,99 | T90: 0,00 | U90: 149,90 | V90: 76813292 | W90: Rua Professora Dolly Carvalho | X90: 8960 | Y90: São Francisco | Z90: Porto Velho | AA90: RO | AB90: Brasil | AD90: PP | AF90: PP | AG90: Francisca Juscileide Do Nascimento Azevedo Pimenta | AH90: juscileideazevedo@gmail.com | AI90: 90437357287
A91: 12525394 | B91: 28/04/2026 16:17 | C91: Pago | D91: Pix | E91: 86645 | F91: Manaus | G91: 30/08/2026 | H91: FALSE | I91: 15299800 | J91: Andreia Rodrigues Silva | K91: 80408729287 | L91: andreia37jayth@gmail.com | M91: (92) 99185-0067 | N91: F | O91: 15/05/1983 | P91: KIT PARTICIPAÇÃO | Q91: 10KM | R91: 149,90 | S91: 14,99 | T91: 0,00 | U91: 149,90 | AD91: M | AF91: M | AG91: Jayth Araujo Gomes | AH91: jayth.araujo@gmail.com | AI91: 82639949268
A92: 12525416 | B92: 28/04/2026 16:39 | C92: Cancelado | D92: Started | E92: 86647 | F92: Porto Velho | G92: 26/07/2026 | H92: FALSE | I92: 15299828 | J92: Kenilla Pagoto | K92: 88864421220 | L92: kenilla_jipa@hotmail.com | M92: 5569992562707 | N92: F | O92: 14/03/1988 | P92: KIT PARTICIPAÇÃO | Q92: 5KM | R92: 149,90 | S92: 14,99 | T92: 0,00 | U92: 149,90 | V92: 76820749 | W92: Rua Guiana | X92: 2904 | Y92: Embratel | Z92: Porto Velho | AA92: RO | AB92: Brasil | AC92: P | AF92: P | AG92: Kenilla Pagoto | AH92: kenilla_jipa@hotmail.com | AI92: 88864421220
A93: 12525422 | B93: 28/04/2026 16:11 | C93: Pago | D93: Cartão Crédito/Visa | E93: 86647 | F93: Porto Velho | G93: 26/07/2026 | H93: FALSE | I93: 15299834 | J93: Cristian Mar | K93: 42178967272 | L93: cristianpvh2@gmail.com | M93: 69984797830 | N93: M | O93: 25/10/1973 | P93: KIT PARTICIPAÇÃO | Q93: 10KM | R93: 149,90 | S93: 14,99 | T93: 0,00 | U93: 149,90 | V93: 76806170 | W93: Rua Aluizio Bentes | X93: 717 | Y93: Floresta | Z93: Porto Velho | AA93: RO | AB93: Brasil | AD93: G | AF93: G | AG93: Cristian Mar | AH93: cristianpvh2@gmail.com | AI93: 42178967272
A94: 12525427 | B94: 28/04/2026 16:40 | C94: Cancelado | D94: Started | E94: 86647 | F94: Porto Velho | G94: 26/07/2026 | H94: FALSE | I94: 15299839 | J94: Sheila Hurtado Vieira | K94: 02265024228 | L94: sheilahurtado072@gmail.com | M94: 5569992419054 | N94: F | O94: 19/08/1990 | P94: KIT PARTICIPAÇÃO | Q94: 5KM | R94: 149,90 | S94: 14,99 | T94: 0,00 | U94: 149,90 | V94: 76804290 | W94: Rua Treze De Setembro | X94: 1479 | Y94: Areal | Z94: Porto Velho | AA94: RO | AB94: Brasil | AC94: PP | AF94: PP | AG94: Sheila Hurtado Vieira | AH94: sheilahurtado072@gmail.com | AI94: 02265024228
A95: 12525437 | B95: 28/04/2026 16:41 | C95: Pago | D95: Pix | E95: 86647 | F95: Porto Velho | G95: 26/07/2026 | H95: FALSE | I95: 15299864 | J95: Isabeli Facanha | K95: 04489599250 | L95: belifacanha@gmail.com | M95: 5569992948864 | N95: F | O95: 29/01/2009 | P95: KIT PARTICIPAÇÃO | Q95: 5KM | R95: 149,90 | S95: 14,99 | T95: 0,00 | U95: 149,90 | V95: 76821405 | W95: Av. Engenheiro Anysio Da Rocha Compasso | X95: 6021 | Y95: Rio Madeira | Z95: Porto Velho | AA95: RO | AB95: Brasil | AC95: PP | AF95: PP | AG95: Isabeli Facanha | AH95: belifacanha@gmail.com | AI95: 04489599250
A96: 12525445 | B96: 28/04/2026 16:56 | C96: Cancelado | D96: Started | E96: 86645 | F96: Manaus | G96: 30/08/2026 | H96: FALSE | I96: 15299872 | J96: Ranger Fabricio Paiva Cardoso | K96: 01302331299 | L96: fabriciopaiva20009@hotmail.com | M96: 5592981957998 | N96: M | O96: 21/05/1991 | P96: KIT PARTICIPAÇÃO | Q96: 5KM | R96: 149,90 | S96: 14,99 | T96: 0,00 | U96: 149,90 | V96: 69055380 | W96: Rua Vereador Manoel Marcal | X96: 645 | Y96: PARQUE 10 | Z96: Manaus | AA96: AM | AB96: Brasil | AC96: G | AF96: G | AG96: Ranger Fabricio Paiva Cardoso | AH96: fabriciopaiva20009@hotmail.com | AI96: 01302331299
A97: 12525452 | B97: 28/04/2026 16:45 | C97: Pago | D97: Cartão Crédito | E97: 86645 | F97: Manaus | G97: 30/08/2026 | H97: FALSE | I97: 15299882 | J97: Maely Augusta Dangelo Farias | K97: 52660281220 | L97: maelydangelo84@gmail.com | M97: 5592984365703 | N97: F | O97: 13/04/1984 | P97: KIT PARTICIPAÇÃO | Q97: 10KM | R97: 149,90 | S97: 14,99 | T97: 0,00 | U97: 149,90 | V97: 69058448 | W97: Rua Barão de Indaiá | X97: 130 | Y97: Flores | Z97: Manaus | AA97: AM | AB97: Brasil | AD97: P | AF97: P | AG97: Maely Augusta Dangelo Farias | AH97: maelydangelo84@gmail.com | AI97: 52660281220
A98: 12525452 | B98: 28/04/2026 16:45 | C98: Pago | D98: Cartão Crédito | E98: 86645 | F98: Manaus | G98: 30/08/2026 | H98: FALSE | I98: 15299883 | J98: Victor Guimaraes De Oliveira Belichar | K98: 00300625278 | L98: victorbelichar@gmail.com | M98: 5592992027059 | N98: M | O98: 11/03/1989 | P98: KIT PARTICIPAÇÃO | Q98: 10KM | R98: 149,90 | S98: 14,99 | T98: 0,00 | U98: 149,90 | V98: 69058448 | W98: Rua Barão de Indaiá | X98: 130 | Y98: Flores | Z98: Manaus | AA98: AM | AB98: Brasil | AD98: GG | AF98: GG | AG98: Maely Augusta Dangelo Farias | AH98: maelydangelo84@gmail.com | AI98: 52660281220
A99: 12525455 | B99: 28/04/2026 16:59 | C99: Pago | D99: Pix | E99: 86645 | F99: Manaus | G99: 30/08/2026 | H99: FALSE | I99: 15299886 | J99: Rocha Carvalho | K99: 24129992287 | L99: rocharun320@gmail.com | M99: 92991211315 | N99: M | O99: 25/05/1965 | P99: KIT PARTICIPAÇÃO | Q99: 10KM | R99: 149,90 | S99: 7,50 | T99: 74,95 | U99: 74,95 | V99: 69033230 | W99: Rua Castelo Branco | X99: 320 | Y99: Sao Jorge | Z99: Manaus | AA99: AM | AB99: Brasil | AD99: M | AF99: M | AG99: Rocha Carvalho | AH99: rocharun320@gmail.com | AI99: 24129992287
A100: 12525498 | B100: 28/04/2026 16:51 | C100: Pago | D100: Pix | E100: 86645 | F100: Manaus | G100: 30/08/2026 | H100: FALSE | I100: 15299945 | J100: David Dos Santos Menezes | K100: 93950390278 | L100: eumenezes91@gmail.com | M100: (92) 99134-6442 | N100: M | O100: 14/06/1991 | P100: KIT PARTICIPAÇÃO | Q100: 5KM | R100: 149,90 | S100: 14,99 | T100: 0,00 | U100: 149,90 | AC100: GG | AF100: GG | AG100: Larissa Gabrielly Dos Santos Mendes | AH100: larissgabrelly@gmail.com | AI100: 01821760298
...

Sheet RESUMO_EVENTOS
A1: Cidade | B1: Estado | C1: Modalidades | D1: Tamanho das camisetas | E1: APP BEMOL - ESTOQUE | F1: TICKETS - ESTOQUE | G1: VENDA APP BEMOL | H1: VENDA TICKETS | I1: SALDO CORTESIA | J1: ESTOQUE CORTESIA | K1: PEDIDO | M1: SALDO APP BEMOL | N1: SALDO TICKET
A2: Rio Branco | B2: AC | C2: 5KM | D2: PP | E2: 99 | F2: 11 | G2: =COUNTIFS('Vendas SAP'!P:P,RESUMO_EVENTOS!A2,'Vendas SAP'!J:J,RESUMO_EVENTOS!C2,'Vendas SAP'!L:L,RESUMO_EVENTOS!D2,'Vendas SAP'!O:O,"INSCRITO") -> 113 | H2: =COUNTIFS('Vendas - Tickets'!F:F,RESUMO_EVENTOS!A2,'Vendas - Tickets'!Q:Q,RESUMO_EVENTOS!C2,'Vendas - Tickets'!AF:AF,RESUMO_EVENTOS!D2,'Vendas - Tickets'!C:C,"Pago") -> 11 | M2: =E2-G2 -> -14 | N2: =F2-H2 -> 0
A3: Rio Branco | B3: AC | C3: 5KM | D3: P | E3: 183 | F3: 40 | G3: =COUNTIFS('Vendas SAP'!P:P,RESUMO_EVENTOS!A3,'Vendas SAP'!J:J,RESUMO_EVENTOS!C3,'Vendas SAP'!L:L,RESUMO_EVENTOS!D3,'Vendas SAP'!O:O,"INSCRITO") -> 265 | H3: =COUNTIFS('Vendas - Tickets'!F:F,RESUMO_EVENTOS!A3,'Vendas - Tickets'!Q:Q,RESUMO_EVENTOS!C3,'Vendas - Tickets'!AF:AF,RESUMO_EVENTOS!D3,'Vendas - Tickets'!C:C,"Pago") -> 28 | M3: =E3-G3 -> -82 | N3: =F3-H3 -> 12
A4: Rio Branco | B4: AC | C4: 5KM | D4: M | E4: 142 | F4: 95 | G4: =COUNTIFS('Vendas SAP'!P:P,RESUMO_EVENTOS!A4,'Vendas SAP'!J:J,RESUMO_EVENTOS!C4,'Vendas SAP'!L:L,RESUMO_EVENTOS!D4,'Vendas SAP'!O:O,"INSCRITO") -> 276 | H4: =COUNTIFS('Vendas - Tickets'!F:F,RESUMO_EVENTOS!A4,'Vendas - Tickets'!Q:Q,RESUMO_EVENTOS!C4,'Vendas - Tickets'!AF:AF,RESUMO_EVENTOS!D4,'Vendas - Tickets'!C:C,"Pago") -> 34 | M4: =E4-G4 -> -134 | N4: =F4-H4 -> 61
A5: Rio Branco | B5: AC | C5: 5KM | D5: G | E5: 120 | F5: 75 | G5: =COUNTIFS('Vendas SAP'!P:P,RESUMO_EVENTOS!A5,'Vendas SAP'!J:J,RESUMO_EVENTOS!C5,'Vendas SAP'!L:L,RESUMO_EVENTOS!D5,'Vendas SAP'!O:O,"INSCRITO") -> 218 | H5: =COUNTIFS('Vendas - Tickets'!F:F,RESUMO_EVENTOS!A5,'Vendas - Tickets'!Q:Q,RESUMO_EVENTOS!C5,'Vendas - Tickets'!AF:AF,RESUMO_EVENTOS!D5,'Vendas - Tickets'!C:C,"Pago") -> 23 | M5: =E5-G5 -> -98 | N5: =F5-H5 -> 52
A6: Rio Branco | B6: AC | C6: 5KM | D6: GG | E6: 53 | F6: 7 | G6: =COUNTIFS('Vendas SAP'!P:P,RESUMO_EVENTOS!A6,'Vendas SAP'!J:J,RESUMO_EVENTOS!C6,'Vendas SAP'!L:L,RESUMO_EVENTOS!D6,'Vendas SAP'!O:O,"INSCRITO") -> 72 | H6: =COUNTIFS('Vendas - Tickets'!F:F,RESUMO_EVENTOS!A6,'Vendas - Tickets'!Q:Q,RESUMO_EVENTOS!C6,'Vendas - Tickets'!AF:AF,RESUMO_EVENTOS!D6,'Vendas - Tickets'!C:C,"Pago") -> 5 | M6: =E6-G6 -> -19 | N6: =F6-H6 -> 2
A7: Rio Branco | B7: AC | C7: 5KM | D7: XG | E7: 27 | F7: 6 | G7: =COUNTIFS('Vendas SAP'!P:P,RESUMO_EVENTOS!A7,'Vendas SAP'!J:J,RESUMO_EVENTOS!C7,'Vendas SAP'!L:L,RESUMO_EVENTOS!D7,'Vendas SAP'!O:O,"INSCRITO") -> 41 | H7: =COUNTIFS('Vendas - Tickets'!F:F,RESUMO_EVENTOS!A7,'Vendas - Tickets'!Q:Q,RESUMO_EVENTOS!C7,'Vendas - Tickets'!AF:AF,RESUMO_EVENTOS!D7,'Vendas - Tickets'!C:C,"Pago") -> 2 | M7: =E7-G7 -> -14 | N7: =F7-H7 -> 4
A8: Rio Branco | B8: AC | C8: 10KM | D8: PP | E8: 26 | F8: 4 | G8: =COUNTIFS('Vendas SAP'!P:P,RESUMO_EVENTOS!A8,'Vendas SAP'!J:J,RESUMO_EVENTOS!C8,'Vendas SAP'!L:L,RESUMO_EVENTOS!D8,'Vendas SAP'!O:O,"INSCRITO") -> 30 | H8: =COUNTIFS('Vendas - Tickets'!F:F,RESUMO_EVENTOS!A8,'Vendas - Tickets'!Q:Q,RESUMO_EVENTOS!C8,'Vendas - Tickets'!AF:AF,RESUMO_EVENTOS!D8,'Vendas - Tickets'!C:C,"Pago") -> 4 | M8: =E8-G8 -> -4 | N8: =F8-H8 -> 0
A9: Rio Branco | B9: AC | C9: 10KM | D9: P | E9: 69 | F9: 11 | G9: =COUNTIFS('Vendas SAP'!P:P,RESUMO_EVENTOS!A9,'Vendas SAP'!J:J,RESUMO_EVENTOS!C9,'Vendas SAP'!L:L,RESUMO_EVENTOS!D9,'Vendas SAP'!O:O,"INSCRITO") -> 82 | H9: =COUNTIFS('Vendas - Tickets'!F:F,RESUMO_EVENTOS!A9,'Vendas - Tickets'!Q:Q,RESUMO_EVENTOS!C9,'Vendas - Tickets'!AF:AF,RESUMO_EVENTOS!D9,'Vendas - Tickets'!C:C,"Pago") -> 11 | M9: =E9-G9 -> -13 | N9: =F9-H9 -> 0
A10: Rio Branco | B10: AC | C10: 10KM | D10: M | E10: 117 | F10: 27 | G10: =COUNTIFS('Vendas SAP'!P:P,RESUMO_EVENTOS!A10,'Vendas SAP'!J:J,RESUMO_EVENTOS!C10,'Vendas SAP'!L:L,RESUMO_EVENTOS!D10,'Vendas SAP'!O:O,"INSCRITO") -> 169 | H10: =COUNTIFS('Vendas - Tickets'!F:F,RESUMO_EVENTOS!A10,'Vendas - Tickets'!Q:Q,RESUMO_EVENTOS!C10,'Vendas - Tickets'!AF:AF,RESUMO_EVENTOS!D10,'Vendas - Tickets'!C:C,"Pago") -> 17 | M10: =E10-G10 -> -52 | N10: =F10-H10 -> 10
A11: Rio Branco | B11: AC | C11: 10KM | D11: G | E11: 87 | F11: 20 | G11: =COUNTIFS('Vendas SAP'!P:P,RESUMO_EVENTOS!A11,'Vendas SAP'!J:J,RESUMO_EVENTOS!C11,'Vendas SAP'!L:L,RESUMO_EVENTOS!D11,'Vendas SAP'!O:O,"INSCRITO") -> 111 | H11: =COUNTIFS('Vendas - Tickets'!F:F,RESUMO_EVENTOS!A11,'Vendas - Tickets'!Q:Q,RESUMO_EVENTOS!C11,'Vendas - Tickets'!AF:AF,RESUMO_EVENTOS!D11,'Vendas - Tickets'!C:C,"Pago") -> 8 | M11: =E11-G11 -> -24 | N11: =F11-H11 -> 12
A12: Rio Branco | B12: AC | C12: 10KM | D12: GG | E12: 17 | F12: 8 | G12: =COUNTIFS('Vendas SAP'!P:P,RESUMO_EVENTOS!A12,'Vendas SAP'!J:J,RESUMO_EVENTOS!C12,'Vendas SAP'!L:L,RESUMO_EVENTOS!D12,'Vendas SAP'!O:O,"INSCRITO") -> 20 | H12: =COUNTIFS('Vendas - Tickets'!F:F,RESUMO_EVENTOS!A12,'Vendas - Tickets'!Q:Q,RESUMO_EVENTOS!C12,'Vendas - Tickets'!AF:AF,RESUMO_EVENTOS!D12,'Vendas - Tickets'!C:C,"Pago") -> 4 | M12: =E12-G12 -> -3 | N12: =F12-H12 -> 4
A13: Rio Branco | B13: AC | C13: 10KM | D13: XG | E13: 9 | F13: 6 | G13: =COUNTIFS('Vendas SAP'!P:P,RESUMO_EVENTOS!A13,'Vendas SAP'!J:J,RESUMO_EVENTOS!C13,'Vendas SAP'!L:L,RESUMO_EVENTOS!D13,'Vendas SAP'!O:O,"INSCRITO") -> 6 | H13: =COUNTIFS('Vendas - Tickets'!F:F,RESUMO_EVENTOS!A13,'Vendas - Tickets'!Q:Q,RESUMO_EVENTOS!C13,'Vendas - Tickets'!AF:AF,RESUMO_EVENTOS!D13,'Vendas - Tickets'!C:C,"Pago") -> 1 | M13: =E13-G13 -> 3 | N13: =F13-H13 -> 5
... A25: Porto Velho | B25: RO | C25: 10KM | D25: XG | E25: 8 | F25: 7 | G25: =COUNTIFS('Vendas SAP'!P:P,RESUMO_EVENTOS!A25,'Vendas SAP'!J:J,RESUMO_EVENTOS!C25,'Vendas SAP'!L:L,RESUMO_EVENTOS!D25,'Vendas SAP'!O:O,"INSCRITO") -> 9 | H25: =COUNTIFS('Vendas - Tickets'!F:F,RESUMO_EVENTOS!A25,'Vendas - Tickets'!Q:Q,RESUMO_EVENTOS!C25,'Vendas - Tickets'!AF:AF,RESUMO_EVENTOS!D25,'Vendas - Tickets'!C:C,"Pago") -> 1 | M25: =E25-G25 -> -1 | N25: =F25-H25 -> 6
A26: Manaus | B26: AM | C26: 5KM | D26: PP | E26: 289 | F26: 71 | G26: =COUNTIFS('Vendas SAP'!P:P,RESUMO_EVENTOS!A26,'Vendas SAP'!J:J,RESUMO_EVENTOS!C26,'Vendas SAP'!L:L,RESUMO_EVENTOS!D26,'Vendas SAP'!O:O,"INSCRITO") -> 365 | H26: =COUNTIFS('Vendas - Tickets'!F:F,RESUMO_EVENTOS!A26,'Vendas - Tickets'!Q:Q,RESUMO_EVENTOS!C26,'Vendas - Tickets'!AF:AF,RESUMO_EVENTOS!D26,'Vendas - Tickets'!C:C,"Pago") -> 69 | M26: =E26-G26 -> -76 | N26: =F26-H26 -> 2 | P26: =M26-(20%*M26) -> -60.8 | Q26: =M26-P26 -> -15.2 | S26: =F26+Q26 -> 55.8
A27: Manaus | B27: AM | C27: 5KM | D27: P | E27: 816 | F27: 123 | G27: =COUNTIFS('Vendas SAP'!P:P,RESUMO_EVENTOS!A27,'Vendas SAP'!J:J,RESUMO_EVENTOS!C27,'Vendas SAP'!L:L,RESUMO_EVENTOS!D27,'Vendas SAP'!O:O,"INSCRITO") -> 1001 | H27: =COUNTIFS('Vendas - Tickets'!F:F,RESUMO_EVENTOS!A27,'Vendas - Tickets'!Q:Q,RESUMO_EVENTOS!C27,'Vendas - Tickets'!AF:AF,RESUMO_EVENTOS!D27,'Vendas - Tickets'!C:C,"Pago") -> 120 | M27: =E27-G27 -> -185 | N27: =F27-H27 -> 3 | P27: 243 | Q27: =M27-P27 -> -428 | S27: =F27+Q27 -> -305
A28: Manaus | B28: AM | C28: 5KM | D28: M | E28: 1301 | F28: 165 | G28: =COUNTIFS('Vendas SAP'!P:P,RESUMO_EVENTOS!A28,'Vendas SAP'!J:J,RESUMO_EVENTOS!C28,'Vendas SAP'!L:L,RESUMO_EVENTOS!D28,'Vendas SAP'!O:O,"INSCRITO") -> 1667 | H28: =COUNTIFS('Vendas - Tickets'!F:F,RESUMO_EVENTOS!A28,'Vendas - Tickets'!Q:Q,RESUMO_EVENTOS!C28,'Vendas - Tickets'!AF:AF,RESUMO_EVENTOS!D28,'Vendas - Tickets'!C:C,"Pago") -> 157 | M28: =E28-G28 -> -366 | N28: =F28-H28 -> 8 | P28: 523 | Q28: =M28-P28 -> -889 | S28: =F28+Q28 -> -724
A29: Manaus | B29: AM | C29: 5KM | D29: G | E29: 709 | F29: 89 | G29: =COUNTIFS('Vendas SAP'!P:P,RESUMO_EVENTOS!A29,'Vendas SAP'!J:J,RESUMO_EVENTOS!C29,'Vendas SAP'!L:L,RESUMO_EVENTOS!D29,'Vendas SAP'!O:O,"INSCRITO") -> 904 | H29: =COUNTIFS('Vendas - Tickets'!F:F,RESUMO_EVENTOS!A29,'Vendas - Tickets'!Q:Q,RESUMO_EVENTOS!C29,'Vendas - Tickets'!AF:AF,RESUMO_EVENTOS!D29,'Vendas - Tickets'!C:C,"Pago") -> 88 | M29: =E29-G29 -> -195 | N29: =F29-H29 -> 1 | P29: 263 | Q29: =M29-P29 -> -458 | S29: =F29+Q29 -> -369
A30: Manaus | B30: AM | C30: 5KM | D30: GG | E30: 126 | F30: 22 | G30: =COUNTIFS('Vendas SAP'!P:P,RESUMO_EVENTOS!A30,'Vendas SAP'!J:J,RESUMO_EVENTOS!C30,'Vendas SAP'!L:L,RESUMO_EVENTOS!D30,'Vendas SAP'!O:O,"INSCRITO") -> 155 | H30: =COUNTIFS('Vendas - Tickets'!F:F,RESUMO_EVENTOS!A30,'Vendas - Tickets'!Q:Q,RESUMO_EVENTOS!C30,'Vendas - Tickets'!AF:AF,RESUMO_EVENTOS!D30,'Vendas - Tickets'!C:C,"Pago") -> 22 | M30: =E30-G30 -> -29 | N30: =F30-H30 -> 0 | P30: 24 | Q30: =M30-P30 -> -53 | S30: =F30+Q30 -> -31
A31: Manaus | B31: AM | C31: 5KM | D31: XG | E31: 58 | F31: 10 | G31: =COUNTIFS('Vendas SAP'!P:P,RESUMO_EVENTOS!A31,'Vendas SAP'!J:J,RESUMO_EVENTOS!C31,'Vendas SAP'!L:L,RESUMO_EVENTOS!D31,'Vendas SAP'!O:O,"INSCRITO") -> 75 | H31: =COUNTIFS('Vendas - Tickets'!F:F,RESUMO_EVENTOS!A31,'Vendas - Tickets'!Q:Q,RESUMO_EVENTOS!C31,'Vendas - Tickets'!AF:AF,RESUMO_EVENTOS!D31,'Vendas - Tickets'!C:C,"Pago") -> 9 | M31: =E31-G31 -> -17 | N31: =F31-H31 -> 1 | P31: 16 | Q31: =M31-P31 -> -33 | S31: =F31+Q31 -> -23
A32: Manaus | B32: AM | C32: 10KM | D32: PP | E32: 112 | F32: 37 | G32: =COUNTIFS('Vendas SAP'!P:P,RESUMO_EVENTOS!A32,'Vendas SAP'!J:J,RESUMO_EVENTOS!C32,'Vendas SAP'!L:L,RESUMO_EVENTOS!D32,'Vendas SAP'!O:O,"INSCRITO") -> 145 | H32: =COUNTIFS('Vendas - Tickets'!F:F,RESUMO_EVENTOS!A32,'Vendas - Tickets'!Q:Q,RESUMO_EVENTOS!C32,'Vendas - Tickets'!AF:AF,RESUMO_EVENTOS!D32,'Vendas - Tickets'!C:C,"Pago") -> 37 | M32: =E32-G32 -> -33 | N32: =F32-H32 -> 0 | P32: 11 | Q32: =M32-P32 -> -44 | S32: =F32+Q32 -> -7
A33: Manaus | B33: AM | C33: 10KM | D33: P | E33: 483 | F33: 73 | G33: =COUNTIFS('Vendas SAP'!P:P,RESUMO_EVENTOS!A33,'Vendas SAP'!J:J,RESUMO_EVENTOS!C33,'Vendas SAP'!L:L,RESUMO_EVENTOS!D33,'Vendas SAP'!O:O,"INSCRITO") -> 615 | H33: =COUNTIFS('Vendas - Tickets'!F:F,RESUMO_EVENTOS!A33,'Vendas - Tickets'!Q:Q,RESUMO_EVENTOS!C33,'Vendas - Tickets'!AF:AF,RESUMO_EVENTOS!D33,'Vendas - Tickets'!C:C,"Pago") -> 70 | M33: =E33-G33 -> -132 | N33: =F33-H33 -> 3 | P33: 211 | Q33: =M33-P33 -> -343 | S33: =F33+Q33 -> -270
A34: Manaus | B34: AM | C34: 10KM | D34: M | E34: 665 | F34: 80 | G34: =COUNTIFS('Vendas SAP'!P:P,RESUMO_EVENTOS!A34,'Vendas SAP'!J:J,RESUMO_EVENTOS!C34,'Vendas SAP'!L:L,RESUMO_EVENTOS!D34,'Vendas SAP'!O:O,"INSCRITO") -> 880 | H34: =COUNTIFS('Vendas - Tickets'!F:F,RESUMO_EVENTOS!A34,'Vendas - Tickets'!Q:Q,RESUMO_EVENTOS!C34,'Vendas - Tickets'!AF:AF,RESUMO_EVENTOS!D34,'Vendas - Tickets'!C:C,"Pago") -> 78 | M34: =E34-G34 -> -215 | N34: =F34-H34 -> 2 | P34: 372 | Q34: =M34-P34 -> -587 | S34: =F34+Q34 -> -507
A35: Manaus | B35: AM | C35: 10KM | D35: G | E35: 412 | F35: 54 | G35: =COUNTIFS('Vendas SAP'!P:P,RESUMO_EVENTOS!A35,'Vendas SAP'!J:J,RESUMO_EVENTOS!C35,'Vendas SAP'!L:L,RESUMO_EVENTOS!D35,'Vendas SAP'!O:O,"INSCRITO") -> 558 | H35: =COUNTIFS('Vendas - Tickets'!F:F,RESUMO_EVENTOS!A35,'Vendas - Tickets'!Q:Q,RESUMO_EVENTOS!C35,'Vendas - Tickets'!AF:AF,RESUMO_EVENTOS!D35,'Vendas - Tickets'!C:C,"Pago") -> 52 | M35: =E35-G35 -> -146 | N35: =F35-H35 -> 2 | P35: 266 | Q35: =M35-P35 -> -412 | S35: =F35+Q35 -> -358
A36: Manaus | B36: AM | C36: 10KM | D36: GG | E36: 65 | F36: 14 | G36: =COUNTIFS('Vendas SAP'!P:P,RESUMO_EVENTOS!A36,'Vendas SAP'!J:J,RESUMO_EVENTOS!C36,'Vendas SAP'!L:L,RESUMO_EVENTOS!D36,'Vendas SAP'!O:O,"INSCRITO") -> 77 | H36: =COUNTIFS('Vendas - Tickets'!F:F,RESUMO_EVENTOS!A36,'Vendas - Tickets'!Q:Q,RESUMO_EVENTOS!C36,'Vendas - Tickets'!AF:AF,RESUMO_EVENTOS!D36,'Vendas - Tickets'!C:C,"Pago") -> 14 | M36: =E36-G36 -> -12 | N36: =F36-H36 -> 0 | P36: 14 | Q36: =M36-P36 -> -26 | S36: =F36+Q36 -> -12
A37: Manaus | B37: AM | C37: 10KM | D37: XG | E37: 13 | F37: 7 | G37: =COUNTIFS('Vendas SAP'!P:P,RESUMO_EVENTOS!A37,'Vendas SAP'!J:J,RESUMO_EVENTOS!C37,'Vendas SAP'!L:L,RESUMO_EVENTOS!D37,'Vendas SAP'!O:O,"INSCRITO") -> 17 | H37: =COUNTIFS('Vendas - Tickets'!F:F,RESUMO_EVENTOS!A37,'Vendas - Tickets'!Q:Q,RESUMO_EVENTOS!C37,'Vendas - Tickets'!AF:AF,RESUMO_EVENTOS!D37,'Vendas - Tickets'!C:C,"Pago") -> 7 | M37: =E37-G37 -> -4 | N37: =F37-H37 -> 0 | P37: 5 | Q37: =M37-P37 -> -9 | S37: =F37+Q37 -> -2
A38: Boa Vista | B38: RR | C38: 5KM | D38: PP | E38: 210 | F38: 30 | G38: =COUNTIFS('Vendas SAP'!P:P,RESUMO_EVENTOS!A38,'Vendas SAP'!J:J,RESUMO_EVENTOS!C38,'Vendas SAP'!L:L,RESUMO_EVENTOS!D38,'Vendas SAP'!O:O,"INSCRITO") -> 210 | H38: =COUNTIFS('Vendas - Tickets'!F:F,RESUMO_EVENTOS!A38,'Vendas - Tickets'!Q:Q,RESUMO_EVENTOS!C38,'Vendas - Tickets'!AF:AF,RESUMO_EVENTOS!D38,'Vendas - Tickets'!C:C,"Pago") -> 16 | M38: =E38-G38 -> 0 | N38: =F38-H38 -> 14
A39: Boa Vista | B39: RR | C39: 5KM | D39: P | E39: 355 | F39: 132 | G39: =COUNTIFS('Vendas SAP'!P:P,RESUMO_EVENTOS!A39,'Vendas SAP'!J:J,RESUMO_EVENTOS!C39,'Vendas SAP'!L:L,RESUMO_EVENTOS!D39,'Vendas SAP'!O:O,"INSCRITO") -> 250 | H39: =COUNTIFS('Vendas - Tickets'!F:F,RESUMO_EVENTOS!A39,'Vendas - Tickets'!Q:Q,RESUMO_EVENTOS!C39,'Vendas - Tickets'!AF:AF,RESUMO_EVENTOS!D39,'Vendas - Tickets'!C:C,"Pago") -> 23 | M39: =E39-G39 -> 105 | N39: =F39-H39 -> 109
A40: Boa Vista | B40: RR | C40: 5KM | D40: M | E40: 271 | F40: 255 | G40: =COUNTIFS('Vendas SAP'!P:P,RESUMO_EVENTOS!A40,'Vendas SAP'!J:J,RESUMO_EVENTOS!C40,'Vendas SAP'!L:L,RESUMO_EVENTOS!D40,'Vendas SAP'!O:O,"INSCRITO") -> 265 | H40: =COUNTIFS('Vendas - Tickets'!F:F,RESUMO_EVENTOS!A40,'Vendas - Tickets'!Q:Q,RESUMO_EVENTOS!C40,'Vendas - Tickets'!AF:AF,RESUMO_EVENTOS!D40,'Vendas - Tickets'!C:C,"Pago") -> 27 | M40: =E40-G40 -> 6 | N40: =F40-H40 -> 228
A41: Boa Vista | B41: RR | C41: 5KM | D41: G | E41: 231 | F41: 262 | G41: =COUNTIFS('Vendas SAP'!P:P,RESUMO_EVENTOS!A41,'Vendas SAP'!J:J,RESUMO_EVENTOS!C41,'Vendas SAP'!L:L,RESUMO_EVENTOS!D41,'Vendas SAP'!O:O,"INSCRITO") -> 165 | H41: =COUNTIFS('Vendas - Tickets'!F:F,RESUMO_EVENTOS!A41,'Vendas - Tickets'!Q:Q,RESUMO_EVENTOS!C41,'Vendas - Tickets'!AF:AF,RESUMO_EVENTOS!D41,'Vendas - Tickets'!C:C,"Pago") -> 8 | M41: =E41-G41 -> 66 | N41: =F41-H41 -> 254
A42: Boa Vista | B42: RR | C42: 5KM | D42: GG | E42: 94 | F42: 50 | G42: =COUNTIFS('Vendas SAP'!P:P,RESUMO_EVENTOS!A42,'Vendas SAP'!J:J,RESUMO_EVENTOS!C42,'Vendas SAP'!L:L,RESUMO_EVENTOS!D42,'Vendas SAP'!O:O,"INSCRITO") -> 62 | H42: =COUNTIFS('Vendas - Tickets'!F:F,RESUMO_EVENTOS!A42,'Vendas - Tickets'!Q:Q,RESUMO_EVENTOS!C42,'Vendas - Tickets'!AF:AF,RESUMO_EVENTOS!D42,'Vendas - Tickets'!C:C,"Pago") -> 1 | M42: =E42-G42 -> 32 | N42: =F42-H42 -> 49
A43: Boa Vista | B43: RR | C43: 5KM | D43: XG | E43: 42 | F43: 50 | G43: =COUNTIFS('Vendas SAP'!P:P,RESUMO_EVENTOS!A43,'Vendas SAP'!J:J,RESUMO_EVENTOS!C43,'Vendas SAP'!L:L,RESUMO_EVENTOS!D43,'Vendas SAP'!O:O,"INSCRITO") -> 26 | H43: =COUNTIFS('Vendas - Tickets'!F:F,RESUMO_EVENTOS!A43,'Vendas - Tickets'!Q:Q,RESUMO_EVENTOS!C43,'Vendas - Tickets'!AF:AF,RESUMO_EVENTOS!D43,'Vendas - Tickets'!C:C,"Pago") -> 4 | M43: =E43-G43 -> 16 | N43: =F43-H43 -> 46
A44: Boa Vista | B44: RR | C44: 10KM | D44: PP | E44: 68 | F44: 8 | G44: =COUNTIFS('Vendas SAP'!P:P,RESUMO_EVENTOS!A44,'Vendas SAP'!J:J,RESUMO_EVENTOS!C44,'Vendas SAP'!L:L,RESUMO_EVENTOS!D44,'Vendas SAP'!O:O,"INSCRITO") -> 81 | H44: =COUNTIFS('Vendas - Tickets'!F:F,RESUMO_EVENTOS!A44,'Vendas - Tickets'!Q:Q,RESUMO_EVENTOS!C44,'Vendas - Tickets'!AF:AF,RESUMO_EVENTOS!D44,'Vendas - Tickets'!C:C,"Pago") -> 8 | M44: =E44-G44 -> -13 | N44: =F44-H44 -> 0
A45: Boa Vista | B45: RR | C45: 10KM | D45: P | E45: 115 | F45: 61 | G45: =COUNTIFS('Vendas SAP'!P:P,RESUMO_EVENTOS!A45,'Vendas SAP'!J:J,RESUMO_EVENTOS!C45,'Vendas SAP'!L:L,RESUMO_EVENTOS!D45,'Vendas SAP'!O:O,"INSCRITO") -> 143 | H45: =COUNTIFS('Vendas - Tickets'!F:F,RESUMO_EVENTOS!A45,'Vendas - Tickets'!Q:Q,RESUMO_EVENTOS!C45,'Vendas - Tickets'!AF:AF,RESUMO_EVENTOS!D45,'Vendas - Tickets'!C:C,"Pago") -> 34 | M45: =E45-G45 -> -28 | N45: =F45-H45 -> 27
A46: Boa Vista | B46: RR | C46: 10KM | D46: M | E46: 230 | F46: 170 | G46: =COUNTIFS('Vendas SAP'!P:P,RESUMO_EVENTOS!A46,'Vendas SAP'!J:J,RESUMO_EVENTOS!C46,'Vendas SAP'!L:L,RESUMO_EVENTOS!D46,'Vendas SAP'!O:O,"INSCRITO") -> 201 | H46: =COUNTIFS('Vendas - Tickets'!F:F,RESUMO_EVENTOS!A46,'Vendas - Tickets'!Q:Q,RESUMO_EVENTOS!C46,'Vendas - Tickets'!AF:AF,RESUMO_EVENTOS!D46,'Vendas - Tickets'!C:C,"Pago") -> 16 | M46: =E46-G46 -> 29 | N46: =F46-H46 -> 154
A47: Boa Vista | B47: RR | C47: 10KM | D47: G | E47: 133 | F47: 142 | G47: =COUNTIFS('Vendas SAP'!P:P,RESUMO_EVENTOS!A47,'Vendas SAP'!J:J,RESUMO_EVENTOS!C47,'Vendas SAP'!L:L,RESUMO_EVENTOS!D47,'Vendas SAP'!O:O,"INSCRITO") -> 98 | H47: =COUNTIFS('Vendas - Tickets'!F:F,RESUMO_EVENTOS!A47,'Vendas - Tickets'!Q:Q,RESUMO_EVENTOS!C47,'Vendas - Tickets'!AF:AF,RESUMO_EVENTOS!D47,'Vendas - Tickets'!C:C,"Pago") -> 5 | M47: =E47-G47 -> 35 | N47: =F47-H47 -> 137
A48: Boa Vista | B48: RR | C48: 10KM | D48: GG | E48: 45 | F48: 12 | G48: =COUNTIFS('Vendas SAP'!P:P,RESUMO_EVENTOS!A48,'Vendas SAP'!J:J,RESUMO_EVENTOS!C48,'Vendas SAP'!L:L,RESUMO_EVENTOS!D48,'Vendas SAP'!O:O,"INSCRITO") -> 23 | H48: =COUNTIFS('Vendas - Tickets'!F:F,RESUMO_EVENTOS!A48,'Vendas - Tickets'!Q:Q,RESUMO_EVENTOS!C48,'Vendas - Tickets'!AF:AF,RESUMO_EVENTOS!D48,'Vendas - Tickets'!C:C,"Pago") -> 1 | M48: =E48-G48 -> 22 | N48: =F48-H48 -> 11
A49: Boa Vista | B49: RR | C49: 10KM | D49: XG | E49: 21 | F49: 12 | G49: =COUNTIFS('Vendas SAP'!P:P,RESUMO_EVENTOS!A49,'Vendas SAP'!J:J,RESUMO_EVENTOS!C49,'Vendas SAP'!L:L,RESUMO_EVENTOS!D49,'Vendas SAP'!O:O,"INSCRITO") -> 9 | H49: =COUNTIFS('Vendas - Tickets'!F:F,RESUMO_EVENTOS!A49,'Vendas - Tickets'!Q:Q,RESUMO_EVENTOS!C49,'Vendas - Tickets'!AF:AF,RESUMO_EVENTOS!D49,'Vendas - Tickets'!C:C,"Pago") -> 1 | M49: =E49-G49 -> 12 | N49: =F49-H49 -> 11
A50: Kids - Manaus | B50: AM | C50: 5KM | D50: PP | G50: =COUNTIFS('Vendas 2026 - APP'!O:O,RESUMO_EVENTOS!A50,'Vendas 2026 - APP'!H:H,RESUMO_EVENTOS!C50,'Vendas 2026 - APP'!J:J,RESUMO_EVENTOS!D50,'Vendas 2026 - APP'!M:M,"INSCRITO") -> 0 | H50: =COUNTIFS('Vendas - Tickets'!Z:Z,RESUMO_EVENTOS!A50,'Vendas - Tickets'!Q:Q,RESUMO_EVENTOS!C50,'Vendas - Tickets'!AE:AE,RESUMO_EVENTOS!D50,'Vendas - Tickets'!C:C,"Pago") -> 0 | M50: =E50-G50 -> 0 | N50: =F50-H50 -> 0
A51: Kids - Manaus | B51: AM | C51: 5KM | D51: P | G51: =COUNTIFS('Vendas 2026 - APP'!O:O,RESUMO_EVENTOS!A51,'Vendas 2026 - APP'!H:H,RESUMO_EVENTOS!C51,'Vendas 2026 - APP'!J:J,RESUMO_EVENTOS!D51,'Vendas 2026 - APP'!M:M,"INSCRITO") -> 0 | H51: =COUNTIFS('Vendas - Tickets'!Z:Z,RESUMO_EVENTOS!A51,'Vendas - Tickets'!Q:Q,RESUMO_EVENTOS!C51,'Vendas - Tickets'!AE:AE,RESUMO_EVENTOS!D51,'Vendas - Tickets'!C:C,"Pago") -> 0 | M51: =E51-G51 -> 0 | N51: =F51-H51 -> 0
A52: Kids - Manaus | B52: AM | C52: 5KM | D52: M | G52: =COUNTIFS('Vendas 2026 - APP'!O:O,RESUMO_EVENTOS!A52,'Vendas 2026 - APP'!H:H,RESUMO_EVENTOS!C52,'Vendas 2026 - APP'!J:J,RESUMO_EVENTOS!D52,'Vendas 2026 - APP'!M:M,"INSCRITO") -> 0 | H52: =COUNTIFS('Vendas - Tickets'!Z:Z,RESUMO_EVENTOS!A52,'Vendas - Tickets'!Q:Q,RESUMO_EVENTOS!C52,'Vendas - Tickets'!AE:AE,RESUMO_EVENTOS!D52,'Vendas - Tickets'!C:C,"Pago") -> 0 | M52: =E52-G52 -> 0 | N52: =F52-H52 -> 0
A53: Kids - Manaus | B53: AM | C53: 5KM | D53: G | G53: =COUNTIFS('Vendas 2026 - APP'!O:O,RESUMO_EVENTOS!A53,'Vendas 2026 - APP'!H:H,RESUMO_EVENTOS!C53,'Vendas 2026 - APP'!J:J,RESUMO_EVENTOS!D53,'Vendas 2026 - APP'!M:M,"INSCRITO") -> 0 | H53: =COUNTIFS('Vendas - Tickets'!Z:Z,RESUMO_EVENTOS!A53,'Vendas - Tickets'!Q:Q,RESUMO_EVENTOS!C53,'Vendas - Tickets'!AE:AE,RESUMO_EVENTOS!D53,'Vendas - Tickets'!C:C,"Pago") -> 0 | M53: =E53-G53 -> 0 | N53: =F53-H53 -> 0
A54: Kids - Manaus | B54: AM | C54: 5KM | D54: GG | G54: =COUNTIFS('Vendas 2026 - APP'!O:O,RESUMO_EVENTOS!A54,'Vendas 2026 - APP'!H:H,RESUMO_EVENTOS!C54,'Vendas 2026 - APP'!J:J,RESUMO_EVENTOS!D54,'Vendas 2026 - APP'!M:M,"INSCRITO") -> 0 | H54: =COUNTIFS('Vendas - Tickets'!Z:Z,RESUMO_EVENTOS!A54,'Vendas - Tickets'!Q:Q,RESUMO_EVENTOS!C54,'Vendas - Tickets'!AE:AE,RESUMO_EVENTOS!D54,'Vendas - Tickets'!C:C,"Pago") -> 0 | M54: =E54-G54 -> 0 | N54: =F54-H54 -> 0
A55: Kids - Manaus | B55: AM | C55: 5KM | D55: XG | G55: =COUNTIFS('Vendas 2026 - APP'!O:O,RESUMO_EVENTOS!A55,'Vendas 2026 - APP'!H:H,RESUMO_EVENTOS!C55,'Vendas 2026 - APP'!J:J,RESUMO_EVENTOS!D55,'Vendas 2026 - APP'!M:M,"INSCRITO") -> 0 | H55: =COUNTIFS('Vendas - Tickets'!Z:Z,RESUMO_EVENTOS!A55,'Vendas - Tickets'!Q:Q,RESUMO_EVENTOS!C55,'Vendas - Tickets'!AE:AE,RESUMO_EVENTOS!D55,'Vendas - Tickets'!C:C,"Pago") -> 0 | M55: =E55-G55 -> 0 | N55: =F55-H55 -> 0
C61: Cidade | D61: Estado | E61: Modalidades | F61: Tamanho das camisetas | G61: atual_SALDO APP BEMOL | I61: futuro_SALDO APP BEMOL | J61: acrescentar_SALDO TICKET | L61: SALDO TICKET
C62: Manaus | D62: AM | E62: 5KM | F62: PP | G62: 90 | I62: 72 | J62: 18 | L62: 71
C63: Manaus | D63: AM | E63: 5KM | F63: P | G63: 304 | I63: 243 | J63: 61 | L63: 139
C64: Manaus | D64: AM | E64: 5KM | F64: M | G64: 654 | I64: 523 | J64: 131 | L64: 214
C65: Manaus | D65: AM | E65: 5KM | F65: G | G65: 329 | I65: 263 | J65: 66 | L65: 119
C66: Manaus | D66: AM | E66: 5KM | F66: GG | G66: 31 | I66: 24 | J66: 7 | L66: 22
C67: Manaus | D67: AM | E67: 5KM | F67: XG | G67: 21 | I67: 16 | J67: 5 | L67: 10
C68: Manaus | D68: AM | E68: 10KM | F68: PP | G68: 14 | I68: 11 | J68: 3 | L68: 37
C69: Manaus | D69: AM | E69: 10KM | F69: P | G69: 264 | I69: 211 | J69: 53 | L69: 99
C70: Manaus | D70: AM | E70: 10KM | F70: M | G70: 466 | I70: 372 | J70: 94 | L70: 142
C71: Manaus | D71: AM | E71: 10KM | F71: G | G71: 333 | I71: 266 | J71: 67 | L71: 97
C72: Manaus | D72: AM | E72: 10KM | F72: GG | G72: 18 | I72: 14 | J72: 4 | L72: 14
C73: Manaus | D73: AM | E73: 10KM | F73: XG | G73: 7 | I73: 5 | J73: 2 | L73: 7

Sheet Vendas SAP
A1: DATA | B1: HORA | C1: CPF | D1: ID_CLIENTE | E1: NOME | F1: EMAIL | G1: TELEFONE | H1: DATA_NASCIMENTO | I1: CATEGORIA | J1: MODALIDADE | K1: GENERO | L1: TAMANHO | M1: TIPO_PAGAMENTO | N1: VALOR | O1: STATUS_PAGAMENTO | P1: EVENTO_ID
A2: 46144 | B2: 074750 | C2: 72040009272 | D2: 0001654888 | E2: ELIANDRO DRUMOND DE CARVALHO | F2: eliandrodrumod@hotmail.com | H2: 27830 | I2: GERAL | J2: 5KM | K2: F | L2: M | M2: CB | N2: 129.9 | O2: INSCRITO | P2: Porto Velho
A3: 46141 | B3: 090810 | C3: 11458080854 | D3: 0001590226 | E3: POLLYANA DE SOUZA BASTOS | F3: pollyana.bastos@hotmail.com | H3: 25859 | I3: GERAL | J3: 5KM | K3: M | L3: M | M3: PIX | N3: 149.9 | O3: INSCRITO | P3: Manaus
A4: 46142 | B4: 200420 | C4: 86047124291 | D4: 0001297093 | E4: KELLYANA RODRIGUES MOURA | F4: kellymcoelho@hotmail.com | H4: 31372 | I4: GERAL | J4: 5KM | K4: M | L4: P | M4: PIX | N4: 129.9 | O4: INSCRITO | P4: Manaus
A5: 46141 | B5: 131231 | C5: 02727186290 | D5: 0003075975 | E5: KARINA DO NASCIMENTO ROQUE | F5: karinaroque28@icloud.com | H5: 34945 | I5: GERAL | J5: 5KM | K5: M | L5: G | M5: PIX | N5: 149.9 | O5: INSCRITO | P5: Manaus
A6: 46147 | B6: 092458 | C6: 77553268291 | D6: 0001245137 | E6: ADRINY MAYARA PIRES DO CARMO | F6: adrinymaypires@gmail.com | H6: 32157 | I6: GERAL | J6: 10KM | K6: M | L6: G | M6: PIX | N6: 149.9 | O6: INSCRITO | P6: Manaus
A7: 46147 | B7: 083903 | C7: 90525566287 | D7: 0001660865 | E7: EDILENE DA SILVA LOPES | F7: edyllene92@gmail.com | H7: 39577 | I7: GERAL | J7: 5KM | K7: M | L7: M | M7: PIX | N7: 149.9 | O7: INSCRITO | P7: Porto Velho
A8: 46145 | B8: 182639 | C8: 02668310288 | D8: 0004911532 | E8: EVANIR DA SILVA SOUZA | F8: evanir.souzaoficial@gmail.com | H8: 35154 | I8: GERAL | J8: 5KM | K8: M | L8: P | M8: CB | N8: 149.9 | O8: INSCRITO | P8: Boa Vista
A9: 46142 | B9: 201048 | C9: 04338620250 | D9: 0004390773 | E9: SARA LIMA DA SILVA | F9: saralima123pvh@gmail.com | H9: 37744 | I9: GERAL | J9: 5KM | K9: M | L9: P | M9: CB | N9: 149.9 | O9: INSCRITO | P9: Porto Velho
A10: 46143 | B10: 235123 | C10: 00953685233 | D10: 0001854158 | E10: ROSIVANIA MORAIS DE ALBUQUERQUE CRU | F10: rosyy_123_@hotmail.com | H10: 33898 | I10: GERAL | J10: 5KM | K10: M | L10: M | M10: CB | N10: 129.9 | O10: INSCRITO | P10: Manaus
A11: 46140 | B11: 144413 | C11: 03271847282 | D11: 0004733139 | E11: DAVID MASCARENHAS DE SA | F11: daviddesa@gmail.com | H11: 35850 | I11: GERAL | J11: 10KM | K11: F | L11: M | M11: CB | N11: 129.9 | O11: INSCRITO | P11: Manaus
A12: 46142 | B12: 193943 | C12: 70524096236 | D12: 0004058786 | E12: SARAH VICTORIA PINHEIRO MAIA | F12: sarah123pinheiro@gmail.com | H12: 37742 | I12: GERAL | J12: 5KM | K12: M | L12: PP | M12: CB | N12: 129.9 | O12: INSCRITO | P12: Manaus
A13: 46143 | B13: 210322 | C13: 88867455249 | D13: 0001215428 | E13: ELINE CABRAL DE VASCONCELOS | F13: elinecabralvasco87@hotmail.com | H13: 32061 | I13: GERAL | J13: 5KM | K13: M | L13: M | M13: PIX | N13: 129.9 | O13: INSCRITO | P13: Manaus
... A758: 46141 | B758: 215505 | C758: 97922897200 | D758: 0001913541 | E758: ADRIELE DA COSTA PEREIRA | F758: Adriellepereira8136@gmail.com | H758: 31619 | I758: GERAL | J758: 5KM | K758: M | L758: P | M758: CB | N758: 129.9 | O758: INSCRITO | P758: Manaus
A759: 46143 | B759: 171658 | C759: 94885451272 | D759: 0001964480 | E759: FABIO MENDES DE SOUZA | F759: fabiot12@hotmail.com | H759: 32426 | J759: 5KM | K759: M | L759: G | M759: PIX | N759: 129.9 | O759: INSCRITO | P759: Rio Branco
A760: 46140 | B760: 150521 | C760: 33677220220 | D760: 0000303207 | E760: RICARDO FRANCO DE LIMA MATTOS | F760: fbarezze338@gmail.com | H760: 26848 | I760: GERAL | J760: 10KM | K760: F | L760: G | M760: CB | N760: 129.9 | O760: INSCRITO | P760: Manaus
A761: 46141 | B761: 183506 | C761: 66426456268 | D761: 0002340993 | E761: VANDER JANIO MEDEIROS PAIXAO | F761: paixaovander495@gmail.com | H761: 28640 | I761: GERAL | J761: 5KM | K761: M | L761: P | M761: CB | N761: 129.9 | O761: INSCRITO | P761: Manaus
A762: 46142 | B762: 134846 | C762: 70535723237 | D762: 0005747159 | E762: RAUL MATHEUS DE LIMA RAPOSO | F762: raulmatheus580@gmail.com | H762: 37366 | I762: GERAL | J762: 10KM | K762: F | L762: M | M762: CB | N762: 129.9 | O762: INSCRITO | P762: Manaus
A763: 46142 | B763: 111418 | C763: 00547545266 | D763: 0002355549 | E763: LOREM JOYCE DA SILVA ALMEIDA | F763: loremjoyce3@gmail.com | H763: 31704 | I763: GERAL | J763: 5KM | K763: M | L763: G | M763: CB | N763: 129.9 | O763: INSCRITO | P763: Manaus
A764: 46146 | B764: 184256 | C764: 87808048291 | D764: 0001204409 | E764: ANDREA VIEIRA BENTES | F764: andreabentes@gmail.com | H764: 32006 | I764: GERAL | J764: 10KM | K764: M | L764: M | M764: PIX | N764: 129.9 | O764: INSCRITO | P764: Manaus
A765: 46141 | B765: 100922 | C765: 01813486247 | D765: 0002271489 | E765: MARIA NASCIMENTO DE OLIVEIRA | F765: marianoliveira0@gmail.com | H765: 34248 | I765: GERAL | J765: 5KM | K765: M | L765: M | M765: PIX | N765: 129.9 | O765: INSCRITO | P765: Manaus
A766: 46142 | B766: 151631 | C766: 01762029278 | D766: 0001876420 | E766: RUAN SILVEIRA FERREIRA | F766: ruansilveiraferreira@gmail.com | H766: 34659 | I766: GERAL | J766: 5KM | K766: F | L766: M | M766: PIX | N766: 129.9 | O766: INSCRITO | P766: Manaus
A767: 46143 | B767: 094838 | C767: 02355889546 | D767: 0002151992 | E767: EDVALDO SOARES ARAUJO NETO | F767: neto.ed@gmail.com | H767: 39573 | I767: GERAL | J767: 10KM | K767: F | L767: P | M767: PIX | N767: 129.9 | O767: INSCRITO | P767: Porto Velho
A768: 46140 | B768: 170312 | C768: 00988465230 | D768: 0001472741 | E768: KETLEEN DE OLIVEIRA VAREJAO | F768: ketleen_oliver20@hotmail.com | H768: 33305 | I768: GERAL | J768: 5KM | K768: M | L768: P | M768: CB | N768: 129.9 | O768: INSCRITO | P768: Manaus
A769: 46141 | B769: 162333 | C769: 02978226242 | D769: 0002634941 | E769: FERNANDO SANTOS DO NASCIMENTO | F769: fs292997@gmail.com | H769: 35921 | I769: COLAB | J769: 5KM | K769: F | L769: G | M769: CB | N769: 129.9 | O769: INSCRITO | P769: Boa Vista
A770: 46142 | B770: 143700 | C770: 04407238259 | D770: 0003796375 | E770: CAROLAYNE SIMAS LINS | F770: carolaynesimas0@gmail.com | H770: 36392 | I770: GERAL | J770: 5KM | K770: M | L770: P | M770: CB | N770: 129.9 | O770: INSCRITO | P770: Manaus
A771: 46149 | B771: 101342 | C771: 75268841220 | D771: 0002086293 | E771: CRISTIANE SOUZA MORAES | F771: crishotong@gmail.com | H771: 29904 | I771: GERAL | J771: 5KM | K771: M | L771: P | M771: PIX | N771: 129.9 | O771: INSCRITO | P771: Porto Velho
... A827: 46144 | B827: 074615 | C827: 93614934268 | D827: 0001232377 | E827: JULIANE RIBEIRO OLIVEIRA | F827: july_oliveira17@hotmail.com | H827: 32234 | I827: GERAL | J827: 5KM | K827: M | L827: M | M827: CB | N827: 149.9 | O827: INSCRITO | P827: Manaus
A828: 46143 | B828: 165215 | C828: 49518909253 | D828: 0001914237 | E828: MARCIA CRISTINA PORTELA DE MESQUITA | F828: marcia.portela@ac.gov.br | H828: 39573 | J828: 5KM | K828: M | L828: M | M828: PIX | N828: 149.9 | O828: INSCRITO | P828: Rio Branco
A829: 46146 | B829: 151118 | C829: 03878154224 | D829: 0003045133 | E829: JACIRA NASCIMENTO DA SILVA | F829: nekaperola@gmail.com | H829: 34613 | I829: GERAL | J829: 10KM | K829: M | L829: M | M829: CB | N829: 149.9 | O829: INSCRITO | P829: Manaus
A830: 46142 | B830: 110309 | C830: 91217865268 | D830: 0002226452 | E830: JACKSON CARLOS MENEZES PESTANA | F830: jkpestana@gmail.com | H830: 32096 | I830: GERAL | J830: 10KM | K830: F | L830: G | M830: PIX | N830: 129.9 | O830: INSCRITO | P830: Manaus
A831: 46140 | B831: 140646 | C831: 69994870220 | D831: 0001655677 | E831: BRUNO MONTENEGRO BENNESBY | F831: brunobennesby@hotmail.com | H831: 29795 | I831: GERAL | J831: 5KM | K831: F | L831: G | M831: CB | N831: 129.9 | O831: INSCRITO | P831: Porto Velho
A832: 46140 | B832: 201013 | C832: 67885080200 | D832: 0001754794 | E832: PATRICIA FARIA SQUINELLO | F832: patriciasquinello@gmail.com | H832: 39570 | I832: GERAL | J832: 10KM | K832: M | L832: P | M832: PIX | N832: 149.9 | O832: INSCRITO | P832: Rio Branco
A833: 46146 | B833: 224915 | C833: 62400444234 | D833: 0002762259 | E833: MARIA JULIA SOUZA DA SILVEIRA | F833: jenniferdasilveira8@gmail.com | H833: 27535 | I833: GERAL | J833: 10KM | K833: M | L833: P | M833: CB | N833: 149.9 | O833: INSCRITO | P833: Rio Branco
A834: 46142 | B834: 183703 | C834: 52095401204 | D834: 0001144182 | E834: ROZENILDA BARBOSA RODRIGUES | F834: rozenildamilda@gmail.com | H834: 28971 | I834: GERAL | J834: 5KM | K834: M | L834: P | M834: CB | N834: 129.9 | O834: INSCRITO | P834: Manaus
A835: 46142 | B835: 183034 | C835: 02421182247 | D835: 0003576139 | E835: LUAN RODRIGO ARRAS VASQUEZ | F835: luanr69@gmail.com | H835: 35420 | I835: GERAL | J835: 10KM | K835: F | L835: G | M835: CB | N835: 149.9 | O835: INSCRITO | P835: Porto Velho
A836: 46142 | B836: 202005 | C836: 99059312287 | D836: 0003034726 | E836: FATIMA DOS SANTOS COSTA | F836: fatymacoostaa@gmail.com | H836: 32254 | I836: GERAL | J836: 5KM | K836: M | L836: PP | M836: PIX | N836: 129.9 | O836: INSCRITO | P836: Manaus
A837: 46144 | B837: 125219 | C837: 33698716372 | D837: 0001045914 | E837: HONORATO DA SILVA OLIVEIRA | F837: nato.oliveira@gmail.com | H837: 25559 | I837: GERAL | J837: 5KM | K837: M | L837: G | M837: CB | N837: 129.9 | O837: INSCRITO | P837: Manaus
A838: 46140 | B838: 152444 | C838: 70427304296 | D838: 0002992300 | E838: JOAO VICTOR PARINTINS FARIAS | F838: jvparintins@gmail.com | H838: 36858 | I838: GERAL | J838: 5KM | K838: F | L838: P | M838: CB | N838: 129.9 | O838: INSCRITO | P838: Manaus
A839: 46143 | B839: 164701 | C839: 02792853298 | D839: 0003018098 | E839: LETICIA DA SILVA RODRIGUES | F839: leticiadasilvarodrigues00@gmail.com | H839: 36655 | I839: COLAB | J839: 5KM | K839: M | L839: M | M839: CB | N839: 129.9 | O839: INSCRITO | P839: Manaus
A840: 46145 | B840: 114527 | C840: 66523141268 | D840: 0001064545 | E840: CARLA GEOVANA CARVALHO DE OLIVEIRA | F840: cgeovana@gmail.com | H840: 29593 | I840: GERAL | J840: 5KM | K840: M | L840: P | M840: CB | N840: 149.9 | O840: INSCRITO | P840: Porto Velho
... A1095: 46143 | B1095: 214005 | C1095: 00856122270 | D1095: 0002037800 | E1095: LUIZ EDUARDO CAMOLEZI RAFAEL CAMPOS | F1095: eduardocamolezi@hotmail.com | H1095: 32797 | I1095: GERAL | J1095: 10KM | K1095: F | L1095: M | M1095: CB | N1095: 129.9 | O1095: INSCRITO | P1095: Manaus
A1096: 46148 | B1096: 162507 | C1096: 70353050253 | D1096: 0004691752 | E1096: DAVI FEITOZA MILLER | F1096: davimiller3941@gmail.com | H1096: 29539 | J1096: 5KM | K1096: M | L1096: XG | M1096: CB | N1096: 129.9 | O1096: INSCRITO | P1096: Rio Branco
A1097: 46141 | B1097: 212301 | C1097: 02342654260 | D1097: 0004613306 | E1097: CAMILA DA SILVA SANTOS | F1097: CAMILABIOMED1994@GMAIL.COM | H1097: 34636 | I1097: GERAL | J1097: 10KM | K1097: M | L1097: PP | M1097: CB | N1097: 149.9 | O1097: INSCRITO | P1097: Rio Branco
A1098: 46143 | B1098: 153603 | C1098: 80589855204 | D1098: 0003198117 | E1098: PATERSON ANUNCIACAO PRADO | F1098: patersonaprado@gmail.com | H1098: 34725 | I1098: GERAL | J1098: 5KM | K1098: F | L1098: G | M1098: CB | N1098: 149.9 | O1098: INSCRITO | P1098: Manaus
A1099: 46142 | B1099: 183409 | C1099: 43948871272 | D1099: 0000298216 | E1099: JARLES PEREIRA DOS SANTOS | F1099: jarles_pereira@outlook.com | H1099: 27248 | I1099: COLAB | J1099: 5KM | K1099: F | L1099: M | M1099: CB | N1099: 129.9 | O1099: INSCRITO | P1099: Manaus
A1100: 46141 | B1100: 104622 | C1100: 00547647263 | D1100: 0001961890 | E1100: ADRYAN JOANA DA COSTA E SILVA | F1100: matheusoliveira11@gmail.com | H1100: 32671 | I1100: GERAL | J1100: 5KM | K1100: M | L1100: M | M1100: PIX | N1100: 129.9 | O1100: INSCRITO | P1100: Manaus
A1101: 46140 | B1101: 175635 | C1101: 01747958239 | D1101: 0001857614 | E1101: THIAGO OLIVEIRA DA SILVA | F1101: thiago_xd17_15@hotmail.com | H1101: 32401 | I1101: GERAL | J1101: 5KM | K1101: F | L1101: P | M1101: CB | N1101: 129.9 | O1101: INSCRITO | P1101: Manaus
A1102: 46147 | B1102: 150247 | C1102: 02774590280 | D1102: 0002500099 | E1102: LEONARDO VIEIRA PRESTES | F1102: leonardo.vieiraprestes@facebook.com | H1102: 35517 | I1102: GERAL | J1102: 5KM | K1102: F | L1102: GG | M1102: CB | N1102: 149.9 | O1102: INSCRITO | P1102: Porto Velho
A1103: 46140 | B1103: 165158 | C1103: 65921194204 | D1103: 0003744160 | E1103: LEILA LOPES ROCHA | F1103: leilalr23@gmail.com | H1103: 29387 | I1103: GERAL | J1103: 5KM | K1103: M | L1103: P | M1103: CB | N1103: 129.9 | O1103: INSCRITO | P1103: Rio Branco
A1104: 46143 | B1104: 182433 | C1104: 45670226291 | D1104: 0001603740 | E1104: TEREZA BEZERRA BARROSO | F1104: ccleiciagomes@yahoo.com.br | H1104: 16103 | I1104: GERAL | J1104: 5KM | K1104: M | L1104: G | M1104: CB | N1104: 74.95 | O1104: INSCRITO | P1104: Manaus
A1105: 46141 | B1105: 113014 | C1105: 06730111275 | D1105: 0006016871 | E1105: THIAGO KAUA DE SOUZA BRAGA | F1105: kauadesouzabragat@gmail.com | H1105: 38922 | I1105: GERAL | J1105: 5KM | K1105: F | L1105: P | M1105: CB | N1105: 149.9 | O1105: INSCRITO | P1105: Porto Velho
A1106: 46143 | B1106: 114548 | C1106: 02026510296 | D1106: 0002363674 | E1106: DAIANA MACARIO DA SILVA | F1106: day_macario@hotmail.com | H1106: 34652 | I1106: GERAL | J1106: 5KM | K1106: M | L1106: M | M1106: CB | N1106: 129.9 | O1106: INSCRITO | P1106: Manaus
A1107: 46143 | B1107: 104328 | C1107: 61678961272 | D1107: 0004084951 | E1107: BRUNA FERNANDA SOARES STOCHI COLFER | F1107: brunafernandastochi@gmail.com | H1107: 29119 | I1107: GERAL | J1107: 5KM | K1107: M | L1107: PP | M1107: CB | N1107: 149.9 | O1107: INSCRITO | P1107: Porto Velho
A1108: 46142 | B1108: 175955 | C1108: 70806896272 | D1108: 0001289467 | E1108: SILVIA KARLA DA SILVA COSTA | F1108: silviakarla@gmail.com | H1108: 29510 | I1108: GERAL | J1108: 5KM | K1108: M | L1108: G | M1108: CB | N1108: 129.9 | O1108: INSCRITO | P1108: Manaus
... A1259: 46140 | B1259: 163330 | C1259: 77151593287 | D1259: 0001206612 | E1259: CLEIDILENE FERREIRA LIMA | F1259: lene_lenin@hotmail.com | H1259: 30778 | I1259: GERAL | J1259: 5KM | K1259: M | L1259: PP | M1259: CB | N1259: 149.9 | O1259: INSCRITO | P1259: Porto Velho
A1260: 46142 | B1260: 155649 | C1260: 52342859287 | D1260: 0002346231 | E1260: FRANK THIENY BRITO DE LIMA | F1260: frankthieny@bol.com.br | H1260: 31244 | J1260: 5KM | K1260: M | L1260: XG | M1260: CB | N1260: 149.9 | O1260: INSCRITO | P1260: Rio Branco
A1261: 46143 | B1261: 104107 | C1261: 66634318204 | D1261: 0001452477 | E1261: ARISTEU FERREIRA DOS SANTOS FILHO | F1261: aristeusantos01@gmail.com | H1261: 29715 | I1261: GERAL | J1261: 5KM | K1261: F | L1261: G | M1261: CB | N1261: 129.9 | O1261: INSCRITO | P1261: Manaus
A1262: 46141 | B1262: 120158 | C1262: 02182274260 | D1262: 0002682146 | E1262: TARCISIO CALADO DA SILVA | F1262: tarcisio_mc2@hotmail.com | H1262: 35812 | I1262: GERAL | J1262: 10KM | K1262: F | L1262: M | M1262: CB | N1262: 149.9 | O1262: INSCRITO | P1262: Porto Velho
A1263: 46140 | B1263: 185515 | C1263: 78635454200 | D1263: 0001359566 | E1263: ELLEN PERES DA ROCHA | F1263: ellen_mikael@hotmail.com | H1263: 31000 | I1263: GERAL | J1263: 5KM | K1263: M | L1263: M | M1263: CB | N1263: 129.9 | O1263: INSCRITO | P1263: Manaus
A1264: 46141 | B1264: 081242 | C1264: 02161215230 | D1264: 0001952476 | E1264: REBECA MOTA DE MORAES | F1264: rebecamoraes25@gmail.com | H1264: 34844 | I1264: GERAL | J1264: 5KM | K1264: M | L1264: M | M1264: CB | N1264: 129.9 | O1264: INSCRITO | P1264: Manaus
A1265: 46142 | B1265: 134023 | C1265: 67283306234 | D1265: 0001007360 | E1265: KATIA ALVES TORRES | F1265: katiaalvestorres@gmail.com | H1265: 29679 | I1265: GERAL | J1265: 5KM | K1265: M | L1265: P | M1265: CB | N1265: 129.9 | O1265: INSCRITO | P1265: Manaus
A1266: 46140 | B1266: 175529 | C1266: 27449068249 | D1266: 0003075962 | E1266: ROSANIA MAIA DE ALMEIDA | F1266: rosaniamaia1@gmail.com | H1266: 24661 | I1266: GERAL | J1266: 5KM | K1266: M | L1266: P | M1266: CB | N1266: 149.9 | O1266: INSCRITO | P1266: Manaus
A1267: 46141 | B1267: 100836 | C1267: 70968596240 | D1267: 0004163883 | E1267: RHOIZA RAIZA BONILLO ALFONZO | F1267: rhoiboni@gmail.com | H1267: 31685 | I1267: GERAL | J1267: 5KM | K1267: M | L1267: M | M1267: CB | N1267: 129.9 | O1267: INSCRITO | P1267: Manaus
A1268: 46147 | B1268: 092043 | C1268: 78965055253 | D1268: 0001107970 | E1268: GILMAR MATHEUS DE JESUS | F1268: ramlig_matheus@hotmail.com | H1268: 31024 | I1268: GERAL | J1268: 10KM | K1268: F | L1268: G | M1268: CB | N1268: 149.9 | O1268: INSCRITO | P1268: Manaus
A1269: 46140 | B1269: 143251 | C1269: 00759633290 | D1269: 0001361657 | E1269: HELOISA DE LIMA COSTA | F1269: heloisa.costa@orientnet.com | H1269: 33248 | I1269: GERAL | J1269: 5KM | K1269: M | L1269: M | M1269: CB | N1269: 129.9 | O1269: INSCRITO | P1269: Manaus
A1270: 46142 | B1270: 203551 | C1270: 38461447204 | D1270: 0001144379 | E1270: HENRIQUE CESAR SILVA ARAUJO | F1270: henriquearaujoth@uol.com.br | H1270: 26404 | I1270: GERAL | J1270: 5KM | K1270: F | L1270: G | M1270: PIX | N1270: 129.9 | O1270: INSCRITO | P1270: Manaus
A1271: 46141 | B1271: 130855 | C1271: 00944996248 | D1271: 0002349460 | E1271: KAROLINE DO NASCIMENTO ROQUE | F1271: karol-roque1@hotmail.com | H1271: 33309 | I1271: GERAL | J1271: 5KM | K1271: M | L1271: G | M1271: PIX | N1271: 149.9 | O1271: INSCRITO | P1271: Manaus
A1272: 46144 | B1272: 193641 | C1272: 04631025255 | D1272: 0005109007 | E1272: LAIS LIMA FREITAS | F1272: laislima422@gmail.com | H1272: 36847 | I1272: GERAL | J1272: 5KM | K1272: M | L1272: P | M1272: PIX | N1272: 149.9 | O1272: INSCRITO | P1272: Porto Velho
... A1380: 46143 | B1380: 211702 | C1380: 70541945270 | D1380: 0005070996 | E1380: STHEFANY RICARDO DE SOUZA | F1380: sthefanyricardo.am@gmail.com | H1380: 38621 | I1380: GERAL | J1380: 10KM | K1380: M | L1380: P | M1380: CB | N1380: 129.9 | O1380: INSCRITO | P1380: Manaus
A1381: 46147 | B1381: 112151 | C1381: 00240554256 | D1381: 0001738594 | E1381: JONATHAN ARAUJO WEBER | F1381: jonathanwebera@gmail.com | H1381: 33637 | J1381: 5KM | K1381: M | L1381: G | M1381: CB | N1381: 129.9 | O1381: INSCRITO | P1381: Rio Branco
A1382: 46140 | B1382: 142036 | C1382: 00862660203 | D1382: 0002531642 | E1382: FLAVIA DA SILVA NEVES | F1382: flaviakimberly7@gmail.com | H1382: 32848 | I1382: GERAL | J1382: 5KM | K1382: M | L1382: PP | M1382: CB | N1382: 129.9 | O1382: INSCRITO | P1382: Manaus
A1383: 46142 | B1383: 150907 | C1383: 15966840709 | D1383: 0004776971 | E1383: LEONARDO DUARTE PEREIRA | F1383: Leonardodupe@gmail.com | H1383: 35378 | I1383: COLAB | J1383: 5KM | K1383: F | L1383: G | M1383: CB | N1383: 129.9 | O1383: INSCRITO | P1383: Porto Velho
A1384: 46146 | B1384: 081346 | C1384: 84426845220 | D1384: 0001957282 | E1384: MARCELA FERREIRA GOMES | F1384: naty_fgomes@hotmail.com | H1384: 31152 | I1384: GERAL | J1384: 10KM | K1384: M | L1384: PP | M1384: PIX | N1384: 149.9 | O1384: INSCRITO | P1384: Boa Vista
A1385: 46140 | B1385: 141859 | C1385: 03698834200 | D1385: 0002656502 | E1385: PEDRO EDUARDO ALEXANDRIA BOTELHO | F1385: pedroedua27@gmail.com | H1385: 36734 | I1385: GERAL | J1385: 5KM | K1385: F | L1385: M | M1385: CB | N1385: 149.9 | O1385: INSCRITO | P1385: Porto Velho
A1386: 46142 | B1386: 120843 | C1386: 34252649234 | D1386: 0000244885 | E1386: ESTELA PEREIRA BARRETO GARCES | F1386: epbg-esrelagarces@hotmail.com | H1386: 25944 | I1386: GERAL | J1386: 5KM | K1386: M | L1386: PP | M1386: CB | N1386: 129.9 | O1386: INSCRITO | P1386: Manaus
A1387: 46142 | B1387: 183616 | C1387: 00759762260 | D1387: 0001926957 | E1387: IASCARA GUIMARAES RIBEIRO | F1387: iascaragr@gmail.com | H1387: 33492 | I1387: GERAL | J1387: 5KM | K1387: M | L1387: P | M1387: CB | N1387: 149.9 | O1387: INSCRITO | P1387: Porto Velho
A1388: 46140 | B1388: 193231 | C1388: 43900470278 | D1388: 0000297476 | E1388: ELISANGELA BARROS | F1388: lys.barros04@gmail.com | H1388: 39570 | I1388: GERAL | J1388: 5KM | K1388: M | L1388: P | M1388: CB | N1388: 149.9 | O1388: INSCRITO | P1388: Manaus
A1389: 46144 | B1389: 092611 | C1389: 79143598234 | D1389: 0002045348 | E1389: ANTONIA MARYLAURA LIMA DE OLIVEIRA | F1389: guerreira.icamiaba@gmail.com | H1389: 31051 | I1389: GERAL | J1389: 10KM | K1389: M | L1389: P | M1389: PIX | N1389: 149.9 | O1389: INSCRITO | P1389: Manaus
A1390: 46141 | B1390: 113134 | C1390: 02235104240 | D1390: 0003900541 | E1390: JOSIENE LEITE DE SOUZA | F1390: jo.leite2025@gmail.com | H1390: 35753 | I1390: COLAB | J1390: 10KM | K1390: M | L1390: M | M1390: CB | N1390: 129.9 | O1390: INSCRITO | P1390: Manaus
A1391: 46145 | B1391: 103115 | C1391: 78556384234 | D1391: 0001709972 | E1391: RUTH CAMPOS DOS SANTOS | F1391: ruthcampos4@hotmail.com | H1391: 30959 | I1391: GERAL | J1391: 10KM | K1391: F | L1391: M | M1391: PIX | N1391: 129.9 | O1391: INSCRITO | P1391: Manaus
A1392: 46142 | B1392: 135739 | C1392: 88144429249 | D1392: 0001839193 | E1392: VINICIUS VIEIRA MORAES | F1392: vv.moraes@yahoo.com.br | H1392: 34689 | I1392: GERAL | J1392: 5KM | K1392: F | L1392: GG | M1392: CB | N1392: 129.9 | O1392: INSCRITO | P1392: Manaus
A1393: 46140 | B1393: 140910 | C1393: 93621787291 | D1393: 0002451168 | E1393: INGRID SILVA DE SAO B OLIVEIRA | F1393: Ingrid.ssbernardo@gmail.com | H1393: 32350 | I1393: GERAL | J1393: 5KM | K1393: M | L1393: GG | M1393: CB | N1393: 129.9 | O1393: INSCRITO | P1393: Manaus
... A1773: 46141 | B1773: 192553 | C1773: 03255248230 | D1773: 0003028360 | E1773: VITORIA RAIANE PERES DA SILVA LIMA | F1773: vraiane268@gmail.com | H1773: 36076 | I1773: COLAB | J1773: 5KM | K1773: F | L1773: P | M1773: CB | N1773: 129.9 | O1773: INSCRITO | P1773: Manaus
A1774: 46150 | B1774: 122315 | C1774: 69668124200 | D1774: 0003257692 | E1774: DEYSEANE SILVA DE ARRUDA | F1774: deysearruda_rr@hotmail.com | H1774: 30090 | J1774: 5KM | K1774: M | L1774: P | M1774: PIX | N1774: 149.9 | O1774: INSCRITO | P1774: Boa Vista
A1775: 46154 | B1775: 125023 | C1775: 27525228353 | D1775: 0001702794 | E1775: JOSE ALEXANDRE DA SILVA | F1775: josealexand@bol.com.br | H1775: 25515 | I1775: GERAL | J1775: 10KM | K1775: M | L1775: P | M1775: PIX | N1775: 149.9 | O1775: INSCRITO | P1775: Porto Velho
A1776: 46144 | B1776: 130230 | C1776: 32323875272 | D1776: 0002496012 | E1776: ELINALDA DA SILVA OLIVEIRA | F1776: elinaldaoliveira.adv@gmail.com | H1776: 27393 | I1776: GERAL | J1776: 5KM | K1776: F | L1776: P | M1776: CB | N1776: 149.9 | O1776: INSCRITO | P1776: Boa Vista
A1777: 46140 | B1777: 144410 | C1777: 00984104151 | D1777: 0002248723 | E1777: ALINE DO SOCORRO DE SOUSA ARRAIS | F1777: alinesouzaarrais@gmail.com | H1777: 29543 | I1777: GERAL | J1777: 5KM | K1777: F | L1777: P | M1777: CB | N1777: 129.9 | O1777: INSCRITO | P1777: Manaus
A1778: 46142 | B1778: 101246 | C1778: 01392291240 | D1778: 0002285138 | E1778: GEANDERSON DUARTE DUTRA | F1778: geanderson.duarte@hotmail.com | H1778: 34022 | I1778: GERAL | J1778: 5KM | K1778: M | L1778: XG | M1778: PIX | N1778: 129.9 | O1778: INSCRITO | P1778: Manaus
A1779: 46166 | B1779: 134736 | C1779: 60038667215 | D1779: 0001146706 | E1779: CACIANO DE ARAUJO FERRAZ | F1779: cacianoferraz@gmail.com | H1779: 29064 | I1779: GERAL | J1779: 10KM | K1779: M | L1779: M | M1779: CB | N1779: 149.9 | O1779: INSCRITO | P1779: Porto Velho
A1780: 46154 | B1780: 015402 | C1780: 3436210293 | D1780: 0003957225 | E1780: RAFAELA DE ARAUJO WICIUK | F1780: rafaelawiciuk@gmail.com | H1780: 37005 | I1780: GERAL | J1780: 5KM | K1780: F | L1780: P | M1780: CB | N1780: 149.9 | O1780: INSCRITO | P1780: Rio Branco
A1781: 46141 | B1781: 191202 | C1781: 00190038209 | D1781: 0002418994 | E1781: ELAINE FLAVIANE NORONHA DA SILVA | F1781: elaineflaviane@gmail.com | H1781: 32059 | I1781: GERAL | J1781: 5KM | K1781: F | L1781: M | M1781: CB | N1781: 129.9 | O1781: INSCRITO | P1781: Manaus
A1782: 46146 | B1782: 190214 | C1782: 31076785204 | D1782: 0001172336 | E1782: SANDRA ELIANA PRAXEDES DA COSTA | F1782: sandra.praxedes3@gmail.com | H1782: 24953 | I1782: GERAL | J1782: 10KM | K1782: F | L1782: M | M1782: CB | N1782: 129.9 | O1782: INSCRITO | P1782: Manaus
A1783: 46140 | B1783: 181432 | C1783: 03975389281 | D1783: 0002417320 | E1783: KALLEY RAMON FIGUEIREDO DE SOUSA | F1783: kalley.ramon@gmail.com | H1783: 35848 | I1783: GERAL | J1783: 5KM | K1783: M | L1783: G | M1783: PIX | N1783: 129.9 | O1783: INSCRITO | P1783: Manaus
A1784: 46141 | B1784: 104622 | C1784: 00547647263 | D1784: 0001961890 | E1784: ADRYAN JOANA DA COSTA E SILVA | F1784: matheusoliveira11@gmail.com | H1784: 32671 | I1784: GERAL | J1784: 5KM | K1784: F | L1784: M | M1784: PIX | N1784: 129.9 | O1784: INSCRITO | P1784: Manaus
A1785: 46140 | B1785: 152444 | C1785: 70427304296 | D1785: 0002992300 | E1785: JOAO VICTOR PARINTINS FARIAS | F1785: jvparintins@gmail.com | H1785: 36858 | I1785: GERAL | J1785: 5KM | K1785: M | L1785: P | M1785: CB | N1785: 129.9 | O1785: INSCRITO | P1785: Manaus
A1786: 46143 | B1786: 153727 | C1786: 72528680287 | D1786: 0001789609 | E1786: LILIANA DOS SANTOS CUSTODIO | F1786: luize.eduardo12345@hotmail.com | H1786: 30579 | I1786: GERAL | J1786: 5KM | K1786: F | L1786: P | M1786: CB | N1786: 149.9 | O1786: INSCRITO | P1786: Manaus
... A1975: 46142 | B1975: 223605 | C1975: 34807497200 | D1975: 0000198654 | E1975: RAIMUNDO ALUIZIO N DOS SANTOS | F1975: aluizio@dmarcos.com.br | H1975: 25730 | I1975: GERAL | J1975: 5KM | K1975: M | L1975: M | M1975: CB | N1975: 129.9 | O1975: INSCRITO | P1975: Manaus
A1976: 46169 | B1976: 034551 | C1976: 03401032216 | D1976: 0006071232 | E1976: RAIMUNDO ANDRADE PEREIRA NETO | F1976: np368995@gmail.com | H1976: 39463 | J1976: 5KM | K1976: F | L1976: G | M1976: CB | N1976: 149.9 | O1976: INSCRITO | P1976: Boa Vista
A1977: 46146 | B1977: 223637 | C1977: 94451931215 | D1977: 0003783194 | E1977: LUCAS DE MOURA FEITOSA | F1977: lucasmourafeitosa@hotmail.com | H1977: 31914 | I1977: GERAL | J1977: 10KM | K1977: M | L1977: M | M1977: CB | N1977: 149.9 | O1977: INSCRITO | P1977: Manaus
...

Sheet Chamados - Cortesia
A1: Email - Colaborador | B1: Nome Completo do Cliente | C1: CPF do Cliente | D1: Data do Contato | E1: N° do Pedido | F1: Qual o percurso do atleta no momento da inscrição? | G1: É PCD? | H1: Motivo do Contato1 | I1: Qual o novo percurso desejado? | J1: Qual o tamanho da camisa no momento da inscrição? | K1: Qual o tamanho da camisa desejado? | L1: Motivo do Contato | M1: Comentários Extras | N1: Coluna1 | O1: Coluna2
A2: shayenefreitas@bemol.com.br | B2: Nayra Alves da Silva | C2: 3789252298 | D2: 46140 | E2: 900000008111193 | G2: Não | H2: Troca de Camisa | J2: P | K2: M | N2: Pedido original: Camisa P; 5KM - Colaborador. Corrida Manaus | Q2: Foi definido no dia 04/05/2026 que esses casos iríamos atender para não gerar frustação no cliente. As camisas e percursos para esses clientes serão da Cortesia.
A3: danielpereira@bemol.com.br | B3: MARIA INES LIMA DA SILVA | C3: 27496759287 | D3: 46140 | E3: 900000006900203 | G3: Não | H3: Outro | L3: Blusa tamanho M Percurso 5km | N3: Pedido original: Camisa P; 10KM - Corrida Manaus
A4: raquelmatos@bemol.com.br | B4: LARISSA DOS SANTOS ALMEIDA ALVES | C4: 2993757229 | D4: 46140 | E4: 900000008113393 | G4: Não | H4: Outro | L4: Cliente não é PCD (escolheu PCD na inscrição), e gostaria de trocar categoria para público geral. whatsapp:+559291964130 | M4: Cliente cancelou o pedido
A5: cleidesilva@bemol.com.br | B5: KAROLINE DO NASCIMENTO ROQUE | C5: 944996248 | D5: 46141 | E5: 900000008116875 | G5: Não | H5: Troca de Camisa | J5: G | K5: PP | N5: Pedido Original: Camisa G; 5KM - Corrida Manaus
A6: mayaralima@bemol.com.br | B6: SAMEA REGINA CORREA MESQUITA | C6: 2993757229 | D6: 46141 | E6: 900000008117227 | G6: Não | H6: Troca de Camisa | J6: G | K6: P | M6: Cliente e contato solicita a troca do tamanho da sua camisa de G para P | N6: Pedido Original: Camisa G; 5KM - Corrida Manaus
A7: shayenefreitas@bemol.com.br | B7: ELEN ADRIANA MOUSINHO LEMOS | C7: 1345726295 | D7: 46142 | E7: 900000008115667 | G7: Não | H7: Troca de Camisa | J7: M | K7: PP | N7: Pedido original: Camisa M; 5KM - Colaborador. Corrida Manaus
A8: ednelsonpires@bemol.com.br | B8: GEOVANA DA SILVA MATOS | C8: 2270310241 | D8: 46142 | E8: 9e+15 | F8: 10km | G8: Não | H8: Troca de Percurso | I8: 5 km | N8: Pedido não encontrado
A9: ednelsonpires@bemol.com.br | B9: CARLOS DANIEL DE ALMEIDA PINTO | C9: 3295650284 | D9: 46142 | E9: 90000008111035 | F9: 10km | G9: Não | H9: Troca de Percurso | I9: 5 km | N9: Pedido não encontrado
A10: sabrinaviana@bemol.com.br | B10: HAROLDO JORGE DE SOUZA PANTOJA | C10: 60088737268 | D10: 46142 | E10: 900000008123033 | G10: Não | H10: Troca de Camisa | J10: M | K10: GG | M10: Cliente informa que no ato da inscrição, selecionou a opção GG e finalizou com a opção m. | N10: Pedido Original: Camisa M; 5KM - Geral. Corrida Manaus
A11: sabrinaviana@bemol.com.br | B11: RIBAMAR MACEDO DA SILVA | C11: 61454478268 | D11: 46142 | E11: 900000006826764 | G11: Não | H11: Troca de Camisa | J11: M | K11: G | M11: Vários clientes relatando que antes de finalizar a compra, já finaliza a inscrição com o tamanho da camisa errada. | N11: Pedido Original: Camisa M; 10KM - Geral. Corrida Manaus
A12: amandamagalhaes@bemol.com.br | B12: DAVI GOMES MATOS | C12: 70540878286 | D12: 46141 | E12: 900000008116859 | G12: Não | H12: Troca de Camisa | J12: G | K12: P | N12: Pedido Original: Camisa G; 5KM - Geral. Corrida Manaus
A13: rayanevales@bemol.com.br | B13: ALOM AIUDE DOS SANTOS | C13: 75848449287 | D13: 46144 | E13: 900000008116961 | G13: Não | H13: Troca de Camisa | J13: GG | K13: G | M13: Por gentileza realizar a alteração do tamanho da camisa conforme solicitação do cliente. Ctt: 92981649524 | N13: Pedido Original: Camisa GG; 10KM - Geral. Corrida Manaus
A14: anepriscila@bemol.com.br | B14: HERIBERTO WANDERLEY | C14: 1556524277 | D14: 46144 | E14: 12558982 | G14: Não | H14: Troca de Camisa | J14: GG | K14: G | N14: Pedido não encontrado
A15: luziasouza@bemol.com.br | B15: CAMILA MIRANDA COSTA | C15: 175728275 | D15: 46144 | E15: 900000008121883 | G15: Não | H15: Troca de Camisa | J15: M | K15: GG | M15: cliente nao se recorda qual tamanho escolheu, mas deseja que seja a GG | N15: Pedido Original: Camisa GG; 10KM - Geral. Corrida Manaus
A16: escarletsales@bemol.com.br | B16: KATHELLEN OLIVEIRA DA SILVA | C16: 5850699210 | D16: 46144 | E16: 900000008114677 | G16: Não | H16: Troca de Camisa | J16: M | K16: P | M16: Cliente optou por solicitar o Tamanho da Camisa M pois não havia disponibilidade Tamanho P / Por gentileza verificar a disponibilidade do tamanho desejado pela cliente. | N16: Pedido Original: Camisa M; 5KM- Geral. Corrida Manaus
A17: sulianamacedo@bemol.com.br | B17: TANIA MARIA MOTA GOMES | C17: 27245268215 | D17: 46142 | E17: 900000008124402 | F17: 5km | G17: Não | H17: Troca de Percurso | I17: 10 km | N17: Pedido Original: Camisa GG, 5KM - Geral; Corrida Porto Velho | O17: Está como M
A18: cleidesilva@bemol.com.br | B18: MAXLENE RODRIGUES ATAIDE | C18: 85875210206 | D18: 46146 | E18: 900000008112796 | F18: 10km | G18: Não | H18: Troca de Percurso | I18: 5 km | N18: Pedido Original: Camisa PP, 10KM - Geral; Corrida Porto Velho
A19: jennifersantos@bemol.com.br | B19: LAILSON PEREIRA B DIOGENES | C19: 94589046253 | D19: 46146 | E19: 900000008110624 | F19: 10km | G19: Não | H19: Troca de Percurso | I19: 5 km | N19: Pedido Original: Camisa G, 10KM - Geral; Corrida Porto Velho
A20: anafreitas@bemol.com.br | B20: EMMANUELLE DA SILVA DUARTE | C20: 78789451287 | D20: 46146 | E20: 900000008110654 | F20: 5km | G20: Não | H20: Troca de Percurso | I20: 10 km | M20: Cliente nos acionou informando que selecionou equivocadamente o percurso de 5km, no entanto, seria de 10km. TEL.: 92994303827 | N20: Pedido Original: Camisa PP, 5KM - Geral; Corrida Manaus
B21: DIEGO LEMOS DA SILVA | C21: 6096734243 | D21: 46141 | E21: 900000008110980 | F21: 5km | G21: Não | H21: Troca de Camisa | I21: 5km | J21: G | K21: M | N21: Pedido Original: Camisa G, 5KM - Geral; Corrida Manaus
